Workbook

Sheet Formulas
C2: Issue | D2: Issue (from treasury) | E2: Total | F2: Rank | I2: Buybacks | J2: Rank | M2: Tender offer | N2: Capital redemption | O2: Capital distribution | P2: TotaL
B3: {=_xlfn.UNIQUE(Issuance!D4:D65536)} -> Aberdeen Equity Income Trust | C3: =SUMIFS(Issuance!$H:$H,Issuance!$D:$D,Formulas!$B3,Issuance!$C:$C,Formulas!C$2) -> 9.7169819 | D3: =SUMIFS(Issuance!$H:$H,Issuance!$D:$D,Formulas!$B3,Issuance!$C:$C,Formulas!D$2) -> 0.62175 | E3: =SUM(C3:D3) -> 10.338732 | F3: =IF(OR(B3="",B3=0,E3=0),"",IF(COUNTIFS($E$3:$E$500,">"&E3,$E$3:$E$500,"<>0")+1<=20,COUNTIFS($E$3:$E$500,">"&E3,$E$3:$E$500,"<>0")+1,"")) | H3: {=_xlfn.UNIQUE(Buybacks!D4:D64390)} -> Aberdeen Asia Focus | I3: =SUMIFS(Buybacks!H:H,Buybacks!D:D,Formulas!H3) -> -16.649146 | J3: =IF(OR(H3="",H3=0,I3=0),"",IF(COUNTIFS($I$3:$I$500,"<"&I3,$I$3:$I$500,"<>0")+1<=20,COUNTIFS($I$3:$I$500,"<"&I3,$I$3:$I$500,"<>0")+1,"")) | L3: {=_xlfn.UNIQUE('Corporate activity'!D4:D65536)} -> Aquila European Renewables | M3: =SUMIFS('Corporate activity'!$H:$H,'Corporate activity'!$D:$D,Formulas!$L3,'Corporate activity'!$C:$C,Formulas!M$2) -> 0 | N3: =SUMIFS('Corporate activity'!$H:$H,'Corporate activity'!$D:$D,Formulas!$L3,'Corporate activity'!$C:$C,Formulas!N$2) -> 0 | O3: =SUMIFS('Corporate activity'!$H:$H,'Corporate activity'!$D:$D,Formulas!$L3,'Corporate activity'!$C:$C,Formulas!O$2) -> -46.8 | P3: =SUM(M3:O3) -> -46.8 | Q3: =IF(OR(L3="",L3=0,P3=0),"",IF(COUNTIFS($P$3:$P$500,"<"&P3,$P$3:$P$500,"<>0")+1<=20,COUNTIFS($P$3:$P$500,"<"&P3,$P$3:$P$500,"<>0")+1,"")) -> 8
B4: Ashoka India Equity | C4: =SUMIFS(Issuance!$H:$H,Issuance!$D:$D,Formulas!$B4,Issuance!$C:$C,Formulas!C$2) -> 1.023525 | D4: =SUMIFS(Issuance!$H:$H,Issuance!$D:$D,Formulas!$B4,Issuance!$C:$C,Formulas!D$2) -> 0 | E4: =SUM(C4:D4) -> 1.023525 | F4: =IF(OR(B4="",B4=0,E4=0),"",IF(COUNTIFS($E$3:$E$500,">"&E4,$E$3:$E$500,"<>0")+1<=20,COUNTIFS($E$3:$E$500,">"&E4,$E$3:$E$500,"<>0")+1,"")) | H4: Aberdeen New India Investment Trust | I4: =SUMIFS(Buybacks!H:H,Buybacks!D:D,Formulas!H4) -> -13.104288 | J4: =IF(OR(H4="",H4=0,I4=0),"",IF(COUNTIFS($I$3:$I$500,"<"&I4,$I$3:$I$500,"<>0")+1<=20,COUNTIFS($I$3:$I$500,"<"&I4,$I$3:$I$500,"<>0")+1,"")) | L4: LMS Capital | M4: =SUMIFS('Corporate activity'!$H:$H,'Corporate activity'!$D:$D,Formulas!$L4,'Corporate activity'!$C:$C,Formulas!M$2) -> 0 | N4: =SUMIFS('Corporate activity'!$H:$H,'Corporate activity'!$D:$D,Formulas!$L4,'Corporate activity'!$C:$C,Formulas!N$2) -> 0 | O4: =SUMIFS('Corporate activity'!$H:$H,'Corporate activity'!$D:$D,Formulas!$L4,'Corporate activity'!$C:$C,Formulas!O$2) -> -1.614549 | P4: =SUM(M4:O4) -> -1.614549 | Q4: =IF(OR(L4="",L4=0,P4=0),"",IF(COUNTIFS($P$3:$P$500,"<"&P4,$P$3:$P$500,"<>0")+1<=20,COUNTIFS($P$3:$P$500,"<"&P4,$P$3:$P$500,"<>0")+1,""))
B5: Ashoka WhiteOak Emerging Markets | C5: =SUMIFS(Issuance!$H:$H,Issuance!$D:$D,Formulas!$B5,Issuance!$C:$C,Formulas!C$2) -> 6.1690169 | D5: =SUMIFS(Issuance!$H:$H,Issuance!$D:$D,Formulas!$B5,Issuance!$C:$C,Formulas!D$2) -> 0 | E5: =SUM(C5:D5) -> 6.1690169 | F5: =IF(OR(B5="",B5=0,E5=0),"",IF(COUNTIFS($E$3:$E$500,">"&E5,$E$3:$E$500,"<>0")+1<=20,COUNTIFS($E$3:$E$500,">"&E5,$E$3:$E$500,"<>0")+1,"")) | H5: Aberdeen UK Smaller Companies Growth | I5: =SUMIFS(Buybacks!H:H,Buybacks!D:D,Formulas!H5) -> -36.699984 | J5: =IF(OR(H5="",H5=0,I5=0),"",IF(COUNTIFS($I$3:$I$500,"<"&I5,$I$3:$I$500,"<>0")+1<=20,COUNTIFS($I$3:$I$500,"<"&I5,$I$3:$I$500,"<>0")+1,"")) | L5: Ashoka WhiteOak Emerging Markets | M5: =SUMIFS('Corporate activity'!$H:$H,'Corporate activity'!$D:$D,Formulas!$L5,'Corporate activity'!$C:$C,Formulas!M$2) -> 0 | N5: =SUMIFS('Corporate activity'!$H:$H,'Corporate activity'!$D:$D,Formulas!$L5,'Corporate activity'!$C:$C,Formulas!N$2) -> -0.137202 | O5: =SUMIFS('Corporate activity'!$H:$H,'Corporate activity'!$D:$D,Formulas!$L5,'Corporate activity'!$C:$C,Formulas!O$2) -> 0 | P5: =SUM(M5:O5) -> -0.137202 | Q5: =IF(OR(L5="",L5=0,P5=0),"",IF(COUNTIFS($P$3:$P$500,"<"&P5,$P$3:$P$500,"<>0")+1<=20,COUNTIFS($P$3:$P$500,"<"&P5,$P$3:$P$500,"<>0")+1,""))
B6: City of London Investment Trust | C6: =SUMIFS(Issuance!$H:$H,Issuance!$D:$D,Formulas!$B6,Issuance!$C:$C,Formulas!C$2) -> 63.3275 | D6: =SUMIFS(Issuance!$H:$H,Issuance!$D:$D,Formulas!$B6,Issuance!$C:$C,Formulas!D$2) -> 0 | E6: =SUM(C6:D6) -> 63.3275 | F6: =IF(OR(B6="",B6=0,E6=0),"",IF(COUNTIFS($E$3:$E$500,">"&E6,$E$3:$E$500,"<>0")+1<=20,COUNTIFS($E$3:$E$500,">"&E6,$E$3:$E$500,"<>0")+1,"")) -> 5 | H6: Aberforth Smaller Companies | I6: =SUMIFS(Buybacks!H:H,Buybacks!D:D,Formulas!H6) -> -43.30337 | J6: =IF(OR(H6="",H6=0,I6=0),"",IF(COUNTIFS($I$3:$I$500,"<"&I6,$I$3:$I$500,"<>0")+1<=20,COUNTIFS($I$3:$I$500,"<"&I6,$I$3:$I$500,"<>0")+1,"")) | L6: JPEL Private Equity | M6: =SUMIFS('Corporate activity'!$H:$H,'Corporate activity'!$D:$D,Formulas!$L6,'Corporate activity'!$C:$C,Formulas!M$2) -> 0 | N6: =SUMIFS('Corporate activity'!$H:$H,'Corporate activity'!$D:$D,Formulas!$L6,'Corporate activity'!$C:$C,Formulas!N$2) -> -4.461816 | O6: =SUMIFS('Corporate activity'!$H:$H,'Corporate activity'!$D:$D,Formulas!$L6,'Corporate activity'!$C:$C,Formulas!O$2) -> 0 | P6: =SUM(M6:O6) -> -4.461816 | Q6: =IF(OR(L6="",L6=0,P6=0),"",IF(COUNTIFS($P$3:$P$500,"<"&P6,$P$3:$P$500,"<>0")+1<=20,COUNTIFS($P$3:$P$500,"<"&P6,$P$3:$P$500,"<>0")+1,""))
B7: CQS New City High Yield Fund | C7: =SUMIFS(Issuance!$H:$H,Issuance!$D:$D,Formulas!$B7,Issuance!$C:$C,Formulas!C$2) -> 17.700425 | D7: =SUMIFS(Issuance!$H:$H,Issuance!$D:$D,Formulas!$B7,Issuance!$C:$C,Formulas!D$2) -> 0 | E7: =SUM(C7:D7) -> 17.700425 | F7: =IF(OR(B7="",B7=0,E7=0),"",IF(COUNTIFS($E$3:$E$500,">"&E7,$E$3:$E$500,"<>0")+1<=20,COUNTIFS($E$3:$E$500,">"&E7,$E$3:$E$500,"<>0")+1,"")) -> 16 | H7: Alliance Witan | I7: =SUMIFS(Buybacks!H:H,Buybacks!D:D,Formulas!H7) -> -141.56233 | J7: =IF(OR(H7="",H7=0,I7=0),"",IF(COUNTIFS($I$3:$I$500,"<"&I7,$I$3:$I$500,"<>0")+1<=20,COUNTIFS($I$3:$I$500,"<"&I7,$I$3:$I$500,"<>0")+1,"")) -> 7 | L7: Doric Nimrod Air Three | M7: =SUMIFS('Corporate activity'!$H:$H,'Corporate activity'!$D:$D,Formulas!$L7,'Corporate activity'!$C:$C,Formulas!M$2) -> 0 | N7: =SUMIFS('Corporate activity'!$H:$H,'Corporate activity'!$D:$D,Formulas!$L7,'Corporate activity'!$C:$C,Formulas!N$2) -> 0 | O7: =SUMIFS('Corporate activity'!$H:$H,'Corporate activity'!$D:$D,Formulas!$L7,'Corporate activity'!$C:$C,Formulas!O$2) -> 0 | P7: =SUM(M7:O7) -> 0 | Q7: =IF(OR(L7="",L7=0,P7=0),"",IF(COUNTIFS($P$3:$P$500,"<"&P7,$P$3:$P$500,"<>0")+1<=20,COUNTIFS($P$3:$P$500,"<"&P7,$P$3:$P$500,"<>0")+1,""))
B8: CT Global Managed Portfolio Growth | C8: =SUMIFS(Issuance!$H:$H,Issuance!$D:$D,Formulas!$B8,Issuance!$C:$C,Formulas!C$2) -> 0.549625 | D8: =SUMIFS(Issuance!$H:$H,Issuance!$D:$D,Formulas!$B8,Issuance!$C:$C,Formulas!D$2) -> 0.6055 | E8: =SUM(C8:D8) -> 1.155125 | F8: =IF(OR(B8="",B8=0,E8=0),"",IF(COUNTIFS($E$3:$E$500,">"&E8,$E$3:$E$500,"<>0")+1<=20,COUNTIFS($E$3:$E$500,">"&E8,$E$3:$E$500,"<>0")+1,"")) | H8: Allianz Technology Trust | I8: =SUMIFS(Buybacks!H:H,Buybacks!D:D,Formulas!H8) -> -160.62452 | J8: =IF(OR(H8="",H8=0,I8=0),"",IF(COUNTIFS($I$3:$I$500,"<"&I8,$I$3:$I$500,"<>0")+1<=20,COUNTIFS($I$3:$I$500,"<"&I8,$I$3:$I$500,"<>0")+1,"")) -> 3 | L8: PRS REIT | M8: =SUMIFS('Corporate activity'!$H:$H,'Corporate activity'!$D:$D,Formulas!$L8,'Corporate activity'!$C:$C,Formulas!M$2) -> 0 | N8: =SUMIFS('Corporate activity'!$H:$H,'Corporate activity'!$D:$D,Formulas!$L8,'Corporate activity'!$C:$C,Formulas!N$2) -> 0 | O8: =SUMIFS('Corporate activity'!$H:$H,'Corporate activity'!$D:$D,Formulas!$L8,'Corporate activity'!$C:$C,Formulas!O$2) -> 0 | P8: =SUM(M8:O8) -> 0 | Q8: =IF(OR(L8="",L8=0,P8=0),"",IF(COUNTIFS($P$3:$P$500,"<"&P8,$P$3:$P$500,"<>0")+1<=20,COUNTIFS($P$3:$P$500,"<"&P8,$P$3:$P$500,"<>0")+1,""))
B9: CT Global Managed Portfolio Income | C9: =SUMIFS(Issuance!$H:$H,Issuance!$D:$D,Formulas!$B9,Issuance!$C:$C,Formulas!C$2) -> 3.7655205 | D9: =SUMIFS(Issuance!$H:$H,Issuance!$D:$D,Formulas!$B9,Issuance!$C:$C,Formulas!D$2) -> 0 | E9: =SUM(C9:D9) -> 3.7655205 | F9: =IF(OR(B9="",B9=0,E9=0),"",IF(COUNTIFS($E$3:$E$500,">"&E9,$E$3:$E$500,"<>0")+1<=20,COUNTIFS($E$3:$E$500,">"&E9,$E$3:$E$500,"<>0")+1,"")) | H9: Artemis UK Future Leaders | I9: =SUMIFS(Buybacks!H:H,Buybacks!D:D,Formulas!H9) -> -2.6335214 | J9: =IF(OR(H9="",H9=0,I9=0),"",IF(COUNTIFS($I$3:$I$500,"<"&I9,$I$3:$I$500,"<>0")+1<=20,COUNTIFS($I$3:$I$500,"<"&I9,$I$3:$I$500,"<>0")+1,"")) | L9: Aberdeen Equity Income Trust | M9: =SUMIFS('Corporate activity'!$H:$H,'Corporate activity'!$D:$D,Formulas!$L9,'Corporate activity'!$C:$C,Formulas!M$2) -> 0 | N9: =SUMIFS('Corporate activity'!$H:$H,'Corporate activity'!$D:$D,Formulas!$L9,'Corporate activity'!$C:$C,Formulas!N$2) -> 0 | O9: =SUMIFS('Corporate activity'!$H:$H,'Corporate activity'!$D:$D,Formulas!$L9,'Corporate activity'!$C:$C,Formulas!O$2) -> 0 | P9: =SUM(M9:O9) -> 0 | Q9: =IF(OR(L9="",L9=0,P9=0),"",IF(COUNTIFS($P$3:$P$500,"<"&P9,$P$3:$P$500,"<>0")+1<=20,COUNTIFS($P$3:$P$500,"<"&P9,$P$3:$P$500,"<>0")+1,""))
B10: EJF Investments | C10: =SUMIFS(Issuance!$H:$H,Issuance!$D:$D,Formulas!$B10,Issuance!$C:$C,Formulas!C$2) -> 8.6486295 | D10: =SUMIFS(Issuance!$H:$H,Issuance!$D:$D,Formulas!$B10,Issuance!$C:$C,Formulas!D$2) -> 0 | E10: =SUM(C10:D10) -> 8.6486295 | F10: =IF(OR(B10="",B10=0,E10=0),"",IF(COUNTIFS($E$3:$E$500,">"&E10,$E$3:$E$500,"<>0")+1<=20,COUNTIFS($E$3:$E$500,">"&E10,$E$3:$E$500,"<>0")+1,"")) | H10: AVI Global Trust | I10: =SUMIFS(Buybacks!H:H,Buybacks!D:D,Formulas!H10) -> -40.507971 | J10: =IF(OR(H10="",H10=0,I10=0),"",IF(COUNTIFS($I$3:$I$500,"<"&I10,$I$3:$I$500,"<>0")+1<=20,COUNTIFS($I$3:$I$500,"<"&I10,$I$3:$I$500,"<>0")+1,"")) | L10: Athelney Trust | M10: =SUMIFS('Corporate activity'!$H:$H,'Corporate activity'!$D:$D,Formulas!$L10,'Corporate activity'!$C:$C,Formulas!M$2) -> 0 | N10: =SUMIFS('Corporate activity'!$H:$H,'Corporate activity'!$D:$D,Formulas!$L10,'Corporate activity'!$C:$C,Formulas!N$2) -> 0 | O10: =SUMIFS('Corporate activity'!$H:$H,'Corporate activity'!$D:$D,Formulas!$L10,'Corporate activity'!$C:$C,Formulas!O$2) -> 0 | P10: =SUM(M10:O10) -> 0 | Q10: =IF(OR(L10="",L10=0,P10=0),"",IF(COUNTIFS($P$3:$P$500,"<"&P10,$P$3:$P$500,"<>0")+1<=20,COUNTIFS($P$3:$P$500,"<"&P10,$P$3:$P$500,"<>0")+1,""))
B11: Henderson Far East Income | C11: =SUMIFS(Issuance!$H:$H,Issuance!$D:$D,Formulas!$B11,Issuance!$C:$C,Formulas!C$2) -> 90.027288 | D11: =SUMIFS(Issuance!$H:$H,Issuance!$D:$D,Formulas!$B11,Issuance!$C:$C,Formulas!D$2) -> 0 | E11: =SUM(C11:D11) -> 90.027288 | F11: =IF(OR(B11="",B11=0,E11=0),"",IF(COUNTIFS($E$3:$E$500,">"&E11,$E$3:$E$500,"<>0")+1<=20,COUNTIFS($E$3:$E$500,">"&E11,$E$3:$E$500,"<>0")+1,"")) -> 4 | H11: Baillie Gifford China Growth | I11: =SUMIFS(Buybacks!H:H,Buybacks!D:D,Formulas!H11) -> -9.4854534 | J11: =IF(OR(H11="",H11=0,I11=0),"",IF(COUNTIFS($I$3:$I$500,"<"&I11,$I$3:$I$500,"<>0")+1<=20,COUNTIFS($I$3:$I$500,"<"&I11,$I$3:$I$500,"<>0")+1,"")) | L11: Develop North | M11: =SUMIFS('Corporate activity'!$H:$H,'Corporate activity'!$D:$D,Formulas!$L11,'Corporate activity'!$C:$C,Formulas!M$2) -> 0 | N11: =SUMIFS('Corporate activity'!$H:$H,'Corporate activity'!$D:$D,Formulas!$L11,'Corporate activity'!$C:$C,Formulas!N$2) -> 0 | O11: =SUMIFS('Corporate activity'!$H:$H,'Corporate activity'!$D:$D,Formulas!$L11,'Corporate activity'!$C:$C,Formulas!O$2) -> 0 | P11: =SUM(M11:O11) -> 0 | Q11: =IF(OR(L11="",L11=0,P11=0),"",IF(COUNTIFS($P$3:$P$500,"<"&P11,$P$3:$P$500,"<>0")+1<=20,COUNTIFS($P$3:$P$500,"<"&P11,$P$3:$P$500,"<>0")+1,""))
B12: Invesco Bond Income Plus | C12: =SUMIFS(Issuance!$H:$H,Issuance!$D:$D,Formulas!$B12,Issuance!$C:$C,Formulas!C$2) -> 98.909156 | D12: =SUMIFS(Issuance!$H:$H,Issuance!$D:$D,Formulas!$B12,Issuance!$C:$C,Formulas!D$2) -> 0 | E12: =SUM(C12:D12) -> 98.909156 | F12: =IF(OR(B12="",B12=0,E12=0),"",IF(COUNTIFS($E$3:$E$500,">"&E12,$E$3:$E$500,"<>0")+1<=20,COUNTIFS($E$3:$E$500,">"&E12,$E$3:$E$500,"<>0")+1,"")) -> 3 | H12: Baillie Gifford European Growth | I12: =SUMIFS(Buybacks!H:H,Buybacks!D:D,Formulas!H12) -> -17.920472 | J12: =IF(OR(H12="",H12=0,I12=0),"",IF(COUNTIFS($I$3:$I$500,"<"&I12,$I$3:$I$500,"<>0")+1<=20,COUNTIFS($I$3:$I$500,"<"&I12,$I$3:$I$500,"<>0")+1,"")) | L12: Global Opportunities | M12: =SUMIFS('Corporate activity'!$H:$H,'Corporate activity'!$D:$D,Formulas!$L12,'Corporate activity'!$C:$C,Formulas!M$2) -> 0 | N12: =SUMIFS('Corporate activity'!$H:$H,'Corporate activity'!$D:$D,Formulas!$L12,'Corporate activity'!$C:$C,Formulas!N$2) -> 0 | O12: =SUMIFS('Corporate activity'!$H:$H,'Corporate activity'!$D:$D,Formulas!$L12,'Corporate activity'!$C:$C,Formulas!O$2) -> 0 | P12: =SUM(M12:O12) -> 0 | Q12: =IF(OR(L12="",L12=0,P12=0),"",IF(COUNTIFS($P$3:$P$500,"<"&P12,$P$3:$P$500,"<>0")+1<=20,COUNTIFS($P$3:$P$500,"<"&P12,$P$3:$P$500,"<>0")+1,""))
B13: M&G Credit Income | C13: =SUMIFS(Issuance!$H:$H,Issuance!$D:$D,Formulas!$B13,Issuance!$C:$C,Formulas!C$2) -> 6.9309 | D13: =SUMIFS(Issuance!$H:$H,Issuance!$D:$D,Formulas!$B13,Issuance!$C:$C,Formulas!D$2) -> 0.0932 | E13: =SUM(C13:D13) -> 7.0241 | F13: =IF(OR(B13="",B13=0,E13=0),"",IF(COUNTIFS($E$3:$E$500,">"&E13,$E$3:$E$500,"<>0")+1<=20,COUNTIFS($E$3:$E$500,">"&E13,$E$3:$E$500,"<>0")+1,"")) | H13: Baillie Gifford Japan Trust | I13: =SUMIFS(Buybacks!H:H,Buybacks!D:D,Formulas!H13) -> -97.394717 | J13: =IF(OR(H13="",H13=0,I13=0),"",IF(COUNTIFS($I$3:$I$500,"<"&I13,$I$3:$I$500,"<>0")+1<=20,COUNTIFS($I$3:$I$500,"<"&I13,$I$3:$I$500,"<>0")+1,"")) -> 11 | L13: Volta Finance | M13: =SUMIFS('Corporate activity'!$H:$H,'Corporate activity'!$D:$D,Formulas!$L13,'Corporate activity'!$C:$C,Formulas!M$2) -> 0 | N13: =SUMIFS('Corporate activity'!$H:$H,'Corporate activity'!$D:$D,Formulas!$L13,'Corporate activity'!$C:$C,Formulas!N$2) -> 0 | O13: =SUMIFS('Corporate activity'!$H:$H,'Corporate activity'!$D:$D,Formulas!$L13,'Corporate activity'!$C:$C,Formulas!O$2) -> 0 | P13: =SUM(M13:O13) -> 0 | Q13: =IF(OR(L13="",L13=0,P13=0),"",IF(COUNTIFS($P$3:$P$500,"<"&P13,$P$3:$P$500,"<>0")+1<=20,COUNTIFS($P$3:$P$500,"<"&P13,$P$3:$P$500,"<>0")+1,""))
B14: Odyssean Investment Trust | C14: =SUMIFS(Issuance!$H:$H,Issuance!$D:$D,Formulas!$B14,Issuance!$C:$C,Formulas!C$2) -> 12.324713 | D14: =SUMIFS(Issuance!$H:$H,Issuance!$D:$D,Formulas!$B14,Issuance!$C:$C,Formulas!D$2) -> 0 | E14: =SUM(C14:D14) -> 12.324713 | F14: =IF(OR(B14="",B14=0,E14=0),"",IF(COUNTIFS($E$3:$E$500,">"&E14,$E$3:$E$500,"<>0")+1<=20,COUNTIFS($E$3:$E$500,">"&E14,$E$3:$E$500,"<>0")+1,"")) -> 18 | H14: Baillie Gifford Shin Nippon | I14: =SUMIFS(Buybacks!H:H,Buybacks!D:D,Formulas!H14) -> -20.471347 | J14: =IF(OR(H14="",H14=0,I14=0),"",IF(COUNTIFS($I$3:$I$500,"<"&I14,$I$3:$I$500,"<>0")+1<=20,COUNTIFS($I$3:$I$500,"<"&I14,$I$3:$I$500,"<>0")+1,"")) | L14: N/A | M14: =SUMIFS('Corporate activity'!$H:$H,'Corporate activity'!$D:$D,Formulas!$L14,'Corporate activity'!$C:$C,Formulas!M$2) -> 0 | N14: =SUMIFS('Corporate activity'!$H:$H,'Corporate activity'!$D:$D,Formulas!$L14,'Corporate activity'!$C:$C,Formulas!N$2) -> 0 | O14: =SUMIFS('Corporate activity'!$H:$H,'Corporate activity'!$D:$D,Formulas!$L14,'Corporate activity'!$C:$C,Formulas!O$2) -> 0 | P14: =SUM(M14:O14) -> 0 | Q14: =IF(OR(L14="",L14=0,P14=0),"",IF(COUNTIFS($P$3:$P$500,"<"&P14,$P$3:$P$500,"<>0")+1<=20,COUNTIFS($P$3:$P$500,"<"&P14,$P$3:$P$500,"<>0")+1,""))
B15: Onward Opportunities | C15: =SUMIFS(Issuance!$H:$H,Issuance!$D:$D,Formulas!$B15,Issuance!$C:$C,Formulas!C$2) -> 6.0800468 | D15: =SUMIFS(Issuance!$H:$H,Issuance!$D:$D,Formulas!$B15,Issuance!$C:$C,Formulas!D$2) -> 0 | E15: =SUM(C15:D15) -> 6.0800468 | F15: =IF(OR(B15="",B15=0,E15=0),"",IF(COUNTIFS($E$3:$E$500,">"&E15,$E$3:$E$500,"<>0")+1<=20,COUNTIFS($E$3:$E$500,">"&E15,$E$3:$E$500,"<>0")+1,"")) | H15: Baillie Gifford UK Growth | I15: =SUMIFS(Buybacks!H:H,Buybacks!D:D,Formulas!H15) -> -18.535714 | J15: =IF(OR(H15="",H15=0,I15=0),"",IF(COUNTIFS($I$3:$I$500,"<"&I15,$I$3:$I$500,"<>0")+1<=20,COUNTIFS($I$3:$I$500,"<"&I15,$I$3:$I$500,"<>0")+1,"")) | L15: JPMorgan Global Emerging Markets Income | M15: =SUMIFS('Corporate activity'!$H:$H,'Corporate activity'!$D:$D,Formulas!$L15,'Corporate activity'!$C:$C,Formulas!M$2) -> 0 | N15: =SUMIFS('Corporate activity'!$H:$H,'Corporate activity'!$D:$D,Formulas!$L15,'Corporate activity'!$C:$C,Formulas!N$2) -> 0 | O15: =SUMIFS('Corporate activity'!$H:$H,'Corporate activity'!$D:$D,Formulas!$L15,'Corporate activity'!$C:$C,Formulas!O$2) -> 0 | P15: =SUM(M15:O15) -> 0 | Q15: =IF(OR(L15="",L15=0,P15=0),"",IF(COUNTIFS($P$3:$P$500,"<"&P15,$P$3:$P$500,"<>0")+1<=20,COUNTIFS($P$3:$P$500,"<"&P15,$P$3:$P$500,"<>0")+1,""))
... B49: BlackRock World Mining | C49: =SUMIFS(Issuance!$H:$H,Issuance!$D:$D,Formulas!$B49,Issuance!$C:$C,Formulas!C$2) -> 0 | D49: =SUMIFS(Issuance!$H:$H,Issuance!$D:$D,Formulas!$B49,Issuance!$C:$C,Formulas!D$2) -> 4.65128 | E49: =SUM(C49:D49) -> 4.65128 | F49: =IF(OR(B49="",B49=0,E49=0),"",IF(COUNTIFS($E$3:$E$500,">"&E49,$E$3:$E$500,"<>0")+1<=20,COUNTIFS($E$3:$E$500,">"&E49,$E$3:$E$500,"<>0")+1,"")) | H49: International Public Partnerships | I49: =SUMIFS(Buybacks!H:H,Buybacks!D:D,Formulas!H49) -> -28.869252 | J49: =IF(OR(H49="",H49=0,I49=0),"",IF(COUNTIFS($I$3:$I$500,"<"&I49,$I$3:$I$500,"<>0")+1<=20,COUNTIFS($I$3:$I$500,"<"&I49,$I$3:$I$500,"<>0")+1,"")) | L49: Schroder Japan Trust | M49: =SUMIFS('Corporate activity'!$H:$H,'Corporate activity'!$D:$D,Formulas!$L49,'Corporate activity'!$C:$C,Formulas!M$2) -> 0 | N49: =SUMIFS('Corporate activity'!$H:$H,'Corporate activity'!$D:$D,Formulas!$L49,'Corporate activity'!$C:$C,Formulas!N$2) -> 0 | O49: =SUMIFS('Corporate activity'!$H:$H,'Corporate activity'!$D:$D,Formulas!$L49,'Corporate activity'!$C:$C,Formulas!O$2) -> 0 | P49: =SUM(M49:O49) -> 0 | Q49: =IF(OR(L49="",L49=0,P49=0),"",IF(COUNTIFS($P$3:$P$500,"<"&P49,$P$3:$P$500,"<>0")+1<=20,COUNTIFS($P$3:$P$500,"<"&P49,$P$3:$P$500,"<>0")+1,""))
B50: 0 | C50: =SUMIFS(Issuance!$H:$H,Issuance!$D:$D,Formulas!$B50,Issuance!$C:$C,Formulas!C$2) -> 0 | D50: =SUMIFS(Issuance!$H:$H,Issuance!$D:$D,Formulas!$B50,Issuance!$C:$C,Formulas!D$2) -> 0 | E50: =SUM(C50:D50) -> 0 | F50: =IF(OR(B50="",B50=0,E50=0),"",IF(COUNTIFS($E$3:$E$500,">"&E50,$E$3:$E$500,"<>0")+1<=20,COUNTIFS($E$3:$E$500,">"&E50,$E$3:$E$500,"<>0")+1,"")) | H50: Invesco Asia Dragon Trust | I50: =SUMIFS(Buybacks!H:H,Buybacks!D:D,Formulas!H50) -> -22.123445 | J50: =IF(OR(H50="",H50=0,I50=0),"",IF(COUNTIFS($I$3:$I$500,"<"&I50,$I$3:$I$500,"<>0")+1<=20,COUNTIFS($I$3:$I$500,"<"&I50,$I$3:$I$500,"<>0")+1,"")) | L50: Cordiant Digital Infrastructure | M50: =SUMIFS('Corporate activity'!$H:$H,'Corporate activity'!$D:$D,Formulas!$L50,'Corporate activity'!$C:$C,Formulas!M$2) -> 0 | N50: =SUMIFS('Corporate activity'!$H:$H,'Corporate activity'!$D:$D,Formulas!$L50,'Corporate activity'!$C:$C,Formulas!N$2) -> 0 | O50: =SUMIFS('Corporate activity'!$H:$H,'Corporate activity'!$D:$D,Formulas!$L50,'Corporate activity'!$C:$C,Formulas!O$2) -> 0 | P50: =SUM(M50:O50) -> 0 | Q50: =IF(OR(L50="",L50=0,P50=0),"",IF(COUNTIFS($P$3:$P$500,"<"&P50,$P$3:$P$500,"<>0")+1<=20,COUNTIFS($P$3:$P$500,"<"&P50,$P$3:$P$500,"<>0")+1,""))
C51: =SUMIFS(Issuance!$H:$H,Issuance!$D:$D,Formulas!$B51,Issuance!$C:$C,Formulas!C$2) -> 0 | D51: =SUMIFS(Issuance!$H:$H,Issuance!$D:$D,Formulas!$B51,Issuance!$C:$C,Formulas!D$2) -> 0 | E51: =SUM(C51:D51) -> 0 | F51: =IF(OR(B51="",B51=0,E51=0),"",IF(COUNTIFS($E$3:$E$500,">"&E51,$E$3:$E$500,"<>0")+1<=20,COUNTIFS($E$3:$E$500,">"&E51,$E$3:$E$500,"<>0")+1,"")) | H51: JPEL Private Equity | I51: =SUMIFS(Buybacks!H:H,Buybacks!D:D,Formulas!H51) -> -4.4652025 | J51: =IF(OR(H51="",H51=0,I51=0),"",IF(COUNTIFS($I$3:$I$500,"<"&I51,$I$3:$I$500,"<>0")+1<=20,COUNTIFS($I$3:$I$500,"<"&I51,$I$3:$I$500,"<>0")+1,"")) | L51: Onward Opportunities | M51: =SUMIFS('Corporate activity'!$H:$H,'Corporate activity'!$D:$D,Formulas!$L51,'Corporate activity'!$C:$C,Formulas!M$2) -> 0 | N51: =SUMIFS('Corporate activity'!$H:$H,'Corporate activity'!$D:$D,Formulas!$L51,'Corporate activity'!$C:$C,Formulas!N$2) -> 0 | O51: =SUMIFS('Corporate activity'!$H:$H,'Corporate activity'!$D:$D,Formulas!$L51,'Corporate activity'!$C:$C,Formulas!O$2) -> 0 | P51: =SUM(M51:O51) -> 0 | Q51: =IF(OR(L51="",L51=0,P51=0),"",IF(COUNTIFS($P$3:$P$500,"<"&P51,$P$3:$P$500,"<>0")+1<=20,COUNTIFS($P$3:$P$500,"<"&P51,$P$3:$P$500,"<>0")+1,""))
C52: =SUMIFS(Issuance!$H:$H,Issuance!$D:$D,Formulas!$B52,Issuance!$C:$C,Formulas!C$2) -> 0 | D52: =SUMIFS(Issuance!$H:$H,Issuance!$D:$D,Formulas!$B52,Issuance!$C:$C,Formulas!D$2) -> 0 | E52: =SUM(C52:D52) -> 0 | F52: =IF(OR(B52="",B52=0,E52=0),"",IF(COUNTIFS($E$3:$E$500,">"&E52,$E$3:$E$500,"<>0")+1<=20,COUNTIFS($E$3:$E$500,">"&E52,$E$3:$E$500,"<>0")+1,"")) | H52: JPMorgan American | I52: =SUMIFS(Buybacks!H:H,Buybacks!D:D,Formulas!H52) -> -50.287901 | J52: =IF(OR(H52="",H52=0,I52=0),"",IF(COUNTIFS($I$3:$I$500,"<"&I52,$I$3:$I$500,"<>0")+1<=20,COUNTIFS($I$3:$I$500,"<"&I52,$I$3:$I$500,"<>0")+1,"")) | L52: Aquila Energy Efficiency | M52: =SUMIFS('Corporate activity'!$H:$H,'Corporate activity'!$D:$D,Formulas!$L52,'Corporate activity'!$C:$C,Formulas!M$2) -> 0 | N52: =SUMIFS('Corporate activity'!$H:$H,'Corporate activity'!$D:$D,Formulas!$L52,'Corporate activity'!$C:$C,Formulas!N$2) -> 0 | O52: =SUMIFS('Corporate activity'!$H:$H,'Corporate activity'!$D:$D,Formulas!$L52,'Corporate activity'!$C:$C,Formulas!O$2) -> 0 | P52: =SUM(M52:O52) -> 0 | Q52: =IF(OR(L52="",L52=0,P52=0),"",IF(COUNTIFS($P$3:$P$500,"<"&P52,$P$3:$P$500,"<>0")+1<=20,COUNTIFS($P$3:$P$500,"<"&P52,$P$3:$P$500,"<>0")+1,""))
C53: =SUMIFS(Issuance!$H:$H,Issuance!$D:$D,Formulas!$B53,Issuance!$C:$C,Formulas!C$2) -> 0 | D53: =SUMIFS(Issuance!$H:$H,Issuance!$D:$D,Formulas!$B53,Issuance!$C:$C,Formulas!D$2) -> 0 | E53: =SUM(C53:D53) -> 0 | F53: =IF(OR(B53="",B53=0,E53=0),"",IF(COUNTIFS($E$3:$E$500,">"&E53,$E$3:$E$500,"<>0")+1<=20,COUNTIFS($E$3:$E$500,">"&E53,$E$3:$E$500,"<>0")+1,"")) | H53: JPMorgan Emerging Markets Growth & Income | I53: =SUMIFS(Buybacks!H:H,Buybacks!D:D,Formulas!H53) -> -46.271991 | J53: =IF(OR(H53="",H53=0,I53=0),"",IF(COUNTIFS($I$3:$I$500,"<"&I53,$I$3:$I$500,"<>0")+1<=20,COUNTIFS($I$3:$I$500,"<"&I53,$I$3:$I$500,"<>0")+1,"")) | L53: Crystal Amber Fund | M53: =SUMIFS('Corporate activity'!$H:$H,'Corporate activity'!$D:$D,Formulas!$L53,'Corporate activity'!$C:$C,Formulas!M$2) -> 0 | N53: =SUMIFS('Corporate activity'!$H:$H,'Corporate activity'!$D:$D,Formulas!$L53,'Corporate activity'!$C:$C,Formulas!N$2) -> 0 | O53: =SUMIFS('Corporate activity'!$H:$H,'Corporate activity'!$D:$D,Formulas!$L53,'Corporate activity'!$C:$C,Formulas!O$2) -> 0 | P53: =SUM(M53:O53) -> 0 | Q53: =IF(OR(L53="",L53=0,P53=0),"",IF(COUNTIFS($P$3:$P$500,"<"&P53,$P$3:$P$500,"<>0")+1<=20,COUNTIFS($P$3:$P$500,"<"&P53,$P$3:$P$500,"<>0")+1,""))
C54: =SUMIFS(Issuance!$H:$H,Issuance!$D:$D,Formulas!$B54,Issuance!$C:$C,Formulas!C$2) -> 0 | D54: =SUMIFS(Issuance!$H:$H,Issuance!$D:$D,Formulas!$B54,Issuance!$C:$C,Formulas!D$2) -> 0 | E54: =SUM(C54:D54) -> 0 | F54: =IF(OR(B54="",B54=0,E54=0),"",IF(COUNTIFS($E$3:$E$500,">"&E54,$E$3:$E$500,"<>0")+1<=20,COUNTIFS($E$3:$E$500,">"&E54,$E$3:$E$500,"<>0")+1,"")) | H54: JPMorgan Global Growth & Income | I54: =SUMIFS(Buybacks!H:H,Buybacks!D:D,Formulas!H54) -> -88.062386 | J54: =IF(OR(H54="",H54=0,I54=0),"",IF(COUNTIFS($I$3:$I$500,"<"&I54,$I$3:$I$500,"<>0")+1<=20,COUNTIFS($I$3:$I$500,"<"&I54,$I$3:$I$500,"<>0")+1,"")) -> 14 | L54: BlackRock Smaller Companies | M54: =SUMIFS('Corporate activity'!$H:$H,'Corporate activity'!$D:$D,Formulas!$L54,'Corporate activity'!$C:$C,Formulas!M$2) -> -162.91717 | N54: =SUMIFS('Corporate activity'!$H:$H,'Corporate activity'!$D:$D,Formulas!$L54,'Corporate activity'!$C:$C,Formulas!N$2) -> 0 | O54: =SUMIFS('Corporate activity'!$H:$H,'Corporate activity'!$D:$D,Formulas!$L54,'Corporate activity'!$C:$C,Formulas!O$2) -> 0 | P54: =SUM(M54:O54) -> -162.91717 | Q54: =IF(OR(L54="",L54=0,P54=0),"",IF(COUNTIFS($P$3:$P$500,"<"&P54,$P$3:$P$500,"<>0")+1<=20,COUNTIFS($P$3:$P$500,"<"&P54,$P$3:$P$500,"<>0")+1,"")) -> 5
C55: =SUMIFS(Issuance!$H:$H,Issuance!$D:$D,Formulas!$B55,Issuance!$C:$C,Formulas!C$2) -> 0 | D55: =SUMIFS(Issuance!$H:$H,Issuance!$D:$D,Formulas!$B55,Issuance!$C:$C,Formulas!D$2) -> 0 | E55: =SUM(C55:D55) -> 0 | F55: =IF(OR(B55="",B55=0,E55=0),"",IF(COUNTIFS($E$3:$E$500,">"&E55,$E$3:$E$500,"<>0")+1<=20,COUNTIFS($E$3:$E$500,">"&E55,$E$3:$E$500,"<>0")+1,"")) | H55: JPMorgan India Growth & Income | I55: =SUMIFS(Buybacks!H:H,Buybacks!D:D,Formulas!H55) -> -11.4882 | J55: =IF(OR(H55="",H55=0,I55=0),"",IF(COUNTIFS($I$3:$I$500,"<"&I55,$I$3:$I$500,"<>0")+1<=20,COUNTIFS($I$3:$I$500,"<"&I55,$I$3:$I$500,"<>0")+1,"")) | L55: Scottish Mortgage | M55: =SUMIFS('Corporate activity'!$H:$H,'Corporate activity'!$D:$D,Formulas!$L55,'Corporate activity'!$C:$C,Formulas!M$2) -> 0 | N55: =SUMIFS('Corporate activity'!$H:$H,'Corporate activity'!$D:$D,Formulas!$L55,'Corporate activity'!$C:$C,Formulas!N$2) -> 0 | O55: =SUMIFS('Corporate activity'!$H:$H,'Corporate activity'!$D:$D,Formulas!$L55,'Corporate activity'!$C:$C,Formulas!O$2) -> 0 | P55: =SUM(M55:O55) -> 0 | Q55: =IF(OR(L55="",L55=0,P55=0),"",IF(COUNTIFS($P$3:$P$500,"<"&P55,$P$3:$P$500,"<>0")+1<=20,COUNTIFS($P$3:$P$500,"<"&P55,$P$3:$P$500,"<>0")+1,""))
C56: =SUMIFS(Issuance!$H:$H,Issuance!$D:$D,Formulas!$B56,Issuance!$C:$C,Formulas!C$2) -> 0 | D56: =SUMIFS(Issuance!$H:$H,Issuance!$D:$D,Formulas!$B56,Issuance!$C:$C,Formulas!D$2) -> 0 | E56: =SUM(C56:D56) -> 0 | F56: =IF(OR(B56="",B56=0,E56=0),"",IF(COUNTIFS($E$3:$E$500,">"&E56,$E$3:$E$500,"<>0")+1<=20,COUNTIFS($E$3:$E$500,">"&E56,$E$3:$E$500,"<>0")+1,"")) | H56: JPMorgan Japanese | I56: =SUMIFS(Buybacks!H:H,Buybacks!D:D,Formulas!H56) -> -61.268784 | J56: =IF(OR(H56="",H56=0,I56=0),"",IF(COUNTIFS($I$3:$I$500,"<"&I56,$I$3:$I$500,"<>0")+1<=20,COUNTIFS($I$3:$I$500,"<"&I56,$I$3:$I$500,"<>0")+1,"")) | L56: Hydrogen Capital Growth | M56: =SUMIFS('Corporate activity'!$H:$H,'Corporate activity'!$D:$D,Formulas!$L56,'Corporate activity'!$C:$C,Formulas!M$2) -> 0 | N56: =SUMIFS('Corporate activity'!$H:$H,'Corporate activity'!$D:$D,Formulas!$L56,'Corporate activity'!$C:$C,Formulas!N$2) -> 0 | O56: =SUMIFS('Corporate activity'!$H:$H,'Corporate activity'!$D:$D,Formulas!$L56,'Corporate activity'!$C:$C,Formulas!O$2) -> 0 | P56: =SUM(M56:O56) -> 0 | Q56: =IF(OR(L56="",L56=0,P56=0),"",IF(COUNTIFS($P$3:$P$500,"<"&P56,$P$3:$P$500,"<>0")+1<=20,COUNTIFS($P$3:$P$500,"<"&P56,$P$3:$P$500,"<>0")+1,""))
C57: =SUMIFS(Issuance!$H:$H,Issuance!$D:$D,Formulas!$B57,Issuance!$C:$C,Formulas!C$2) -> 0 | D57: =SUMIFS(Issuance!$H:$H,Issuance!$D:$D,Formulas!$B57,Issuance!$C:$C,Formulas!D$2) -> 0 | E57: =SUM(C57:D57) -> 0 | F57: =IF(OR(B57="",B57=0,E57=0),"",IF(COUNTIFS($E$3:$E$500,">"&E57,$E$3:$E$500,"<>0")+1<=20,COUNTIFS($E$3:$E$500,">"&E57,$E$3:$E$500,"<>0")+1,"")) | H57: JPMorgan US Smaller Companies | I57: =SUMIFS(Buybacks!H:H,Buybacks!D:D,Formulas!H57) -> -19.967124 | J57: =IF(OR(H57="",H57=0,I57=0),"",IF(COUNTIFS($I$3:$I$500,"<"&I57,$I$3:$I$500,"<>0")+1<=20,COUNTIFS($I$3:$I$500,"<"&I57,$I$3:$I$500,"<>0")+1,"")) | L57: Life Science REIT | M57: =SUMIFS('Corporate activity'!$H:$H,'Corporate activity'!$D:$D,Formulas!$L57,'Corporate activity'!$C:$C,Formulas!M$2) -> 0 | N57: =SUMIFS('Corporate activity'!$H:$H,'Corporate activity'!$D:$D,Formulas!$L57,'Corporate activity'!$C:$C,Formulas!N$2) -> 0 | O57: =SUMIFS('Corporate activity'!$H:$H,'Corporate activity'!$D:$D,Formulas!$L57,'Corporate activity'!$C:$C,Formulas!O$2) -> 0 | P57: =SUM(M57:O57) -> 0 | Q57: =IF(OR(L57="",L57=0,P57=0),"",IF(COUNTIFS($P$3:$P$500,"<"&P57,$P$3:$P$500,"<>0")+1<=20,COUNTIFS($P$3:$P$500,"<"&P57,$P$3:$P$500,"<>0")+1,""))
C58: =SUMIFS(Issuance!$H:$H,Issuance!$D:$D,Formulas!$B58,Issuance!$C:$C,Formulas!C$2) -> 0 | D58: =SUMIFS(Issuance!$H:$H,Issuance!$D:$D,Formulas!$B58,Issuance!$C:$C,Formulas!D$2) -> 0 | E58: =SUM(C58:D58) -> 0 | F58: =IF(OR(B58="",B58=0,E58=0),"",IF(COUNTIFS($E$3:$E$500,">"&E58,$E$3:$E$500,"<>0")+1<=20,COUNTIFS($E$3:$E$500,">"&E58,$E$3:$E$500,"<>0")+1,"")) | H58: Mercantile Investment Trust | I58: =SUMIFS(Buybacks!H:H,Buybacks!D:D,Formulas!H58) -> -145.3855 | J58: =IF(OR(H58="",H58=0,I58=0),"",IF(COUNTIFS($I$3:$I$500,"<"&I58,$I$3:$I$500,"<>0")+1<=20,COUNTIFS($I$3:$I$500,"<"&I58,$I$3:$I$500,"<>0")+1,"")) -> 6 | L58: CVC Income & Growth | M58: =SUMIFS('Corporate activity'!$H:$H,'Corporate activity'!$D:$D,Formulas!$L58,'Corporate activity'!$C:$C,Formulas!M$2) -> -0.033264 | N58: =SUMIFS('Corporate activity'!$H:$H,'Corporate activity'!$D:$D,Formulas!$L58,'Corporate activity'!$C:$C,Formulas!N$2) -> 0 | O58: =SUMIFS('Corporate activity'!$H:$H,'Corporate activity'!$D:$D,Formulas!$L58,'Corporate activity'!$C:$C,Formulas!O$2) -> 0 | P58: =SUM(M58:O58) -> -0.033264 | Q58: =IF(OR(L58="",L58=0,P58=0),"",IF(COUNTIFS($P$3:$P$500,"<"&P58,$P$3:$P$500,"<>0")+1<=20,COUNTIFS($P$3:$P$500,"<"&P58,$P$3:$P$500,"<>0")+1,""))
C59: =SUMIFS(Issuance!$H:$H,Issuance!$D:$D,Formulas!$B59,Issuance!$C:$C,Formulas!C$2) -> 0 | D59: =SUMIFS(Issuance!$H:$H,Issuance!$D:$D,Formulas!$B59,Issuance!$C:$C,Formulas!D$2) -> 0 | E59: =SUM(C59:D59) -> 0 | F59: =IF(OR(B59="",B59=0,E59=0),"",IF(COUNTIFS($E$3:$E$500,">"&E59,$E$3:$E$500,"<>0")+1<=20,COUNTIFS($E$3:$E$500,">"&E59,$E$3:$E$500,"<>0")+1,"")) | H59: Mid Wynd International | I59: =SUMIFS(Buybacks!H:H,Buybacks!D:D,Formulas!H59) -> -43.485891 | J59: =IF(OR(H59="",H59=0,I59=0),"",IF(COUNTIFS($I$3:$I$500,"<"&I59,$I$3:$I$500,"<>0")+1<=20,COUNTIFS($I$3:$I$500,"<"&I59,$I$3:$I$500,"<>0")+1,"")) | L59: Tetragon Financial Group | M59: =SUMIFS('Corporate activity'!$H:$H,'Corporate activity'!$D:$D,Formulas!$L59,'Corporate activity'!$C:$C,Formulas!M$2) -> -36.888 | N59: =SUMIFS('Corporate activity'!$H:$H,'Corporate activity'!$D:$D,Formulas!$L59,'Corporate activity'!$C:$C,Formulas!N$2) -> 0 | O59: =SUMIFS('Corporate activity'!$H:$H,'Corporate activity'!$D:$D,Formulas!$L59,'Corporate activity'!$C:$C,Formulas!O$2) -> 0 | P59: =SUM(M59:O59) -> -36.888 | Q59: =IF(OR(L59="",L59=0,P59=0),"",IF(COUNTIFS($P$3:$P$500,"<"&P59,$P$3:$P$500,"<>0")+1<=20,COUNTIFS($P$3:$P$500,"<"&P59,$P$3:$P$500,"<>0")+1,"")) -> 14
C60: =SUMIFS(Issuance!$H:$H,Issuance!$D:$D,Formulas!$B60,Issuance!$C:$C,Formulas!C$2) -> 0 | D60: =SUMIFS(Issuance!$H:$H,Issuance!$D:$D,Formulas!$B60,Issuance!$C:$C,Formulas!D$2) -> 0 | E60: =SUM(C60:D60) -> 0 | F60: =IF(OR(B60="",B60=0,E60=0),"",IF(COUNTIFS($E$3:$E$500,">"&E60,$E$3:$E$500,"<>0")+1<=20,COUNTIFS($E$3:$E$500,">"&E60,$E$3:$E$500,"<>0")+1,"")) | H60: MIGO Opportunities Trust | I60: =SUMIFS(Buybacks!H:H,Buybacks!D:D,Formulas!H60) -> -2.0076496 | J60: =IF(OR(H60="",H60=0,I60=0),"",IF(COUNTIFS($I$3:$I$500,"<"&I60,$I$3:$I$500,"<>0")+1<=20,COUNTIFS($I$3:$I$500,"<"&I60,$I$3:$I$500,"<>0")+1,"")) | L60: Home REIT | M60: =SUMIFS('Corporate activity'!$H:$H,'Corporate activity'!$D:$D,Formulas!$L60,'Corporate activity'!$C:$C,Formulas!M$2) -> 0 | N60: =SUMIFS('Corporate activity'!$H:$H,'Corporate activity'!$D:$D,Formulas!$L60,'Corporate activity'!$C:$C,Formulas!N$2) -> 0 | O60: =SUMIFS('Corporate activity'!$H:$H,'Corporate activity'!$D:$D,Formulas!$L60,'Corporate activity'!$C:$C,Formulas!O$2) -> 0 | P60: =SUM(M60:O60) -> 0 | Q60: =IF(OR(L60="",L60=0,P60=0),"",IF(COUNTIFS($P$3:$P$500,"<"&P60,$P$3:$P$500,"<>0")+1<=20,COUNTIFS($P$3:$P$500,"<"&P60,$P$3:$P$500,"<>0")+1,""))
C61: =SUMIFS(Issuance!$H:$H,Issuance!$D:$D,Formulas!$B61,Issuance!$C:$C,Formulas!C$2) -> 0 | D61: =SUMIFS(Issuance!$H:$H,Issuance!$D:$D,Formulas!$B61,Issuance!$C:$C,Formulas!D$2) -> 0 | E61: =SUM(C61:D61) -> 0 | F61: =IF(OR(B61="",B61=0,E61=0),"",IF(COUNTIFS($E$3:$E$500,">"&E61,$E$3:$E$500,"<>0")+1<=20,COUNTIFS($E$3:$E$500,">"&E61,$E$3:$E$500,"<>0")+1,"")) | H61: Molten Ventures | I61: =SUMIFS(Buybacks!H:H,Buybacks!D:D,Formulas!H61) -> -12.413618 | J61: =IF(OR(H61="",H61=0,I61=0),"",IF(COUNTIFS($I$3:$I$500,"<"&I61,$I$3:$I$500,"<>0")+1<=20,COUNTIFS($I$3:$I$500,"<"&I61,$I$3:$I$500,"<>0")+1,"")) | L61: Biotech Growth Trust | M61: =SUMIFS('Corporate activity'!$H:$H,'Corporate activity'!$D:$D,Formulas!$L61,'Corporate activity'!$C:$C,Formulas!M$2) -> 0 | N61: =SUMIFS('Corporate activity'!$H:$H,'Corporate activity'!$D:$D,Formulas!$L61,'Corporate activity'!$C:$C,Formulas!N$2) -> 0 | O61: =SUMIFS('Corporate activity'!$H:$H,'Corporate activity'!$D:$D,Formulas!$L61,'Corporate activity'!$C:$C,Formulas!O$2) -> 0 | P61: =SUM(M61:O61) -> 0 | Q61: =IF(OR(L61="",L61=0,P61=0),"",IF(COUNTIFS($P$3:$P$500,"<"&P61,$P$3:$P$500,"<>0")+1<=20,COUNTIFS($P$3:$P$500,"<"&P61,$P$3:$P$500,"<>0")+1,""))
C62: =SUMIFS(Issuance!$H:$H,Issuance!$D:$D,Formulas!$B62,Issuance!$C:$C,Formulas!C$2) -> 0 | D62: =SUMIFS(Issuance!$H:$H,Issuance!$D:$D,Formulas!$B62,Issuance!$C:$C,Formulas!D$2) -> 0 | E62: =SUM(C62:D62) -> 0 | F62: =IF(OR(B62="",B62=0,E62=0),"",IF(COUNTIFS($E$3:$E$500,">"&E62,$E$3:$E$500,"<>0")+1<=20,COUNTIFS($E$3:$E$500,">"&E62,$E$3:$E$500,"<>0")+1,"")) | H62: Monks | I62: =SUMIFS(Buybacks!H:H,Buybacks!D:D,Formulas!H62) -> -156.71252 | J62: =IF(OR(H62="",H62=0,I62=0),"",IF(COUNTIFS($I$3:$I$500,"<"&I62,$I$3:$I$500,"<>0")+1<=20,COUNTIFS($I$3:$I$500,"<"&I62,$I$3:$I$500,"<>0")+1,"")) -> 5 | L62: International Biotechnology | M62: =SUMIFS('Corporate activity'!$H:$H,'Corporate activity'!$D:$D,Formulas!$L62,'Corporate activity'!$C:$C,Formulas!M$2) -> 0 | N62: =SUMIFS('Corporate activity'!$H:$H,'Corporate activity'!$D:$D,Formulas!$L62,'Corporate activity'!$C:$C,Formulas!N$2) -> 0 | O62: =SUMIFS('Corporate activity'!$H:$H,'Corporate activity'!$D:$D,Formulas!$L62,'Corporate activity'!$C:$C,Formulas!O$2) -> 0 | P62: =SUM(M62:O62) -> 0 | Q62: =IF(OR(L62="",L62=0,P62=0),"",IF(COUNTIFS($P$3:$P$500,"<"&P62,$P$3:$P$500,"<>0")+1<=20,COUNTIFS($P$3:$P$500,"<"&P62,$P$3:$P$500,"<>0")+1,""))
... C113: =SUMIFS(Issuance!$H:$H,Issuance!$D:$D,Formulas!$B113,Issuance!$C:$C,Formulas!C$2) -> 0 | D113: =SUMIFS(Issuance!$H:$H,Issuance!$D:$D,Formulas!$B113,Issuance!$C:$C,Formulas!D$2) -> 0 | E113: =SUM(C113:D113) -> 0 | F113: =IF(OR(B113="",B113=0,E113=0),"",IF(COUNTIFS($E$3:$E$500,">"&E113,$E$3:$E$500,"<>0")+1<=20,COUNTIFS($E$3:$E$500,">"&E113,$E$3:$E$500,"<>0")+1,"")) | H113: JPMorgan UK Small Cap Growth & Income | I113: =SUMIFS(Buybacks!H:H,Buybacks!D:D,Formulas!H113) -> -13.905853 | J113: =IF(OR(H113="",H113=0,I113=0),"",IF(COUNTIFS($I$3:$I$500,"<"&I113,$I$3:$I$500,"<>0")+1<=20,COUNTIFS($I$3:$I$500,"<"&I113,$I$3:$I$500,"<>0")+1,"")) | L113: NextEnergy Solar | M113: =SUMIFS('Corporate activity'!$H:$H,'Corporate activity'!$D:$D,Formulas!$L113,'Corporate activity'!$C:$C,Formulas!M$2) -> 0 | N113: =SUMIFS('Corporate activity'!$H:$H,'Corporate activity'!$D:$D,Formulas!$L113,'Corporate activity'!$C:$C,Formulas!N$2) -> 0 | O113: =SUMIFS('Corporate activity'!$H:$H,'Corporate activity'!$D:$D,Formulas!$L113,'Corporate activity'!$C:$C,Formulas!O$2) -> 0 | P113: =SUM(M113:O113) -> 0 | Q113: =IF(OR(L113="",L113=0,P113=0),"",IF(COUNTIFS($P$3:$P$500,"<"&P113,$P$3:$P$500,"<>0")+1<=20,COUNTIFS($P$3:$P$500,"<"&P113,$P$3:$P$500,"<>0")+1,""))
C114: =SUMIFS(Issuance!$H:$H,Issuance!$D:$D,Formulas!$B114,Issuance!$C:$C,Formulas!C$2) -> 0 | D114: =SUMIFS(Issuance!$H:$H,Issuance!$D:$D,Formulas!$B114,Issuance!$C:$C,Formulas!D$2) -> 0 | E114: =SUM(C114:D114) -> 0 | F114: =IF(OR(B114="",B114=0,E114=0),"",IF(COUNTIFS($E$3:$E$500,">"&E114,$E$3:$E$500,"<>0")+1<=20,COUNTIFS($E$3:$E$500,">"&E114,$E$3:$E$500,"<>0")+1,"")) | H114: Life Settlement Assets | I114: =SUMIFS(Buybacks!H:H,Buybacks!D:D,Formulas!H114) -> -3.7889855 | J114: =IF(OR(H114="",H114=0,I114=0),"",IF(COUNTIFS($I$3:$I$500,"<"&I114,$I$3:$I$500,"<>0")+1<=20,COUNTIFS($I$3:$I$500,"<"&I114,$I$3:$I$500,"<>0")+1,"")) | L114: 0 | M114: =SUMIFS('Corporate activity'!$H:$H,'Corporate activity'!$D:$D,Formulas!$L114,'Corporate activity'!$C:$C,Formulas!M$2) -> 0 | N114: =SUMIFS('Corporate activity'!$H:$H,'Corporate activity'!$D:$D,Formulas!$L114,'Corporate activity'!$C:$C,Formulas!N$2) -> 0 | O114: =SUMIFS('Corporate activity'!$H:$H,'Corporate activity'!$D:$D,Formulas!$L114,'Corporate activity'!$C:$C,Formulas!O$2) -> 0 | P114: =SUM(M114:O114) -> 0 | Q114: =IF(OR(L114="",L114=0,P114=0),"",IF(COUNTIFS($P$3:$P$500,"<"&P114,$P$3:$P$500,"<>0")+1<=20,COUNTIFS($P$3:$P$500,"<"&P114,$P$3:$P$500,"<>0")+1,""))
C115: =SUMIFS(Issuance!$H:$H,Issuance!$D:$D,Formulas!$B115,Issuance!$C:$C,Formulas!C$2) -> 0 | D115: =SUMIFS(Issuance!$H:$H,Issuance!$D:$D,Formulas!$B115,Issuance!$C:$C,Formulas!D$2) -> 0 | E115: =SUM(C115:D115) -> 0 | F115: =IF(OR(B115="",B115=0,E115=0),"",IF(COUNTIFS($E$3:$E$500,">"&E115,$E$3:$E$500,"<>0")+1<=20,COUNTIFS($E$3:$E$500,">"&E115,$E$3:$E$500,"<>0")+1,"")) | H115: M&G Credit Income | I115: =SUMIFS(Buybacks!H:H,Buybacks!D:D,Formulas!H115) -> -0.2230025 | J115: =IF(OR(H115="",H115=0,I115=0),"",IF(COUNTIFS($I$3:$I$500,"<"&I115,$I$3:$I$500,"<>0")+1<=20,COUNTIFS($I$3:$I$500,"<"&I115,$I$3:$I$500,"<>0")+1,"")) | M115: =SUMIFS('Corporate activity'!$H:$H,'Corporate activity'!$D:$D,Formulas!$L115,'Corporate activity'!$C:$C,Formulas!M$2) -> 0 | N115: =SUMIFS('Corporate activity'!$H:$H,'Corporate activity'!$D:$D,Formulas!$L115,'Corporate activity'!$C:$C,Formulas!N$2) -> 0 | O115: =SUMIFS('Corporate activity'!$H:$H,'Corporate activity'!$D:$D,Formulas!$L115,'Corporate activity'!$C:$C,Formulas!O$2) -> 0 | P115: =SUM(M115:O115) -> 0 | Q115: =IF(OR(L115="",L115=0,P115=0),"",IF(COUNTIFS($P$3:$P$500,"<"&P115,$P$3:$P$500,"<>0")+1<=20,COUNTIFS($P$3:$P$500,"<"&P115,$P$3:$P$500,"<>0")+1,""))
C116: =SUMIFS(Issuance!$H:$H,Issuance!$D:$D,Formulas!$B116,Issuance!$C:$C,Formulas!C$2) -> 0 | D116: =SUMIFS(Issuance!$H:$H,Issuance!$D:$D,Formulas!$B116,Issuance!$C:$C,Formulas!D$2) -> 0 | E116: =SUM(C116:D116) -> 0 | F116: =IF(OR(B116="",B116=0,E116=0),"",IF(COUNTIFS($E$3:$E$500,">"&E116,$E$3:$E$500,"<>0")+1<=20,COUNTIFS($E$3:$E$500,">"&E116,$E$3:$E$500,"<>0")+1,"")) | H116: Montanaro UK Smaller Companies | I116: =SUMIFS(Buybacks!H:H,Buybacks!D:D,Formulas!H116) -> -5.3833052 | J116: =IF(OR(H116="",H116=0,I116=0),"",IF(COUNTIFS($I$3:$I$500,"<"&I116,$I$3:$I$500,"<>0")+1<=20,COUNTIFS($I$3:$I$500,"<"&I116,$I$3:$I$500,"<>0")+1,"")) | M116: =SUMIFS('Corporate activity'!$H:$H,'Corporate activity'!$D:$D,Formulas!$L116,'Corporate activity'!$C:$C,Formulas!M$2) -> 0 | N116: =SUMIFS('Corporate activity'!$H:$H,'Corporate activity'!$D:$D,Formulas!$L116,'Corporate activity'!$C:$C,Formulas!N$2) -> 0 | O116: =SUMIFS('Corporate activity'!$H:$H,'Corporate activity'!$D:$D,Formulas!$L116,'Corporate activity'!$C:$C,Formulas!O$2) -> 0 | P116: =SUM(M116:O116) -> 0 | Q116: =IF(OR(L116="",L116=0,P116=0),"",IF(COUNTIFS($P$3:$P$500,"<"&P116,$P$3:$P$500,"<>0")+1<=20,COUNTIFS($P$3:$P$500,"<"&P116,$P$3:$P$500,"<>0")+1,""))
C117: =SUMIFS(Issuance!$H:$H,Issuance!$D:$D,Formulas!$B117,Issuance!$C:$C,Formulas!C$2) -> 0 | D117: =SUMIFS(Issuance!$H:$H,Issuance!$D:$D,Formulas!$B117,Issuance!$C:$C,Formulas!D$2) -> 0 | E117: =SUM(C117:D117) -> 0 | F117: =IF(OR(B117="",B117=0,E117=0),"",IF(COUNTIFS($E$3:$E$500,">"&E117,$E$3:$E$500,"<>0")+1<=20,COUNTIFS($E$3:$E$500,">"&E117,$E$3:$E$500,"<>0")+1,"")) | H117: North American Income Trust | I117: =SUMIFS(Buybacks!H:H,Buybacks!D:D,Formulas!H117) -> -0.19755984 | J117: =IF(OR(H117="",H117=0,I117=0),"",IF(COUNTIFS($I$3:$I$500,"<"&I117,$I$3:$I$500,"<>0")+1<=20,COUNTIFS($I$3:$I$500,"<"&I117,$I$3:$I$500,"<>0")+1,"")) | M117: =SUMIFS('Corporate activity'!$H:$H,'Corporate activity'!$D:$D,Formulas!$L117,'Corporate activity'!$C:$C,Formulas!M$2) -> 0 | N117: =SUMIFS('Corporate activity'!$H:$H,'Corporate activity'!$D:$D,Formulas!$L117,'Corporate activity'!$C:$C,Formulas!N$2) -> 0 | O117: =SUMIFS('Corporate activity'!$H:$H,'Corporate activity'!$D:$D,Formulas!$L117,'Corporate activity'!$C:$C,Formulas!O$2) -> 0 | P117: =SUM(M117:O117) -> 0 | Q117: =IF(OR(L117="",L117=0,P117=0),"",IF(COUNTIFS($P$3:$P$500,"<"&P117,$P$3:$P$500,"<>0")+1<=20,COUNTIFS($P$3:$P$500,"<"&P117,$P$3:$P$500,"<>0")+1,""))
C118: =SUMIFS(Issuance!$H:$H,Issuance!$D:$D,Formulas!$B118,Issuance!$C:$C,Formulas!C$2) -> 0 | D118: =SUMIFS(Issuance!$H:$H,Issuance!$D:$D,Formulas!$B118,Issuance!$C:$C,Formulas!D$2) -> 0 | E118: =SUM(C118:D118) -> 0 | F118: =IF(OR(B118="",B118=0,E118=0),"",IF(COUNTIFS($E$3:$E$500,">"&E118,$E$3:$E$500,"<>0")+1<=20,COUNTIFS($E$3:$E$500,">"&E118,$E$3:$E$500,"<>0")+1,"")) | H118: Personal Assets Trust | I118: =SUMIFS(Buybacks!H:H,Buybacks!D:D,Formulas!H118) -> -40.194673 | J118: =IF(OR(H118="",H118=0,I118=0),"",IF(COUNTIFS($I$3:$I$500,"<"&I118,$I$3:$I$500,"<>0")+1<=20,COUNTIFS($I$3:$I$500,"<"&I118,$I$3:$I$500,"<>0")+1,"")) | M118: =SUMIFS('Corporate activity'!$H:$H,'Corporate activity'!$D:$D,Formulas!$L118,'Corporate activity'!$C:$C,Formulas!M$2) -> 0 | N118: =SUMIFS('Corporate activity'!$H:$H,'Corporate activity'!$D:$D,Formulas!$L118,'Corporate activity'!$C:$C,Formulas!N$2) -> 0 | O118: =SUMIFS('Corporate activity'!$H:$H,'Corporate activity'!$D:$D,Formulas!$L118,'Corporate activity'!$C:$C,Formulas!O$2) -> 0 | P118: =SUM(M118:O118) -> 0 | Q118: =IF(OR(L118="",L118=0,P118=0),"",IF(COUNTIFS($P$3:$P$500,"<"&P118,$P$3:$P$500,"<>0")+1<=20,COUNTIFS($P$3:$P$500,"<"&P118,$P$3:$P$500,"<>0")+1,""))
C119: =SUMIFS(Issuance!$H:$H,Issuance!$D:$D,Formulas!$B119,Issuance!$C:$C,Formulas!C$2) -> 0 | D119: =SUMIFS(Issuance!$H:$H,Issuance!$D:$D,Formulas!$B119,Issuance!$C:$C,Formulas!D$2) -> 0 | E119: =SUM(C119:D119) -> 0 | F119: =IF(OR(B119="",B119=0,E119=0),"",IF(COUNTIFS($E$3:$E$500,">"&E119,$E$3:$E$500,"<>0")+1<=20,COUNTIFS($E$3:$E$500,">"&E119,$E$3:$E$500,"<>0")+1,"")) | H119: Polar Capital Global Financials | I119: =SUMIFS(Buybacks!H:H,Buybacks!D:D,Formulas!H119) -> -12.386149 | J119: =IF(OR(H119="",H119=0,I119=0),"",IF(COUNTIFS($I$3:$I$500,"<"&I119,$I$3:$I$500,"<>0")+1<=20,COUNTIFS($I$3:$I$500,"<"&I119,$I$3:$I$500,"<>0")+1,"")) | M119: =SUMIFS('Corporate activity'!$H:$H,'Corporate activity'!$D:$D,Formulas!$L119,'Corporate activity'!$C:$C,Formulas!M$2) -> 0 | N119: =SUMIFS('Corporate activity'!$H:$H,'Corporate activity'!$D:$D,Formulas!$L119,'Corporate activity'!$C:$C,Formulas!N$2) -> 0 | O119: =SUMIFS('Corporate activity'!$H:$H,'Corporate activity'!$D:$D,Formulas!$L119,'Corporate activity'!$C:$C,Formulas!O$2) -> 0 | P119: =SUM(M119:O119) -> 0 | Q119: =IF(OR(L119="",L119=0,P119=0),"",IF(COUNTIFS($P$3:$P$500,"<"&P119,$P$3:$P$500,"<>0")+1<=20,COUNTIFS($P$3:$P$500,"<"&P119,$P$3:$P$500,"<>0")+1,""))
C120: =SUMIFS(Issuance!$H:$H,Issuance!$D:$D,Formulas!$B120,Issuance!$C:$C,Formulas!C$2) -> 0 | D120: =SUMIFS(Issuance!$H:$H,Issuance!$D:$D,Formulas!$B120,Issuance!$C:$C,Formulas!D$2) -> 0 | E120: =SUM(C120:D120) -> 0 | F120: =IF(OR(B120="",B120=0,E120=0),"",IF(COUNTIFS($E$3:$E$500,">"&E120,$E$3:$E$500,"<>0")+1<=20,COUNTIFS($E$3:$E$500,">"&E120,$E$3:$E$500,"<>0")+1,"")) | H120: Real Estate Credit Investments | I120: =SUMIFS(Buybacks!H:H,Buybacks!D:D,Formulas!H120) -> -0.82075 | J120: =IF(OR(H120="",H120=0,I120=0),"",IF(COUNTIFS($I$3:$I$500,"<"&I120,$I$3:$I$500,"<>0")+1<=20,COUNTIFS($I$3:$I$500,"<"&I120,$I$3:$I$500,"<>0")+1,"")) | M120: =SUMIFS('Corporate activity'!$H:$H,'Corporate activity'!$D:$D,Formulas!$L120,'Corporate activity'!$C:$C,Formulas!M$2) -> 0 | N120: =SUMIFS('Corporate activity'!$H:$H,'Corporate activity'!$D:$D,Formulas!$L120,'Corporate activity'!$C:$C,Formulas!N$2) -> 0 | O120: =SUMIFS('Corporate activity'!$H:$H,'Corporate activity'!$D:$D,Formulas!$L120,'Corporate activity'!$C:$C,Formulas!O$2) -> 0 | P120: =SUM(M120:O120) -> 0 | Q120: =IF(OR(L120="",L120=0,P120=0),"",IF(COUNTIFS($P$3:$P$500,"<"&P120,$P$3:$P$500,"<>0")+1<=20,COUNTIFS($P$3:$P$500,"<"&P120,$P$3:$P$500,"<>0")+1,""))
C121: =SUMIFS(Issuance!$H:$H,Issuance!$D:$D,Formulas!$B121,Issuance!$C:$C,Formulas!C$2) -> 0 | D121: =SUMIFS(Issuance!$H:$H,Issuance!$D:$D,Formulas!$B121,Issuance!$C:$C,Formulas!D$2) -> 0 | E121: =SUM(C121:D121) -> 0 | F121: =IF(OR(B121="",B121=0,E121=0),"",IF(COUNTIFS($E$3:$E$500,">"&E121,$E$3:$E$500,"<>0")+1<=20,COUNTIFS($E$3:$E$500,">"&E121,$E$3:$E$500,"<>0")+1,"")) | H121: RTW Biotech Opportunities | I121: =SUMIFS(Buybacks!H:H,Buybacks!D:D,Formulas!H121) -> -6.4663945 | J121: =IF(OR(H121="",H121=0,I121=0),"",IF(COUNTIFS($I$3:$I$500,"<"&I121,$I$3:$I$500,"<>0")+1<=20,COUNTIFS($I$3:$I$500,"<"&I121,$I$3:$I$500,"<>0")+1,"")) | M121: =SUMIFS('Corporate activity'!$H:$H,'Corporate activity'!$D:$D,Formulas!$L121,'Corporate activity'!$C:$C,Formulas!M$2) -> 0 | N121: =SUMIFS('Corporate activity'!$H:$H,'Corporate activity'!$D:$D,Formulas!$L121,'Corporate activity'!$C:$C,Formulas!N$2) -> 0 | O121: =SUMIFS('Corporate activity'!$H:$H,'Corporate activity'!$D:$D,Formulas!$L121,'Corporate activity'!$C:$C,Formulas!O$2) -> 0 | P121: =SUM(M121:O121) -> 0 | Q121: =IF(OR(L121="",L121=0,P121=0),"",IF(COUNTIFS($P$3:$P$500,"<"&P121,$P$3:$P$500,"<>0")+1<=20,COUNTIFS($P$3:$P$500,"<"&P121,$P$3:$P$500,"<>0")+1,""))
C122: =SUMIFS(Issuance!$H:$H,Issuance!$D:$D,Formulas!$B122,Issuance!$C:$C,Formulas!C$2) -> 0 | D122: =SUMIFS(Issuance!$H:$H,Issuance!$D:$D,Formulas!$B122,Issuance!$C:$C,Formulas!D$2) -> 0 | E122: =SUM(C122:D122) -> 0 | F122: =IF(OR(B122="",B122=0,E122=0),"",IF(COUNTIFS($E$3:$E$500,">"&E122,$E$3:$E$500,"<>0")+1<=20,COUNTIFS($E$3:$E$500,">"&E122,$E$3:$E$500,"<>0")+1,"")) | H122: Schroder Japan Trust | I122: =SUMIFS(Buybacks!H:H,Buybacks!D:D,Formulas!H122) -> -2.40552 | J122: =IF(OR(H122="",H122=0,I122=0),"",IF(COUNTIFS($I$3:$I$500,"<"&I122,$I$3:$I$500,"<>0")+1<=20,COUNTIFS($I$3:$I$500,"<"&I122,$I$3:$I$500,"<>0")+1,"")) | M122: =SUMIFS('Corporate activity'!$H:$H,'Corporate activity'!$D:$D,Formulas!$L122,'Corporate activity'!$C:$C,Formulas!M$2) -> 0 | N122: =SUMIFS('Corporate activity'!$H:$H,'Corporate activity'!$D:$D,Formulas!$L122,'Corporate activity'!$C:$C,Formulas!N$2) -> 0 | O122: =SUMIFS('Corporate activity'!$H:$H,'Corporate activity'!$D:$D,Formulas!$L122,'Corporate activity'!$C:$C,Formulas!O$2) -> 0 | P122: =SUM(M122:O122) -> 0 | Q122: =IF(OR(L122="",L122=0,P122=0),"",IF(COUNTIFS($P$3:$P$500,"<"&P122,$P$3:$P$500,"<>0")+1<=20,COUNTIFS($P$3:$P$500,"<"&P122,$P$3:$P$500,"<>0")+1,""))
C123: =SUMIFS(Issuance!$H:$H,Issuance!$D:$D,Formulas!$B123,Issuance!$C:$C,Formulas!C$2) -> 0 | D123: =SUMIFS(Issuance!$H:$H,Issuance!$D:$D,Formulas!$B123,Issuance!$C:$C,Formulas!D$2) -> 0 | E123: =SUM(C123:D123) -> 0 | F123: =IF(OR(B123="",B123=0,E123=0),"",IF(COUNTIFS($E$3:$E$500,">"&E123,$E$3:$E$500,"<>0")+1<=20,COUNTIFS($E$3:$E$500,">"&E123,$E$3:$E$500,"<>0")+1,"")) | H123: Value and Indexed Property Income Trust | I123: =SUMIFS(Buybacks!H:H,Buybacks!D:D,Formulas!H123) -> -0.9817 | J123: =IF(OR(H123="",H123=0,I123=0),"",IF(COUNTIFS($I$3:$I$500,"<"&I123,$I$3:$I$500,"<>0")+1<=20,COUNTIFS($I$3:$I$500,"<"&I123,$I$3:$I$500,"<>0")+1,"")) | M123: =SUMIFS('Corporate activity'!$H:$H,'Corporate activity'!$D:$D,Formulas!$L123,'Corporate activity'!$C:$C,Formulas!M$2) -> 0 | N123: =SUMIFS('Corporate activity'!$H:$H,'Corporate activity'!$D:$D,Formulas!$L123,'Corporate activity'!$C:$C,Formulas!N$2) -> 0 | O123: =SUMIFS('Corporate activity'!$H:$H,'Corporate activity'!$D:$D,Formulas!$L123,'Corporate activity'!$C:$C,Formulas!O$2) -> 0 | P123: =SUM(M123:O123) -> 0 | Q123: =IF(OR(L123="",L123=0,P123=0),"",IF(COUNTIFS($P$3:$P$500,"<"&P123,$P$3:$P$500,"<>0")+1<=20,COUNTIFS($P$3:$P$500,"<"&P123,$P$3:$P$500,"<>0")+1,""))
C124: =SUMIFS(Issuance!$H:$H,Issuance!$D:$D,Formulas!$B124,Issuance!$C:$C,Formulas!C$2) -> 0 | D124: =SUMIFS(Issuance!$H:$H,Issuance!$D:$D,Formulas!$B124,Issuance!$C:$C,Formulas!D$2) -> 0 | E124: =SUM(C124:D124) -> 0 | F124: =IF(OR(B124="",B124=0,E124=0),"",IF(COUNTIFS($E$3:$E$500,">"&E124,$E$3:$E$500,"<>0")+1<=20,COUNTIFS($E$3:$E$500,">"&E124,$E$3:$E$500,"<>0")+1,"")) | H124: AVI Japan Opportunity Trust | I124: =SUMIFS(Buybacks!H:H,Buybacks!D:D,Formulas!H124) -> -0.565785 | J124: =IF(OR(H124="",H124=0,I124=0),"",IF(COUNTIFS($I$3:$I$500,"<"&I124,$I$3:$I$500,"<>0")+1<=20,COUNTIFS($I$3:$I$500,"<"&I124,$I$3:$I$500,"<>0")+1,"")) | M124: =SUMIFS('Corporate activity'!$H:$H,'Corporate activity'!$D:$D,Formulas!$L124,'Corporate activity'!$C:$C,Formulas!M$2) -> 0 | N124: =SUMIFS('Corporate activity'!$H:$H,'Corporate activity'!$D:$D,Formulas!$L124,'Corporate activity'!$C:$C,Formulas!N$2) -> 0 | O124: =SUMIFS('Corporate activity'!$H:$H,'Corporate activity'!$D:$D,Formulas!$L124,'Corporate activity'!$C:$C,Formulas!O$2) -> 0 | P124: =SUM(M124:O124) -> 0 | Q124: =IF(OR(L124="",L124=0,P124=0),"",IF(COUNTIFS($P$3:$P$500,"<"&P124,$P$3:$P$500,"<>0")+1<=20,COUNTIFS($P$3:$P$500,"<"&P124,$P$3:$P$500,"<>0")+1,""))
C125: =SUMIFS(Issuance!$H:$H,Issuance!$D:$D,Formulas!$B125,Issuance!$C:$C,Formulas!C$2) -> 0 | D125: =SUMIFS(Issuance!$H:$H,Issuance!$D:$D,Formulas!$B125,Issuance!$C:$C,Formulas!D$2) -> 0 | E125: =SUM(C125:D125) -> 0 | F125: =IF(OR(B125="",B125=0,E125=0),"",IF(COUNTIFS($E$3:$E$500,">"&E125,$E$3:$E$500,"<>0")+1<=20,COUNTIFS($E$3:$E$500,">"&E125,$E$3:$E$500,"<>0")+1,"")) | H125: BioPharma Credit | I125: =SUMIFS(Buybacks!H:H,Buybacks!D:D,Formulas!H125) -> -5.5877548 | J125: =IF(OR(H125="",H125=0,I125=0),"",IF(COUNTIFS($I$3:$I$500,"<"&I125,$I$3:$I$500,"<>0")+1<=20,COUNTIFS($I$3:$I$500,"<"&I125,$I$3:$I$500,"<>0")+1,"")) | M125: =SUMIFS('Corporate activity'!$H:$H,'Corporate activity'!$D:$D,Formulas!$L125,'Corporate activity'!$C:$C,Formulas!M$2) -> 0 | N125: =SUMIFS('Corporate activity'!$H:$H,'Corporate activity'!$D:$D,Formulas!$L125,'Corporate activity'!$C:$C,Formulas!N$2) -> 0 | O125: =SUMIFS('Corporate activity'!$H:$H,'Corporate activity'!$D:$D,Formulas!$L125,'Corporate activity'!$C:$C,Formulas!O$2) -> 0 | P125: =SUM(M125:O125) -> 0 | Q125: =IF(OR(L125="",L125=0,P125=0),"",IF(COUNTIFS($P$3:$P$500,"<"&P125,$P$3:$P$500,"<>0")+1<=20,COUNTIFS($P$3:$P$500,"<"&P125,$P$3:$P$500,"<>0")+1,""))
C126: =SUMIFS(Issuance!$H:$H,Issuance!$D:$D,Formulas!$B126,Issuance!$C:$C,Formulas!C$2) -> 0 | D126: =SUMIFS(Issuance!$H:$H,Issuance!$D:$D,Formulas!$B126,Issuance!$C:$C,Formulas!D$2) -> 0 | E126: =SUM(C126:D126) -> 0 | F126: =IF(OR(B126="",B126=0,E126=0),"",IF(COUNTIFS($E$3:$E$500,">"&E126,$E$3:$E$500,"<>0")+1<=20,COUNTIFS($E$3:$E$500,">"&E126,$E$3:$E$500,"<>0")+1,"")) | H126: Golden Prospect Precious Metals | I126: =SUMIFS(Buybacks!H:H,Buybacks!D:D,Formulas!H126) -> -16.787561 | J126: =IF(OR(H126="",H126=0,I126=0),"",IF(COUNTIFS($I$3:$I$500,"<"&I126,$I$3:$I$500,"<>0")+1<=20,COUNTIFS($I$3:$I$500,"<"&I126,$I$3:$I$500,"<>0")+1,"")) | M126: =SUMIFS('Corporate activity'!$H:$H,'Corporate activity'!$D:$D,Formulas!$L126,'Corporate activity'!$C:$C,Formulas!M$2) -> 0 | N126: =SUMIFS('Corporate activity'!$H:$H,'Corporate activity'!$D:$D,Formulas!$L126,'Corporate activity'!$C:$C,Formulas!N$2) -> 0 | O126: =SUMIFS('Corporate activity'!$H:$H,'Corporate activity'!$D:$D,Formulas!$L126,'Corporate activity'!$C:$C,Formulas!O$2) -> 0 | P126: =SUM(M126:O126) -> 0 | Q126: =IF(OR(L126="",L126=0,P126=0),"",IF(COUNTIFS($P$3:$P$500,"<"&P126,$P$3:$P$500,"<>0")+1<=20,COUNTIFS($P$3:$P$500,"<"&P126,$P$3:$P$500,"<>0")+1,""))
... C140: =SUMIFS(Issuance!$H:$H,Issuance!$D:$D,Formulas!$B140,Issuance!$C:$C,Formulas!C$2) -> 0 | D140: =SUMIFS(Issuance!$H:$H,Issuance!$D:$D,Formulas!$B140,Issuance!$C:$C,Formulas!D$2) -> 0 | E140: =SUM(C140:D140) -> 0 | F140: =IF(OR(B140="",B140=0,E140=0),"",IF(COUNTIFS($E$3:$E$500,">"&E140,$E$3:$E$500,"<>0")+1<=20,COUNTIFS($E$3:$E$500,">"&E140,$E$3:$E$500,"<>0")+1,"")) | H140: UIL | I140: =SUMIFS(Buybacks!H:H,Buybacks!D:D,Formulas!H140) -> -0.070315 | J140: =IF(OR(H140="",H140=0,I140=0),"",IF(COUNTIFS($I$3:$I$500,"<"&I140,$I$3:$I$500,"<>0")+1<=20,COUNTIFS($I$3:$I$500,"<"&I140,$I$3:$I$500,"<>0")+1,"")) | M140: =SUMIFS('Corporate activity'!$H:$H,'Corporate activity'!$D:$D,Formulas!$L140,'Corporate activity'!$C:$C,Formulas!M$2) -> 0 | N140: =SUMIFS('Corporate activity'!$H:$H,'Corporate activity'!$D:$D,Formulas!$L140,'Corporate activity'!$C:$C,Formulas!N$2) -> 0 | O140: =SUMIFS('Corporate activity'!$H:$H,'Corporate activity'!$D:$D,Formulas!$L140,'Corporate activity'!$C:$C,Formulas!O$2) -> 0 | P140: =SUM(M140:O140) -> 0 | Q140: =IF(OR(L140="",L140=0,P140=0),"",IF(COUNTIFS($P$3:$P$500,"<"&P140,$P$3:$P$500,"<>0")+1<=20,COUNTIFS($P$3:$P$500,"<"&P140,$P$3:$P$500,"<>0")+1,""))
C141: =SUMIFS(Issuance!$H:$H,Issuance!$D:$D,Formulas!$B141,Issuance!$C:$C,Formulas!C$2) -> 0 | D141: =SUMIFS(Issuance!$H:$H,Issuance!$D:$D,Formulas!$B141,Issuance!$C:$C,Formulas!D$2) -> 0 | E141: =SUM(C141:D141) -> 0 | F141: =IF(OR(B141="",B141=0,E141=0),"",IF(COUNTIFS($E$3:$E$500,">"&E141,$E$3:$E$500,"<>0")+1<=20,COUNTIFS($E$3:$E$500,">"&E141,$E$3:$E$500,"<>0")+1,"")) | H141: 0 | I141: =SUMIFS(Buybacks!H:H,Buybacks!D:D,Formulas!H141) -> 0 | J141: =IF(OR(H141="",H141=0,I141=0),"",IF(COUNTIFS($I$3:$I$500,"<"&I141,$I$3:$I$500,"<>0")+1<=20,COUNTIFS($I$3:$I$500,"<"&I141,$I$3:$I$500,"<>0")+1,"")) | M141: =SUMIFS('Corporate activity'!$H:$H,'Corporate activity'!$D:$D,Formulas!$L141,'Corporate activity'!$C:$C,Formulas!M$2) -> 0 | N141: =SUMIFS('Corporate activity'!$H:$H,'Corporate activity'!$D:$D,Formulas!$L141,'Corporate activity'!$C:$C,Formulas!N$2) -> 0 | O141: =SUMIFS('Corporate activity'!$H:$H,'Corporate activity'!$D:$D,Formulas!$L141,'Corporate activity'!$C:$C,Formulas!O$2) -> 0 | P141: =SUM(M141:O141) -> 0 | Q141: =IF(OR(L141="",L141=0,P141=0),"",IF(COUNTIFS($P$3:$P$500,"<"&P141,$P$3:$P$500,"<>0")+1<=20,COUNTIFS($P$3:$P$500,"<"&P141,$P$3:$P$500,"<>0")+1,""))
C142: =SUMIFS(Issuance!$H:$H,Issuance!$D:$D,Formulas!$B142,Issuance!$C:$C,Formulas!C$2) -> 0 | D142: =SUMIFS(Issuance!$H:$H,Issuance!$D:$D,Formulas!$B142,Issuance!$C:$C,Formulas!D$2) -> 0 | E142: =SUM(C142:D142) -> 0 | F142: =IF(OR(B142="",B142=0,E142=0),"",IF(COUNTIFS($E$3:$E$500,">"&E142,$E$3:$E$500,"<>0")+1<=20,COUNTIFS($E$3:$E$500,">"&E142,$E$3:$E$500,"<>0")+1,"")) | I142: =SUMIFS(Buybacks!H:H,Buybacks!D:D,Formulas!H142) -> 0 | J142: =IF(OR(H142="",H142=0,I142=0),"",IF(COUNTIFS($I$3:$I$500,"<"&I142,$I$3:$I$500,"<>0")+1<=20,COUNTIFS($I$3:$I$500,"<"&I142,$I$3:$I$500,"<>0")+1,"")) | M142: =SUMIFS('Corporate activity'!$H:$H,'Corporate activity'!$D:$D,Formulas!$L142,'Corporate activity'!$C:$C,Formulas!M$2) -> 0 | N142: =SUMIFS('Corporate activity'!$H:$H,'Corporate activity'!$D:$D,Formulas!$L142,'Corporate activity'!$C:$C,Formulas!N$2) -> 0 | O142: =SUMIFS('Corporate activity'!$H:$H,'Corporate activity'!$D:$D,Formulas!$L142,'Corporate activity'!$C:$C,Formulas!O$2) -> 0 | P142: =SUM(M142:O142) -> 0 | Q142: =IF(OR(L142="",L142=0,P142=0),"",IF(COUNTIFS($P$3:$P$500,"<"&P142,$P$3:$P$500,"<>0")+1<=20,COUNTIFS($P$3:$P$500,"<"&P142,$P$3:$P$500,"<>0")+1,""))
C143: =SUMIFS(Issuance!$H:$H,Issuance!$D:$D,Formulas!$B143,Issuance!$C:$C,Formulas!C$2) -> 0 | D143: =SUMIFS(Issuance!$H:$H,Issuance!$D:$D,Formulas!$B143,Issuance!$C:$C,Formulas!D$2) -> 0 | E143: =SUM(C143:D143) -> 0 | F143: =IF(OR(B143="",B143=0,E143=0),"",IF(COUNTIFS($E$3:$E$500,">"&E143,$E$3:$E$500,"<>0")+1<=20,COUNTIFS($E$3:$E$500,">"&E143,$E$3:$E$500,"<>0")+1,"")) | I143: =SUMIFS(Buybacks!H:H,Buybacks!D:D,Formulas!H143) -> 0 | J143: =IF(OR(H143="",H143=0,I143=0),"",IF(COUNTIFS($I$3:$I$500,"<"&I143,$I$3:$I$500,"<>0")+1<=20,COUNTIFS($I$3:$I$500,"<"&I143,$I$3:$I$500,"<>0")+1,"")) | M143: =SUMIFS('Corporate activity'!$H:$H,'Corporate activity'!$D:$D,Formulas!$L143,'Corporate activity'!$C:$C,Formulas!M$2) -> 0 | N143: =SUMIFS('Corporate activity'!$H:$H,'Corporate activity'!$D:$D,Formulas!$L143,'Corporate activity'!$C:$C,Formulas!N$2) -> 0 | O143: =SUMIFS('Corporate activity'!$H:$H,'Corporate activity'!$D:$D,Formulas!$L143,'Corporate activity'!$C:$C,Formulas!O$2) -> 0 | P143: =SUM(M143:O143) -> 0 | Q143: =IF(OR(L143="",L143=0,P143=0),"",IF(COUNTIFS($P$3:$P$500,"<"&P143,$P$3:$P$500,"<>0")+1<=20,COUNTIFS($P$3:$P$500,"<"&P143,$P$3:$P$500,"<>0")+1,""))
C144: =SUMIFS(Issuance!$H:$H,Issuance!$D:$D,Formulas!$B144,Issuance!$C:$C,Formulas!C$2) -> 0 | D144: =SUMIFS(Issuance!$H:$H,Issuance!$D:$D,Formulas!$B144,Issuance!$C:$C,Formulas!D$2) -> 0 | E144: =SUM(C144:D144) -> 0 | F144: =IF(OR(B144="",B144=0,E144=0),"",IF(COUNTIFS($E$3:$E$500,">"&E144,$E$3:$E$500,"<>0")+1<=20,COUNTIFS($E$3:$E$500,">"&E144,$E$3:$E$500,"<>0")+1,"")) | I144: =SUMIFS(Buybacks!H:H,Buybacks!D:D,Formulas!H144) -> 0 | J144: =IF(OR(H144="",H144=0,I144=0),"",IF(COUNTIFS($I$3:$I$500,"<"&I144,$I$3:$I$500,"<>0")+1<=20,COUNTIFS($I$3:$I$500,"<"&I144,$I$3:$I$500,"<>0")+1,"")) | M144: =SUMIFS('Corporate activity'!$H:$H,'Corporate activity'!$D:$D,Formulas!$L144,'Corporate activity'!$C:$C,Formulas!M$2) -> 0 | N144: =SUMIFS('Corporate activity'!$H:$H,'Corporate activity'!$D:$D,Formulas!$L144,'Corporate activity'!$C:$C,Formulas!N$2) -> 0 | O144: =SUMIFS('Corporate activity'!$H:$H,'Corporate activity'!$D:$D,Formulas!$L144,'Corporate activity'!$C:$C,Formulas!O$2) -> 0 | P144: =SUM(M144:O144) -> 0 | Q144: =IF(OR(L144="",L144=0,P144=0),"",IF(COUNTIFS($P$3:$P$500,"<"&P144,$P$3:$P$500,"<>0")+1<=20,COUNTIFS($P$3:$P$500,"<"&P144,$P$3:$P$500,"<>0")+1,""))
C145: =SUMIFS(Issuance!$H:$H,Issuance!$D:$D,Formulas!$B145,Issuance!$C:$C,Formulas!C$2) -> 0 | D145: =SUMIFS(Issuance!$H:$H,Issuance!$D:$D,Formulas!$B145,Issuance!$C:$C,Formulas!D$2) -> 0 | E145: =SUM(C145:D145) -> 0 | F145: =IF(OR(B145="",B145=0,E145=0),"",IF(COUNTIFS($E$3:$E$500,">"&E145,$E$3:$E$500,"<>0")+1<=20,COUNTIFS($E$3:$E$500,">"&E145,$E$3:$E$500,"<>0")+1,"")) | I145: =SUMIFS(Buybacks!H:H,Buybacks!D:D,Formulas!H145) -> 0 | J145: =IF(OR(H145="",H145=0,I145=0),"",IF(COUNTIFS($I$3:$I$500,"<"&I145,$I$3:$I$500,"<>0")+1<=20,COUNTIFS($I$3:$I$500,"<"&I145,$I$3:$I$500,"<>0")+1,"")) | M145: =SUMIFS('Corporate activity'!$H:$H,'Corporate activity'!$D:$D,Formulas!$L145,'Corporate activity'!$C:$C,Formulas!M$2) -> 0 | N145: =SUMIFS('Corporate activity'!$H:$H,'Corporate activity'!$D:$D,Formulas!$L145,'Corporate activity'!$C:$C,Formulas!N$2) -> 0 | O145: =SUMIFS('Corporate activity'!$H:$H,'Corporate activity'!$D:$D,Formulas!$L145,'Corporate activity'!$C:$C,Formulas!O$2) -> 0 | P145: =SUM(M145:O145) -> 0 | Q145: =IF(OR(L145="",L145=0,P145=0),"",IF(COUNTIFS($P$3:$P$500,"<"&P145,$P$3:$P$500,"<>0")+1<=20,COUNTIFS($P$3:$P$500,"<"&P145,$P$3:$P$500,"<>0")+1,""))
C146: =SUMIFS(Issuance!$H:$H,Issuance!$D:$D,Formulas!$B146,Issuance!$C:$C,Formulas!C$2) -> 0 | D146: =SUMIFS(Issuance!$H:$H,Issuance!$D:$D,Formulas!$B146,Issuance!$C:$C,Formulas!D$2) -> 0 | E146: =SUM(C146:D146) -> 0 | F146: =IF(OR(B146="",B146=0,E146=0),"",IF(COUNTIFS($E$3:$E$500,">"&E146,$E$3:$E$500,"<>0")+1<=20,COUNTIFS($E$3:$E$500,">"&E146,$E$3:$E$500,"<>0")+1,"")) | I146: =SUMIFS(Buybacks!H:H,Buybacks!D:D,Formulas!H146) -> 0 | J146: =IF(OR(H146="",H146=0,I146=0),"",IF(COUNTIFS($I$3:$I$500,"<"&I146,$I$3:$I$500,"<>0")+1<=20,COUNTIFS($I$3:$I$500,"<"&I146,$I$3:$I$500,"<>0")+1,"")) | M146: =SUMIFS('Corporate activity'!$H:$H,'Corporate activity'!$D:$D,Formulas!$L146,'Corporate activity'!$C:$C,Formulas!M$2) -> 0 | N146: =SUMIFS('Corporate activity'!$H:$H,'Corporate activity'!$D:$D,Formulas!$L146,'Corporate activity'!$C:$C,Formulas!N$2) -> 0 | O146: =SUMIFS('Corporate activity'!$H:$H,'Corporate activity'!$D:$D,Formulas!$L146,'Corporate activity'!$C:$C,Formulas!O$2) -> 0 | P146: =SUM(M146:O146) -> 0 | Q146: =IF(OR(L146="",L146=0,P146=0),"",IF(COUNTIFS($P$3:$P$500,"<"&P146,$P$3:$P$500,"<>0")+1<=20,COUNTIFS($P$3:$P$500,"<"&P146,$P$3:$P$500,"<>0")+1,""))
C147: =SUMIFS(Issuance!$H:$H,Issuance!$D:$D,Formulas!$B147,Issuance!$C:$C,Formulas!C$2) -> 0 | D147: =SUMIFS(Issuance!$H:$H,Issuance!$D:$D,Formulas!$B147,Issuance!$C:$C,Formulas!D$2) -> 0 | E147: =SUM(C147:D147) -> 0 | F147: =IF(OR(B147="",B147=0,E147=0),"",IF(COUNTIFS($E$3:$E$500,">"&E147,$E$3:$E$500,"<>0")+1<=20,COUNTIFS($E$3:$E$500,">"&E147,$E$3:$E$500,"<>0")+1,"")) | I147: =SUMIFS(Buybacks!H:H,Buybacks!D:D,Formulas!H147) -> 0 | J147: =IF(OR(H147="",H147=0,I147=0),"",IF(COUNTIFS($I$3:$I$500,"<"&I147,$I$3:$I$500,"<>0")+1<=20,COUNTIFS($I$3:$I$500,"<"&I147,$I$3:$I$500,"<>0")+1,"")) | M147: =SUMIFS('Corporate activity'!$H:$H,'Corporate activity'!$D:$D,Formulas!$L147,'Corporate activity'!$C:$C,Formulas!M$2) -> 0 | N147: =SUMIFS('Corporate activity'!$H:$H,'Corporate activity'!$D:$D,Formulas!$L147,'Corporate activity'!$C:$C,Formulas!N$2) -> 0 | O147: =SUMIFS('Corporate activity'!$H:$H,'Corporate activity'!$D:$D,Formulas!$L147,'Corporate activity'!$C:$C,Formulas!O$2) -> 0 | P147: =SUM(M147:O147) -> 0 | Q147: =IF(OR(L147="",L147=0,P147=0),"",IF(COUNTIFS($P$3:$P$500,"<"&P147,$P$3:$P$500,"<>0")+1<=20,COUNTIFS($P$3:$P$500,"<"&P147,$P$3:$P$500,"<>0")+1,""))
C148: =SUMIFS(Issuance!$H:$H,Issuance!$D:$D,Formulas!$B148,Issuance!$C:$C,Formulas!C$2) -> 0 | D148: =SUMIFS(Issuance!$H:$H,Issuance!$D:$D,Formulas!$B148,Issuance!$C:$C,Formulas!D$2) -> 0 | E148: =SUM(C148:D148) -> 0 | F148: =IF(OR(B148="",B148=0,E148=0),"",IF(COUNTIFS($E$3:$E$500,">"&E148,$E$3:$E$500,"<>0")+1<=20,COUNTIFS($E$3:$E$500,">"&E148,$E$3:$E$500,"<>0")+1,"")) | I148: =SUMIFS(Buybacks!H:H,Buybacks!D:D,Formulas!H148) -> 0 | J148: =IF(OR(H148="",H148=0,I148=0),"",IF(COUNTIFS($I$3:$I$500,"<"&I148,$I$3:$I$500,"<>0")+1<=20,COUNTIFS($I$3:$I$500,"<"&I148,$I$3:$I$500,"<>0")+1,"")) | M148: =SUMIFS('Corporate activity'!$H:$H,'Corporate activity'!$D:$D,Formulas!$L148,'Corporate activity'!$C:$C,Formulas!M$2) -> 0 | N148: =SUMIFS('Corporate activity'!$H:$H,'Corporate activity'!$D:$D,Formulas!$L148,'Corporate activity'!$C:$C,Formulas!N$2) -> 0 | O148: =SUMIFS('Corporate activity'!$H:$H,'Corporate activity'!$D:$D,Formulas!$L148,'Corporate activity'!$C:$C,Formulas!O$2) -> 0 | P148: =SUM(M148:O148) -> 0 | Q148: =IF(OR(L148="",L148=0,P148=0),"",IF(COUNTIFS($P$3:$P$500,"<"&P148,$P$3:$P$500,"<>0")+1<=20,COUNTIFS($P$3:$P$500,"<"&P148,$P$3:$P$500,"<>0")+1,""))
C149: =SUMIFS(Issuance!$H:$H,Issuance!$D:$D,Formulas!$B149,Issuance!$C:$C,Formulas!C$2) -> 0 | D149: =SUMIFS(Issuance!$H:$H,Issuance!$D:$D,Formulas!$B149,Issuance!$C:$C,Formulas!D$2) -> 0 | E149: =SUM(C149:D149) -> 0 | F149: =IF(OR(B149="",B149=0,E149=0),"",IF(COUNTIFS($E$3:$E$500,">"&E149,$E$3:$E$500,"<>0")+1<=20,COUNTIFS($E$3:$E$500,">"&E149,$E$3:$E$500,"<>0")+1,"")) | I149: =SUMIFS(Buybacks!H:H,Buybacks!D:D,Formulas!H149) -> 0 | J149: =IF(OR(H149="",H149=0,I149=0),"",IF(COUNTIFS($I$3:$I$500,"<"&I149,$I$3:$I$500,"<>0")+1<=20,COUNTIFS($I$3:$I$500,"<"&I149,$I$3:$I$500,"<>0")+1,"")) | M149: =SUMIFS('Corporate activity'!$H:$H,'Corporate activity'!$D:$D,Formulas!$L149,'Corporate activity'!$C:$C,Formulas!M$2) -> 0 | N149: =SUMIFS('Corporate activity'!$H:$H,'Corporate activity'!$D:$D,Formulas!$L149,'Corporate activity'!$C:$C,Formulas!N$2) -> 0 | O149: =SUMIFS('Corporate activity'!$H:$H,'Corporate activity'!$D:$D,Formulas!$L149,'Corporate activity'!$C:$C,Formulas!O$2) -> 0 | P149: =SUM(M149:O149) -> 0 | Q149: =IF(OR(L149="",L149=0,P149=0),"",IF(COUNTIFS($P$3:$P$500,"<"&P149,$P$3:$P$500,"<>0")+1<=20,COUNTIFS($P$3:$P$500,"<"&P149,$P$3:$P$500,"<>0")+1,""))
C150: =SUMIFS(Issuance!$H:$H,Issuance!$D:$D,Formulas!$B150,Issuance!$C:$C,Formulas!C$2) -> 0 | D150: =SUMIFS(Issuance!$H:$H,Issuance!$D:$D,Formulas!$B150,Issuance!$C:$C,Formulas!D$2) -> 0 | E150: =SUM(C150:D150) -> 0 | F150: =IF(OR(B150="",B150=0,E150=0),"",IF(COUNTIFS($E$3:$E$500,">"&E150,$E$3:$E$500,"<>0")+1<=20,COUNTIFS($E$3:$E$500,">"&E150,$E$3:$E$500,"<>0")+1,"")) | I150: =SUMIFS(Buybacks!H:H,Buybacks!D:D,Formulas!H150) -> 0 | J150: =IF(OR(H150="",H150=0,I150=0),"",IF(COUNTIFS($I$3:$I$500,"<"&I150,$I$3:$I$500,"<>0")+1<=20,COUNTIFS($I$3:$I$500,"<"&I150,$I$3:$I$500,"<>0")+1,"")) | M150: =SUMIFS('Corporate activity'!$H:$H,'Corporate activity'!$D:$D,Formulas!$L150,'Corporate activity'!$C:$C,Formulas!M$2) -> 0 | N150: =SUMIFS('Corporate activity'!$H:$H,'Corporate activity'!$D:$D,Formulas!$L150,'Corporate activity'!$C:$C,Formulas!N$2) -> 0 | O150: =SUMIFS('Corporate activity'!$H:$H,'Corporate activity'!$D:$D,Formulas!$L150,'Corporate activity'!$C:$C,Formulas!O$2) -> 0 | P150: =SUM(M150:O150) -> 0 | Q150: =IF(OR(L150="",L150=0,P150=0),"",IF(COUNTIFS($P$3:$P$500,"<"&P150,$P$3:$P$500,"<>0")+1<=20,COUNTIFS($P$3:$P$500,"<"&P150,$P$3:$P$500,"<>0")+1,""))
C151: =SUMIFS(Issuance!$H:$H,Issuance!$D:$D,Formulas!$B151,Issuance!$C:$C,Formulas!C$2) -> 0 | D151: =SUMIFS(Issuance!$H:$H,Issuance!$D:$D,Formulas!$B151,Issuance!$C:$C,Formulas!D$2) -> 0 | E151: =SUM(C151:D151) -> 0 | F151: =IF(OR(B151="",B151=0,E151=0),"",IF(COUNTIFS($E$3:$E$500,">"&E151,$E$3:$E$500,"<>0")+1<=20,COUNTIFS($E$3:$E$500,">"&E151,$E$3:$E$500,"<>0")+1,"")) | I151: =SUMIFS(Buybacks!H:H,Buybacks!D:D,Formulas!H151) -> 0 | J151: =IF(OR(H151="",H151=0,I151=0),"",IF(COUNTIFS($I$3:$I$500,"<"&I151,$I$3:$I$500,"<>0")+1<=20,COUNTIFS($I$3:$I$500,"<"&I151,$I$3:$I$500,"<>0")+1,"")) | M151: =SUMIFS('Corporate activity'!$H:$H,'Corporate activity'!$D:$D,Formulas!$L151,'Corporate activity'!$C:$C,Formulas!M$2) -> 0 | N151: =SUMIFS('Corporate activity'!$H:$H,'Corporate activity'!$D:$D,Formulas!$L151,'Corporate activity'!$C:$C,Formulas!N$2) -> 0 | O151: =SUMIFS('Corporate activity'!$H:$H,'Corporate activity'!$D:$D,Formulas!$L151,'Corporate activity'!$C:$C,Formulas!O$2) -> 0 | P151: =SUM(M151:O151) -> 0 | Q151: =IF(OR(L151="",L151=0,P151=0),"",IF(COUNTIFS($P$3:$P$500,"<"&P151,$P$3:$P$500,"<>0")+1<=20,COUNTIFS($P$3:$P$500,"<"&P151,$P$3:$P$500,"<>0")+1,""))
C152: =SUMIFS(Issuance!$H:$H,Issuance!$D:$D,Formulas!$B152,Issuance!$C:$C,Formulas!C$2) -> 0 | D152: =SUMIFS(Issuance!$H:$H,Issuance!$D:$D,Formulas!$B152,Issuance!$C:$C,Formulas!D$2) -> 0 | E152: =SUM(C152:D152) -> 0 | F152: =IF(OR(B152="",B152=0,E152=0),"",IF(COUNTIFS($E$3:$E$500,">"&E152,$E$3:$E$500,"<>0")+1<=20,COUNTIFS($E$3:$E$500,">"&E152,$E$3:$E$500,"<>0")+1,"")) | I152: =SUMIFS(Buybacks!H:H,Buybacks!D:D,Formulas!H152) -> 0 | J152: =IF(OR(H152="",H152=0,I152=0),"",IF(COUNTIFS($I$3:$I$500,"<"&I152,$I$3:$I$500,"<>0")+1<=20,COUNTIFS($I$3:$I$500,"<"&I152,$I$3:$I$500,"<>0")+1,"")) | M152: =SUMIFS('Corporate activity'!$H:$H,'Corporate activity'!$D:$D,Formulas!$L152,'Corporate activity'!$C:$C,Formulas!M$2) -> 0 | N152: =SUMIFS('Corporate activity'!$H:$H,'Corporate activity'!$D:$D,Formulas!$L152,'Corporate activity'!$C:$C,Formulas!N$2) -> 0 | O152: =SUMIFS('Corporate activity'!$H:$H,'Corporate activity'!$D:$D,Formulas!$L152,'Corporate activity'!$C:$C,Formulas!O$2) -> 0 | P152: =SUM(M152:O152) -> 0 | Q152: =IF(OR(L152="",L152=0,P152=0),"",IF(COUNTIFS($P$3:$P$500,"<"&P152,$P$3:$P$500,"<>0")+1<=20,COUNTIFS($P$3:$P$500,"<"&P152,$P$3:$P$500,"<>0")+1,""))
C153: =SUMIFS(Issuance!$H:$H,Issuance!$D:$D,Formulas!$B153,Issuance!$C:$C,Formulas!C$2) -> 0 | D153: =SUMIFS(Issuance!$H:$H,Issuance!$D:$D,Formulas!$B153,Issuance!$C:$C,Formulas!D$2) -> 0 | E153: =SUM(C153:D153) -> 0 | F153: =IF(OR(B153="",B153=0,E153=0),"",IF(COUNTIFS($E$3:$E$500,">"&E153,$E$3:$E$500,"<>0")+1<=20,COUNTIFS($E$3:$E$500,">"&E153,$E$3:$E$500,"<>0")+1,"")) | I153: =SUMIFS(Buybacks!H:H,Buybacks!D:D,Formulas!H153) -> 0 | J153: =IF(OR(H153="",H153=0,I153=0),"",IF(COUNTIFS($I$3:$I$500,"<"&I153,$I$3:$I$500,"<>0")+1<=20,COUNTIFS($I$3:$I$500,"<"&I153,$I$3:$I$500,"<>0")+1,"")) | M153: =SUMIFS('Corporate activity'!$H:$H,'Corporate activity'!$D:$D,Formulas!$L153,'Corporate activity'!$C:$C,Formulas!M$2) -> 0 | N153: =SUMIFS('Corporate activity'!$H:$H,'Corporate activity'!$D:$D,Formulas!$L153,'Corporate activity'!$C:$C,Formulas!N$2) -> 0 | O153: =SUMIFS('Corporate activity'!$H:$H,'Corporate activity'!$D:$D,Formulas!$L153,'Corporate activity'!$C:$C,Formulas!O$2) -> 0 | P153: =SUM(M153:O153) -> 0 | Q153: =IF(OR(L153="",L153=0,P153=0),"",IF(COUNTIFS($P$3:$P$500,"<"&P153,$P$3:$P$500,"<>0")+1<=20,COUNTIFS($P$3:$P$500,"<"&P153,$P$3:$P$500,"<>0")+1,""))
... C1000: =SUMIFS(Issuance!$H:$H,Issuance!$D:$D,Formulas!$B1000,Issuance!$C:$C,Formulas!C$2) -> 0 | D1000: =SUMIFS(Issuance!$H:$H,Issuance!$D:$D,Formulas!$B1000,Issuance!$C:$C,Formulas!D$2) -> 0 | E1000: =SUM(C1000:D1000) -> 0 | F1000: =IF(OR(B1000="",B1000=0,E1000=0),"",IF(COUNTIFS($E$3:$E$500,">"&E1000,$E$3:$E$500,"<>0")+1<=20,COUNTIFS($E$3:$E$500,">"&E1000,$E$3:$E$500,"<>0")+1,"")) | I1000: =SUMIFS(Buybacks!H:H,Buybacks!D:D,Formulas!H1000) -> 0 | J1000: =IF(OR(H1000="",H1000=0,I1000=0),"",IF(COUNTIFS($I$3:$I$500,"<"&I1000,$I$3:$I$500,"<>0")+1<=20,COUNTIFS($I$3:$I$500,"<"&I1000,$I$3:$I$500,"<>0")+1,"")) | M1000: =SUMIFS('Corporate activity'!$H:$H,'Corporate activity'!$D:$D,Formulas!$L1000,'Corporate activity'!$C:$C,Formulas!M$2) -> 0 | N1000: =SUMIFS('Corporate activity'!$H:$H,'Corporate activity'!$D:$D,Formulas!$L1000,'Corporate activity'!$C:$C,Formulas!N$2) -> 0 | O1000: =SUMIFS('Corporate activity'!$H:$H,'Corporate activity'!$D:$D,Formulas!$L1000,'Corporate activity'!$C:$C,Formulas!O$2) -> 0 | P1000: =SUM(M1000:O1000) -> 0 | Q1000: =IF(OR(L1000="",L1000=0,P1000=0),"",IF(COUNTIFS($P$3:$P$500,"<"&P1000,$P$3:$P$500,"<>0")+1<=20,COUNTIFS($P$3:$P$500,"<"&P1000,$P$3:$P$500,"<>0")+1,""))

Sheet Summary
B1: Produced by theaic.co.uk, 1st August 2026. Please note that, whilst we endeavour to verify all data sources, the information contained is not guaranteed to be accurate and the AIC does not accept responsibility for any errors or omissions.
B2: Corporate activity 2026 YTD
B5: IPOs | C5: =SUMIF($B$16:$B$26,"New Issue",$C$16:$C$26) -> 0
B6: Issuance | C6: =SUM($C$17:$C$26)-C5 -> 1473.6761
B7: Buybacks | C7: =ABS(SUMIF($E$17:$E$26,"Buyback",$F$17:$F$26))*-1 -> -5022.2825
B8: Company departures | C8: =SUMIF(E17:E26,"*" & "depart" & "*",$F$17:$F$26)+SUMIF($E$17:$E$26,"*" & "merge" & "*",$F$17:$F$26) -> -5213.7461
B9: Tenders & redemptions | C9: =(SUM($F$17:$F$26))-SUM($C$7:$C$8) -> -3034.3349
B11: TA-(Roll+Bankd)
B16: Event type | C16: Total assets in (£m) | E16: Event type | F16: Total assets out (£m) | H16: Event type | I16: No. of occurrences | K16: VCT event type (by calendar year) | L16: Value (£m) YTD
B17: Issue (from treasury) | C17: =SUMIF(Issuance!C:C,B17,Issuance!H:H) -> 786.20972 | E17: Buyback | F17: =SUM(Buybacks!H:H) -> -5022.2825 | H17: Fee change | I17: =COUNTIF('Corporate activity'!C:C,Summary!H17) -> 23 | K17: Buyback | L17: =SUMIF(VCT!C:C,K17,VCT!Q:Q) -> -104.73905
B18: Issue | C18: =SUMIF(Issuance!C:C,B18,Issuance!H:H) -> 550.95767 | E18: Reconstruct/depart | F18: =IF( SUMIF('Corporate activity'!C:C,E18,'Corporate activity'!H:H)=0, "-",SUMIF('Corporate activity'!C:C,E18,'Corporate activity'!H:H) -SUMIF('Corporate activity'!C:C,E18,'Corporate activity'!I:I) -SUMIF('Corporate activity'!C:C,E18,'Corporate activity'!J:J)) -> -2314.2308 | H18: New management | I18: =COUNTIF('Corporate activity'!C:C,Summary!H18) -> 10 | K18: Tender offer | L18: =SUMIF(VCT!C:C,K18,VCT!Q:Q) -> -9.205706
B19: Issue (C share) | C19: =SUMIF(Issuance!C:C,B19,Issuance!H:H) -> 136.50866 | E19: Depart/liquidate | F19: =IF( SUMIF('Corporate activity'!C:C,E19,'Corporate activity'!H:H)=0, "-",SUMIF('Corporate activity'!C:C,E19,'Corporate activity'!H:H) -SUMIF('Corporate activity'!C:C,E19,'Corporate activity'!I:I) -SUMIF('Corporate activity'!C:C,E19,'Corporate activity'!J:J)) -> -2689.9735 | H19: Investment policy change | I19: =COUNTIF('Corporate activity'!C:C,"Policy change") -> 7
B20: IPO | C20: =SUMIF(Issuance!C:C,"New issue",'Corporate activity'!H:H) -> 0 | E20: Tender offer | F20: =IF(SUMIF('Corporate activity'!C:C,E20,'Corporate activity'!H:H)=0,"-",SUMIF('Corporate activity'!C:C,E20,'Corporate activity'!H:H)) -> -2730.7674 | H20: New name | I20: =COUNTIF('Corporate activity'!C:C,Summary!H20) -> 5 | K20: Tax year | L20: DRIS | M20: Fundraising | N20: Total
E21: Merger | F21: =IF( SUMIF('Corporate activity'!C:C,"Merge/depart",'Corporate activity'!H:H)=0, "-", SUMIF('Corporate activity'!C:C,"Merge/depart",'Corporate activity'!H:H) - SUMIF('Corporate activity'!C:C,"Merge/depart",'Corporate activity'!I:I) - SUMIF('Corporate activity'!C:C,"Merge/depart",'Corporate activity'!J:J)) -> -209.54183 | H21: Capital change | I21: =COUNTIF('Corporate activity'!C:C,Summary!H21) -> 4 | K21: 2025/26 | L21: 61 | M21: 857 | N21: =SUM(L21:M21) -> 918
E22: Capital redemption | F22: =IF(SUMIF('Corporate activity'!C:C,E22,'Corporate activity'!H:H)=0,"-",SUMIF('Corporate activity'!C:C,E22,'Corporate activity'!H:H)) -> -187.55053 | H22: Realisation policy | I22: =COUNTIF('Corporate activity'!C:C,Summary!H22) -> 4 | K22: 2026/27 to date | L22: =SUMIFS(VCT!Q:Q,VCT!N:N,"2026/27",VCT!C:C,"Issue (DRIS)") -> 16.92989 | M22: =SUMIFS(VCT!Q:Q,VCT!N:N,"2026/27",VCT!C:C,"Issue") -> 17.514842 | N22: =SUM(L22:M22) -> 34.444732
E23: Capital distribution | F23: =IF(SUMIF('Corporate activity'!C:C,E23,'Corporate activity'!H:H)=0,"-",SUMIF('Corporate activity'!C:C,E23,'Corporate activity'!H:H)) -> -116.01695 | H23: Listing change | I23: =COUNTIF('Corporate activity'!C:C,Summary!H23) -> 3
H24: Trading status | I24: =COUNTIF('Corporate activity'!C:C,Summary!H24) -> 3 | K24: No. of VCT offers | L24: Current
H25: AIC sector change | I25: =COUNTIF('Corporate activity'!C:C,Summary!H25) -> 2 | K25: Open | L25: =COUNTIF(VCT!C:C,"open offer for subscription") -> 11
H26: Domicile change | I26: =COUNTIF('Corporate activity'!C:C,Summary!H26) -> 1
A27: =MAX(Formulas!F:F) -> 20 | D27: =MAX(Formulas!J:J) -> 20 | G27: =MAX(Formulas!Q:Q) -> 20
A28: 0 | B28: Top 20 companies (Issuance) | C28: Issuance (£m) | D28: 0 | E28: Top 20 companies (Buybacks) | F28: Buybacks (£m) | G28: 0 | H28: Top 20 companies (Other tenders / redemptions) | I28: Other tenders / redemptions (£m) | K28: Company departures | L28: Departure month | M28: Assets at departure (£m)
A29: =IF(OR($A28="",$A28>$A$27-1),"",$A28+1) -> 1 | B29: =IF($A29="","",_xlfn.XLOOKUP($A29,Formulas!$F:$F,Formulas!$B:$B)) -> Scottish Mortgage | C29: =IF($A29="","",_xlfn.XLOOKUP($A29,Formulas!$F:$F,Formulas!$E:$E)) -> 519.08239 | D29: =IF(OR($D28="",$D28>$D$27-1),"",$D28+1) -> 1 | E29: =IF($D29="","",_xlfn.XLOOKUP($D29,Formulas!J:J,Formulas!H:H)) -> Scottish Mortgage | F29: =IF($D29="","",_xlfn.XLOOKUP($D29,Formulas!J:J,Formulas!I:I)) -> -796.68848 | G29: =IF(OR($G28="",$G28>$G$27-1),"",$G28+1) -> 1 | H29: =_xlfn.XLOOKUP(G29,Formulas!Q:Q,Formulas!L:L) -> Herald Investment Trust | I29: =_xlfn.XLOOKUP(G29,Formulas!Q:Q,Formulas!P:P) -> -957.35847 | K29: {=_xlfn.LET(_xlpm.events,'Corporate activity'!$C$4:$C$3000,_xlpm.companies,'Corporate activity'!$D$4:$D$3000,_xlpm.months,'Corporate activity'!$B$4:$B$3000,_xlpm.assets,'Corporate activity'!$H$4:$H$3000-'Corporate activity'!$I$4:$I$3000-'Corporate activity'!$J$4:$J$3000,_xlpm.status,'Corporate activity'!$A$4:$A$3000,_xlpm.include,ISNUMBER(SEARCH("depart",_xlpm.events))*(_xlpm.months<>"TBA")*ISERROR(SEARCH("await",_xlpm.status)),_xlpm.depart,_xlfn._xlws.FILTER(CHOOSE({1,2,3},_xlpm.companies,_xlpm.months,_xlpm.assets),_xlpm.include),_xlfn.UNIQUE(_xlpm.depart))} -> Doric Nimrod Air Three | L29: Jan | M29: -142.347
A30: =IF(OR($A29="",$A29>$A$27-1),"",$A29+1) -> 2 | B30: =IF($A30="","",_xlfn.XLOOKUP($A30,Formulas!$F:$F,Formulas!$B:$B)) -> TwentyFour Income Fund | C30: =IF($A30="","",_xlfn.XLOOKUP($A30,Formulas!$F:$F,Formulas!$E:$E)) -> 110.62046 | D30: =IF(OR($D29="",$D29>$D$27-1),"",$D29+1) -> 2 | E30: =IF($D30="","",_xlfn.XLOOKUP($D30,Formulas!J:J,Formulas!H:H)) -> 3i Group | F30: =IF($D30="","",_xlfn.XLOOKUP($D30,Formulas!J:J,Formulas!I:I)) -> -359.54513 | G30: =IF(OR($G29="",$G29>$G$27-1),"",$G29+1) -> 2 | H30: =_xlfn.XLOOKUP(G30,Formulas!Q:Q,Formulas!L:L) -> Impax Environmental Markets | I30: =_xlfn.XLOOKUP(G30,Formulas!Q:Q,Formulas!P:P) -> -733.2478 | K30: PRS REIT | L30: Jan | M30: -815.37143
A31: =IF(OR($A30="",$A30>$A$27-1),"",$A30+1) -> 3 | B31: =IF($A31="","",_xlfn.XLOOKUP($A31,Formulas!$F:$F,Formulas!$B:$B)) -> Invesco Bond Income Plus | C31: =IF($A31="","",_xlfn.XLOOKUP($A31,Formulas!$F:$F,Formulas!$E:$E)) -> 98.909156 | D31: =IF(OR($D30="",$D30>$D$27-1),"",$D30+1) -> 3 | E31: =IF($D31="","",_xlfn.XLOOKUP($D31,Formulas!J:J,Formulas!H:H)) -> Allianz Technology Trust | F31: =IF($D31="","",_xlfn.XLOOKUP($D31,Formulas!J:J,Formulas!I:I)) -> -160.62452 | G31: =IF(OR($G30="",$G30>$G$27-1),"",$G30+1) -> 3 | H31: =_xlfn.XLOOKUP(G31,Formulas!Q:Q,Formulas!L:L) -> RIT Capital Partners | I31: =_xlfn.XLOOKUP(G31,Formulas!Q:Q,Formulas!P:P) -> -299.99999 | K31: Starwood European Real Estate Finance | L31: Feb | M31: -22.36
A32: =IF(OR($A31="",$A31>$A$27-1),"",$A31+1) -> 4 | B32: =IF($A32="","",_xlfn.XLOOKUP($A32,Formulas!$F:$F,Formulas!$B:$B)) -> Henderson Far East Income | C32: =IF($A32="","",_xlfn.XLOOKUP($A32,Formulas!$F:$F,Formulas!$E:$E)) -> 90.027288 | D32: =IF(OR($D31="",$D31>$D$27-1),"",$D31+1) -> 4 | E32: =IF($D32="","",_xlfn.XLOOKUP($D32,Formulas!J:J,Formulas!H:H)) -> Pantheon International | F32: =IF($D32="","",_xlfn.XLOOKUP($D32,Formulas!J:J,Formulas!I:I)) -> -158.22095 | G32: =IF(OR($G31="",$G31>$G$27-1),"",$G31+1) -> 4 | H32: =_xlfn.XLOOKUP(G32,Formulas!Q:Q,Formulas!L:L) -> Vietnam Enterprise Investments | I32: =_xlfn.XLOOKUP(G32,Formulas!Q:Q,Formulas!P:P) -> -263.55335 | K32: Franklin Global Trust | L32: Feb | M32: -6.23117
A33: =IF(OR($A32="",$A32>$A$27-1),"",$A32+1) -> 5 | B33: =IF($A33="","",_xlfn.XLOOKUP($A33,Formulas!$F:$F,Formulas!$B:$B)) -> City of London Investment Trust | C33: =IF($A33="","",_xlfn.XLOOKUP($A33,Formulas!$F:$F,Formulas!$E:$E)) -> 63.3275 | D33: =IF(OR($D32="",$D32>$D$27-1),"",$D32+1) -> 5 | E33: =IF($D33="","",_xlfn.XLOOKUP($D33,Formulas!J:J,Formulas!H:H)) -> Monks | F33: =IF($D33="","",_xlfn.XLOOKUP($D33,Formulas!J:J,Formulas!I:I)) -> -156.71252 | G33: =IF(OR($G32="",$G32>$G$27-1),"",$G32+1) -> 5 | H33: =_xlfn.XLOOKUP(G33,Formulas!Q:Q,Formulas!L:L) -> BlackRock Smaller Companies | I33: =_xlfn.XLOOKUP(G33,Formulas!Q:Q,Formulas!P:P) -> -162.91717 | K33: Smithson | L33: Feb | M33: -1679
A34: =IF(OR($A33="",$A33>$A$27-1),"",$A33+1) -> 6 | B34: =IF($A34="","",_xlfn.XLOOKUP($A34,Formulas!$F:$F,Formulas!$B:$B)) -> Temple Bar Investment Trust | C34: =IF($A34="","",_xlfn.XLOOKUP($A34,Formulas!$F:$F,Formulas!$E:$E)) -> 59.647078 | D34: =IF(OR($D33="",$D33>$D$27-1),"",$D33+1) -> 6 | E34: =IF($D34="","",_xlfn.XLOOKUP($D34,Formulas!J:J,Formulas!H:H)) -> Mercantile Investment Trust | F34: =IF($D34="","",_xlfn.XLOOKUP($D34,Formulas!J:J,Formulas!I:I)) -> -145.3855 | G34: =IF(OR($G33="",$G33>$G$27-1),"",$G33+1) -> 6 | H34: =_xlfn.XLOOKUP(G34,Formulas!Q:Q,Formulas!L:L) -> Baillie Gifford Shin Nippon | I34: =_xlfn.XLOOKUP(G34,Formulas!Q:Q,Formulas!P:P) -> -57.755505 | K34: abrdn Diversified Income & Growth | L34: Mar | M34: -46.5
A35: =IF(OR($A34="",$A34>$A$27-1),"",$A34+1) -> 7 | B35: =IF($A35="","",_xlfn.XLOOKUP($A35,Formulas!$F:$F,Formulas!$B:$B)) -> CVC Income & Growth | C35: =IF($A35="","",_xlfn.XLOOKUP($A35,Formulas!$F:$F,Formulas!$E:$E)) -> 40.055654 | D35: =IF(OR($D34="",$D34>$D$27-1),"",$D34+1) -> 7 | E35: =IF($D35="","",_xlfn.XLOOKUP($D35,Formulas!J:J,Formulas!H:H)) -> Alliance Witan | F35: =IF($D35="","",_xlfn.XLOOKUP($D35,Formulas!J:J,Formulas!I:I)) -> -141.56233 | G35: =IF(OR($G34="",$G34>$G$27-1),"",$G34+1) -> 7 | H35: =_xlfn.XLOOKUP(G35,Formulas!Q:Q,Formulas!L:L) -> BlackRock Frontiers | I35: =_xlfn.XLOOKUP(G35,Formulas!Q:Q,Formulas!P:P) -> -48.139318 | K35: Shires Income | L35: Mar | M35: -14.279663
A36: =IF(OR($A35="",$A35>$A$27-1),"",$A35+1) -> 8 | B36: =IF($A36="","",_xlfn.XLOOKUP($A36,Formulas!$F:$F,Formulas!$B:$B)) -> Polar Capital Global Healthcare | C36: =IF($A36="","",_xlfn.XLOOKUP($A36,Formulas!$F:$F,Formulas!$E:$E)) -> 39.042794 | D36: =IF(OR($D35="",$D35>$D$27-1),"",$D35+1) -> 8 | E36: =IF($D36="","",_xlfn.XLOOKUP($D36,Formulas!J:J,Formulas!H:H)) -> Finsbury Growth & Income Trust | F36: =IF($D36="","",_xlfn.XLOOKUP($D36,Formulas!J:J,Formulas!I:I)) -> -139.90656 | G36: =IF(OR($G35="",$G35>$G$27-1),"",$G35+1) -> 8 | H36: =_xlfn.XLOOKUP(G36,Formulas!Q:Q,Formulas!L:L) -> Aquila European Renewables | I36: =_xlfn.XLOOKUP(G36,Formulas!Q:Q,Formulas!P:P) -> -46.8 | K36: BlackRock Throgmorton Trust | L36: Apr | M36: -189.031
A37: =IF(OR($A36="",$A36>$A$27-1),"",$A36+1) -> 9 | B37: =IF($A37="","",_xlfn.XLOOKUP($A37,Formulas!$F:$F,Formulas!$B:$B)) -> Invesco Global Equity Income Trust | C37: =IF($A37="","",_xlfn.XLOOKUP($A37,Formulas!$F:$F,Formulas!$E:$E)) -> 29.07668 | D37: =IF(OR($D36="",$D36>$D$27-1),"",$D36+1) -> 9 | E37: =IF($D37="","",_xlfn.XLOOKUP($D37,Formulas!J:J,Formulas!H:H)) -> Templeton Emerging Markets | F37: =IF($D37="","",_xlfn.XLOOKUP($D37,Formulas!J:J,Formulas!I:I)) -> -111.29841 | G37: =IF(OR($G36="",$G36>$G$27-1),"",$G36+1) -> 9 | H37: =_xlfn.XLOOKUP(G37,Formulas!Q:Q,Formulas!L:L) -> AVI Japan Opportunity Trust | I37: =_xlfn.XLOOKUP(G37,Formulas!Q:Q,Formulas!P:P) -> -46.740591 | K37: Hydrogen Capital Growth | L37: Apr | M37: -39.34
A38: =IF(OR($A37="",$A37>$A$27-1),"",$A37+1) -> 10 | B38: =IF($A38="","",_xlfn.XLOOKUP($A38,Formulas!$F:$F,Formulas!$B:$B)) -> Rockwood Strategic | C38: =IF($A38="","",_xlfn.XLOOKUP($A38,Formulas!$F:$F,Formulas!$E:$E)) -> 23.674806 | D38: =IF(OR($D37="",$D37>$D$27-1),"",$D37+1) -> 10 | E38: =IF($D38="","",_xlfn.XLOOKUP($D38,Formulas!J:J,Formulas!H:H)) -> Worldwide Healthcare Trust | F38: =IF($D38="","",_xlfn.XLOOKUP($D38,Formulas!J:J,Formulas!I:I)) -> -103.18445 | G38: =IF(OR($G37="",$G37>$G$27-1),"",$G37+1) -> 10 | H38: =_xlfn.XLOOKUP(G38,Formulas!Q:Q,Formulas!L:L) -> GCP Asset Backed Income | I38: =_xlfn.XLOOKUP(G38,Formulas!Q:Q,Formulas!P:P) -> -44.999564 | K38: Life Science REIT | L38: Apr | M38: -233.1
A39: =IF(OR($A38="",$A38>$A$27-1),"",$A38+1) -> 11 | B39: =IF($A39="","",_xlfn.XLOOKUP($A39,Formulas!$F:$F,Formulas!$B:$B)) -> BlackRock American Income | C39: =IF($A39="","",_xlfn.XLOOKUP($A39,Formulas!$F:$F,Formulas!$E:$E)) -> 21.83832 | D39: =IF(OR($D38="",$D38>$D$27-1),"",$D38+1) -> 11 | E39: =IF($D39="","",_xlfn.XLOOKUP($D39,Formulas!J:J,Formulas!H:H)) -> Baillie Gifford Japan Trust | F39: =IF($D39="","",_xlfn.XLOOKUP($D39,Formulas!J:J,Formulas!I:I)) -> -97.394717 | G39: =IF(OR($G38="",$G38>$G$27-1),"",$G38+1) -> 11 | H39: =_xlfn.XLOOKUP(G39,Formulas!Q:Q,Formulas!L:L) -> JPMorgan Global Core Real Assets | I39: =_xlfn.XLOOKUP(G39,Formulas!Q:Q,Formulas!P:P) -> -44.547622 | K39: Augmentum Fintech | L39: May | M39: -266.81
A40: =IF(OR($A39="",$A39>$A$27-1),"",$A39+1) -> 12 | B40: =IF($A40="","",_xlfn.XLOOKUP($A40,Formulas!$F:$F,Formulas!$B:$B)) -> TwentyFour Select Monthly Income | C40: =IF($A40="","",_xlfn.XLOOKUP($A40,Formulas!$F:$F,Formulas!$E:$E)) -> 21.376325 | D40: =IF(OR($D39="",$D39>$D$27-1),"",$D39+1) -> 12 | E40: =IF($D40="","",_xlfn.XLOOKUP($D40,Formulas!J:J,Formulas!H:H)) -> Scottish American | F40: =IF($D40="","",_xlfn.XLOOKUP($D40,Formulas!J:J,Formulas!I:I)) -> -96.787294 | G40: =IF(OR($G39="",$G39>$G$27-1),"",$G39+1) -> 12 | H40: =_xlfn.XLOOKUP(G40,Formulas!Q:Q,Formulas!L:L) -> abrdn Diversified Income & Growth | I40: =_xlfn.XLOOKUP(G40,Formulas!Q:Q,Formulas!P:P) -> -43.7 | K40: Bailiwick Investments | L40: May | M40: -81.560783
A41: =IF(OR($A40="",$A40>$A$27-1),"",$A40+1) -> 13 | B41: =IF($A41="","",_xlfn.XLOOKUP($A41,Formulas!$F:$F,Formulas!$B:$B)) -> Schiehallion Fund | C41: =IF($A41="","",_xlfn.XLOOKUP($A41,Formulas!$F:$F,Formulas!$E:$E)) -> 20.745694 | D41: =IF(OR($D40="",$D40>$D$27-1),"",$D40+1) -> 13 | E41: =IF($D41="","",_xlfn.XLOOKUP($D41,Formulas!J:J,Formulas!H:H)) -> Pershing Square Holdings | F41: =IF($D41="","",_xlfn.XLOOKUP($D41,Formulas!J:J,Formulas!I:I)) -> -95.952901 | G41: =IF(OR($G40="",$G40>$G$27-1),"",$G40+1) -> 13 | H41: =_xlfn.XLOOKUP(G41,Formulas!Q:Q,Formulas!L:L) -> Bellevue Healthcare Trust | I41: =_xlfn.XLOOKUP(G41,Formulas!Q:Q,Formulas!P:P) -> -41.807385 | K41: Amedeo Air Four Plus | L41: Jun | M41: -789.30927
... A43: =IF(OR($A42="",$A42>$A$27-1),"",$A42+1) -> 15 | B43: =IF($A43="","",_xlfn.XLOOKUP($A43,Formulas!$F:$F,Formulas!$B:$B)) -> Murray International | C43: =IF($A43="","",_xlfn.XLOOKUP($A43,Formulas!$F:$F,Formulas!$E:$E)) -> 18.523796 | D43: =IF(OR($D42="",$D42>$D$27-1),"",$D42+1) -> 15 | E43: =IF($D43="","",_xlfn.XLOOKUP($D43,Formulas!J:J,Formulas!H:H)) -> Edinburgh Investment Trust | F43: =IF($D43="","",_xlfn.XLOOKUP($D43,Formulas!J:J,Formulas!I:I)) -> -85.722487 | G43: =IF(OR($G42="",$G42>$G$27-1),"",$G42+1) -> 15 | H43: =_xlfn.XLOOKUP(G43,Formulas!Q:Q,Formulas!L:L) -> BlackRock Latin American | I43: =_xlfn.XLOOKUP(G43,Formulas!Q:Q,Formulas!P:P) -> -32.590349 | K43: Bluefield Solar Income Fund | L43: Jul | M43: -607.27576
A44: =IF(OR($A43="",$A43>$A$27-1),"",$A43+1) -> 16 | B44: =IF($A44="","",_xlfn.XLOOKUP($A44,Formulas!$F:$F,Formulas!$B:$B)) -> CQS New City High Yield Fund | C44: =IF($A44="","",_xlfn.XLOOKUP($A44,Formulas!$F:$F,Formulas!$E:$E)) -> 17.700425 | D44: =IF(OR($D43="",$D43>$D$27-1),"",$D43+1) -> 16 | E44: =IF($D44="","",_xlfn.XLOOKUP($D44,Formulas!J:J,Formulas!H:H)) -> HarbourVest Global Private Equity | F44: =IF($D44="","",_xlfn.XLOOKUP($D44,Formulas!J:J,Formulas!I:I)) -> -80.046921 | G44: =IF(OR($G43="",$G43>$G$27-1),"",$G43+1) -> 16 | H44: =_xlfn.XLOOKUP(G44,Formulas!Q:Q,Formulas!L:L) -> Riverstone Energy | I44: =_xlfn.XLOOKUP(G44,Formulas!Q:Q,Formulas!P:P) -> -29.999035
A45: =IF(OR($A44="",$A44>$A$27-1),"",$A44+1) -> 17 | B45: =IF($A45="","",_xlfn.XLOOKUP($A45,Formulas!$F:$F,Formulas!$B:$B)) -> Personal Assets Trust | C45: =IF($A45="","",_xlfn.XLOOKUP($A45,Formulas!$F:$F,Formulas!$E:$E)) -> 14.801727 | D45: =IF(OR($D44="",$D44>$D$27-1),"",$D44+1) -> 17 | E45: =IF($D45="","",_xlfn.XLOOKUP($D45,Formulas!J:J,Formulas!H:H)) -> Fidelity European | F45: =IF($D45="","",_xlfn.XLOOKUP($D45,Formulas!J:J,Formulas!I:I)) -> -77.137178 | G45: =IF(OR($G44="",$G44>$G$27-1),"",$G44+1) -> 17 | H45: =_xlfn.XLOOKUP(G45,Formulas!Q:Q,Formulas!L:L) -> Digital 9 Infrastructure | I45: =_xlfn.XLOOKUP(G45,Formulas!Q:Q,Formulas!P:P) -> -29.996543
A46: =IF(OR($A45="",$A45>$A$27-1),"",$A45+1) -> 18 | B46: =IF($A46="","",_xlfn.XLOOKUP($A46,Formulas!$F:$F,Formulas!$B:$B)) -> Odyssean Investment Trust | C46: =IF($A46="","",_xlfn.XLOOKUP($A46,Formulas!$F:$F,Formulas!$E:$E)) -> 12.324713 | D46: =IF(OR($D45="",$D45>$D$27-1),"",$D45+1) -> 18 | E46: =IF($D46="","",_xlfn.XLOOKUP($D46,Formulas!J:J,Formulas!H:H)) -> Bankers | F46: =IF($D46="","",_xlfn.XLOOKUP($D46,Formulas!J:J,Formulas!I:I)) -> -77.113361 | G46: =IF(OR($G45="",$G45>$G$27-1),"",$G45+1) -> 18 | H46: =_xlfn.XLOOKUP(G46,Formulas!Q:Q,Formulas!L:L) -> Phoenix Spree Deutschland | I46: =_xlfn.XLOOKUP(G46,Formulas!Q:Q,Formulas!P:P) -> -17.500001
A47: =IF(OR($A46="",$A46>$A$27-1),"",$A46+1) -> 19 | B47: =IF($A47="","",_xlfn.XLOOKUP($A47,Formulas!$F:$F,Formulas!$B:$B)) -> Nippon Active Value Fund | C47: =IF($A47="","",_xlfn.XLOOKUP($A47,Formulas!$F:$F,Formulas!$E:$E)) -> 11.6601 | D47: =IF(OR($D46="",$D46>$D$27-1),"",$D46+1) -> 19 | E47: =IF($D47="","",_xlfn.XLOOKUP($D47,Formulas!J:J,Formulas!H:H)) -> Polar Capital Technology | F47: =IF($D47="","",_xlfn.XLOOKUP($D47,Formulas!J:J,Formulas!I:I)) -> -75.04768 | G47: =IF(OR($G46="",$G46>$G$27-1),"",$G46+1) -> 19 | H47: =_xlfn.XLOOKUP(G47,Formulas!Q:Q,Formulas!L:L) -> abrdn European Logistics Income | I47: =_xlfn.XLOOKUP(G47,Formulas!Q:Q,Formulas!P:P) -> -16.5
A48: =IF(OR($A47="",$A47>$A$27-1),"",$A47+1) -> 20 | B48: =IF($A48="","",_xlfn.XLOOKUP($A48,Formulas!$F:$F,Formulas!$B:$B)) -> Ceiba Investments | C48: =IF($A48="","",_xlfn.XLOOKUP($A48,Formulas!$F:$F,Formulas!$E:$E)) -> 10.46304 | D48: =IF(OR($D47="",$D47>$D$27-1),"",$D47+1) -> 20 | E48: =IF($D48="","",_xlfn.XLOOKUP($D48,Formulas!J:J,Formulas!H:H)) -> Fidelity Emerging Markets | F48: =IF($D48="","",_xlfn.XLOOKUP($D48,Formulas!J:J,Formulas!I:I)) -> -70.850708 | G48: =IF(OR($G47="",$G47>$G$27-1),"",$G47+1) -> 20 | H48: =_xlfn.XLOOKUP(G48,Formulas!Q:Q,Formulas!L:L) -> RM Infrastructure Income | I48: =_xlfn.XLOOKUP(G48,Formulas!Q:Q,Formulas!P:P) -> -12.379

Sheet Corporate activity
A1: Produced by theaic.co.uk, 1st August 2026. Please note that, whilst we endeavour to verify all data sources, the information contained is not guaranteed to be accurate and the AIC does not accept responsibility for any errors or omissions.
A2: "Await" entries are taken from the company news announcements and are still to be finalised - therefore they may be subject to change.
A3: Year | B3: Month | C3: Event | D3: Company name | E3: Management group | F3: AIC sector | G3: Additional | H3: Total assets (£m) | I3: Rollover assets (£m) | J3: Bank debt (£m) | K3: Other info | L3: Domicile | M3: Listing
A4: 2026 | B4: Jan | C4: Capital Distribution | D4: Aquila European Renewables | E4: Aquila Capital Investment | F4: Renewable Energy Infrastructure | G4: The company made a capital distribution of approximately €34,000,00 (£29,400,000) to shareholders by way of an issue and subsequent repurchase of B shares on 29/01/2026. | H4: -29.4 | L4: UK | M4: MAIN
A5: 2026 | B5: Jan | C5: Capital Distribution | D5: LMS Capital | E5: LMS Capital | F5: Private Equity | G5: The company made a capital distribution of £1,614,549 to shareholders by way of an issue and subsequent repurchase of B shares on 19/01/2025. | H5: -1.614549 | L5: UK | M5: MAIN
A6: 2026 | B6: Jan | C6: Capital Redemption | D6: Ashoka WhiteOak Emerging Markets | E6: Acorn Asset Management | F6: Global Emerging Markets | G6: 92,088 shares redeemed at a price of 148.99p per share resulting in £137,202 departing on 15/01/2025. | H6: -0.137202 | L6: UK | M6: MAIN
A7: 2026 | B7: Jan | C7: Capital Redemption | D7: JPEL Private Equity | E7: Fortress Investment Group | F7: Private Equity | G7: 4,545,267 shares redeemed at a price of 98p per share resulting in £4,461,816 departing on 13/01/2025. | H7: -4.461816 | L7: GUE | M7: MAIN
A8: 2026 | B8: Jan | C8: Depart/Liquidate | D8: Doric Nimrod Air Three | E8: Doric Partners | F8: Leasing | G8: Liquidated. No rollover vehicle. Cancellation was effective on 16/01/2026. | H8: -142.347 | I8: 0 | J8: 0 | L8: GUE | M8: SFS
A9: 2026 | B9: Jan | C9: Depart/Liquidate | D9: PRS REIT | E9: Sigma Capital | F9: Property - UK Residential | G9: Liquidated. No rollover vehicle. Cancellation was effective on 06/01/2026. | H9: -1141.52 | I9: 0 | J9: -326.14857 | K9: UK REIT | L9: UK | M9: SFS
A10: 2026 | B10: Jan | C10: Fee change | D10: Aberdeen Equity Income Trust | E10: Aberdeen | F10: UK Equity Income | G10: The company has changed its management fee. Base fee: no change. The change is effective from 13/02/2026. | K10: Addition of a fixed £120,000 fee | L10: UK | M10: MAIN
A11: 2026 | B11: Jan | C11: Fee change | D11: Athelney Trust | E11: EC Pohl & Co Pty | F11: UK Smaller Companies | G11: The company has changed its management fee. Base fee: no change, Performance fee: introduced. The change is effective from 01/01/2026. | L11: UK | M11: MAIN
A12: 2026 | B12: Jan | C12: Fee change | D12: Develop North | E12: Tier One Capital | F12: Property - Debt | G12: The company has changed its management fee. Base fee: reduced, Tiered fee: changed. The change is effective from 18/02/2026. | L12: UK | M12: MAIN
A13: 2026 | B13: Jan | C13: Listing Change | D13: Aquila European Renewables | E13: Aquila Capital Investment | F13: Renewable Energy Infrastructure | G13: The company cancelled its listing on Euronext Growth Dublin on 19/01/26. The company will retain its listing on the Premium Segment of the Main exchange of the London Stock Exchange. | L13: UK | M13: MAIN
A14: 2026 | B14: Jan | C14: Management Change | D14: Global Opportunities | E14: Global Opportunities | F14: Global | G14: to Goodhart Partners. Company is no longer self-managed. | K14: History remains | L14: UK | M14: MAIN
A15: 2026 | B15: Jan | C15: Management Change | D15: Volta Finance | E15: AXA Investment Managers | F15: Debt - Structured Finance | G15: to BNP Paribas Asset Management | K15: History remains | L15: GUE | M15: MAIN/EURONEXT
A16: 2026 | B16: Jan | C16: MG Merge | D16: N/A | E16: BNP Paribas Asset Management | G16: AXA Investment Managers Paris merged with BNP Asset management | L16: N/A | M16: N/A
A17: 2026 | B17: Jan | C17: MG Name Change | D17: N/A | E17: SVM Asset Management | G17: to RGI Fund Management | L17: N/A | M17: N/A
A18: 2026 | B18: Jan | C18: MG New Name | D18: N/A | E18: RGI Fund Management | G18: from SVM Asset Management | L18: N/A | M18: N/A
A19: 2026 | B19: Jan | C19: Name Change | D19: JPMorgan Global Emerging Markets Income | E19: J.P. Morgan Asset Management | F19: Global Emerging Markets | G19: to JPMorgan Emerging Markets Dividend Income | L19: UK | M19: MAIN
A20: 2026 | B20: Jan | C20: New Management | D20: Global Opportunities | E20: Goodhart Partners | F20: Global | G20: from Global Opportunities. Company is no longer self-managed. | K20: History remains | L20: UK | M20: MAIN
A21: 2026 | B21: Jan | C21: New Management | D21: Volta Finance | E21: BNP Paribas Asset Management | F21: Debt - Structured Finance | G21: from AXA Investment Managers | K21: History remains | L21: GUE | M21: MAIN/EURONEXT
A22: 2026 | B22: Jan | C22: New Name | D22: JPMorgan Emerging Markets Dividend Income | E22: J.P. Morgan Asset Management | F22: Global Emerging Markets | G22: from JPMorgan Global Emerging Markets Income | L22: UK | M22: MAIN
A23: 2026 | B23: Jan | C23: Tender Offer | D23: AVI Japan Opportunity Trust | E23: Asset Value Investors | F23: Japanese Smaller Companies | G23: 26,899,713 shares tendered at a price of 173.76p per share resulting in £46,740,591 departing. | H23: -46.740591 | L23: UK | M23: MAIN
A24: 2026 | B24: Jan | C24: Tender Offer | D24: TwentyFour Select Monthly Income | E24: TwentyFour Asset Management | F24: Debt - Loans & Bonds | G24: 303,278 shares tendered at a price of 87.07p per share resulting in £264,064 departing. | H24: -0.264064 | L24: GUE | M24: MAIN
A25: 2026 | B25: Jan | C25: Tender Offer | D25: Vietnam Enterprise Investments | E25: Dragon Capital | F25: Country Specialist | G25: 16,108,143 shares tendered at a price of 914.82p per share resulting in £147,360,514 departing. | H25: -147.36051 | L25: CAY | M25: MAIN
A26: 2026 | B26: Feb | C26: Capital Distribution | D26: abrdn Diversified Income & Growth | E26: abrdn | F26: Flexible Investment | G26: The company made a capital distribution of £43,700,000 to shareholders by way of an issue and subsequent repurchase of B shares on 27/02/2025. | H26: -43.7 | L26: UK | M26: MAIN
A27: 2026 | B27: Feb | C27: Capital Redemption | D27: JPMorgan Global Core Real Assets | E27: J.P. Morgan Asset Management | F27: Flexible Investment | G27: 21,827,843 shares redeemed at a price of 94.06p per share resulting in £20,530,355 departing on 06/02/2025. | H27: -20.530355 | L27: GUE | M27: MAIN
A28: 2026 | B28: Feb | C28: Depart/Liquidate | D28: Starwood European Real Estate Finance | E28: Starwood European Finance Partners | F28: Property - Debt | G28: Liquidated. No rollover vehicle. Cancellation was effective on 27/02/2026. | H28: -22.36 | I28: 0 | J28: 0 | L28: GUE | M28: MAIN
A29: 2026 | B29: Feb | C29: Domicile Change | D29: Schiehallion Fund | E29: Baillie Gifford | F29: Growth Capital | G29: The company has re-domiciled to the UK from Guernsey. | L29: UK | M29: MAIN
A30: 2026 | B30: Feb | C30: Fee change | D30: BlackRock Throgmorton Trust | E30: BlackRock Investment Management (UK) | F30: UK Smaller Companies | G30: The company has changed its management fee. Base fee: increased, Performance fee: removed, Fee basis change from total assets to net assets. The change is effective from 10/04/2026. | L30: UK | M30: MAIN
A31: 2026 | B31: Feb | C31: Fee change | D31: Pantheon International | E31: Pantheon Ventures | F31: Private Equity | G31: The company has changed its management fee. Base fee: reduced, Performance fee: no change, Tiered fee: removed. The change is effective from 01/06/2026. | L31: UK | M31: MAIN
A32: 2026 | B32: Feb | C32: Merge | D32: Invesco Global Equity Income Trust | E32: Invesco Asset Management | F32: Global Equity Income | G32: The company merged with Franklin Global Trust , with Invesco Global Equity Income Trust being the continuing company. Franklin Global shareholders were entitled receive new IGET shares and/or cash. Shareholders approved the scheme at the general meeting held on 18/02/2026. | H32: 162.17883 | I32: 162.17883 | J32: 0 | L32: UK | M32: MAIN
A33: 2026 | B33: Feb | C33: Merge/Depart | D33: Franklin Global Trust | E33: Franklin Templeton Investments | F33: Global | G33: The company merged with Invesco Global Equity Income Trust, with Invesco Global Equity Income Trust being the continuing company. Franklin Global shareholders were entitled receive new IGET shares and/or cash. Shareholders approved the scheme at the general meeting held on 18/02/2026. | H33: -168.41 | I33: -162.17883 | J33: 0 | L33: UK | M33: MAIN
A34: 2026 | B34: Feb | C34: Reconstruct/Depart | D34: Smithson | E34: Fundsmith | F34: Global Smaller Companies | G34: Liquidated. The company wound up into a new open-ended fund, with 58.64% of shares opting for a cash exit. The scheme resolutions passed at the general meetings, the first of which was held on 10/02/2026 and the second on 25/02/2026, with the expected scheme effective date and liquidators appointed on 27/02/2026. | H34: -1679 | I34: 0 | J34: 0 | L34: UK | M34: MAIN
A35: 2026 | B35: Feb | C35: Tender Offer | D35: Strategic Equity Capital | E35: Gresham House Asset Management | F35: UK Smaller Companies | G35: 2,444,164 shares at an average price of 410p per share resulting in £10,021,072 departing. | H35: -10.021072 | L35: UK | M35: MAIN
A36: 2026 | B36: Mar | C36: Capital Distribution | D36: Aquila European Renewables | E36: Aquila Capital Investment | F36: Renewable Energy Infrastructure | G36: The company made a capital distribution of approximately €20,000,000 (£17,400,000) to shareholders by way of an issue and subsequent repurchase of B shares on 26/03/2026. | H36: -17.4 | L36: UK | M36: MAIN
A37: 2026 | B37: Mar | C37: Capital Redemption | D37: Riverstone Credit Opportunities Income | E37: Riverstone Investment Group | F37: Debt - Loans & Bonds | G37: 12,134,802 shares redeemed at a price of $0.89 per share resulting in $10,799,974 (£8,115,559) departing on 30/03/2025. | H37: -8.113455 | L37: UK | M37: SFS
A38: 2026 | B38: Mar | C38: Depart/Liquidate | D38: abrdn Diversified Income & Growth | E38: abrdn | F38: Flexible Investment | G38: Liquidated. No rollover vehicle. Cancellation was effective on 30/03/2026. | H38: -46.5 | I38: 0 | J38: 0 | L38: UK | M38: MAIN
A39: 2026 | B39: Mar | C39: Fee change | D39: Alliance Witan | E39: Willis Towers Watson | F39: Global | G39: The company has changed its management fee. Base fee: reduced. The change is effective from 01/01/2027. | L39: UK | M39: MAIN
A40: 2026 | B40: Mar | C40: Fee change | D40: Alliance Witan | E40: Willis Towers Watson | F40: Global | G40: The company has changed its management fee. Base fee: reduced, Tiered fee: removed. The change is effective from 01/04/2026. | L40: UK | M40: MAIN
A41: 2026 | B41: Mar | C41: Fee change | D41: Henderson High Income | E41: Janus Henderson Investors | F41: UK Equity & Bond Income | G41: The company has changed its management fee. Base fee: changed, Fee basis change from total assets to net assets. The change is effective from 01/01/2026. | L41: UK | M41: MAIN
A42: 2026 | B42: Mar | C42: Fee change | D42: Scottish Oriental Smaller Companies | E42: FSSA IM | F42: Asia Pacific Smaller Companies | G42: The company has changed its management fee. Base fee: reduced, Performance fee: removed, Tiered fee: introduced, Fee basis change from net assets to net assets and market cap. The change is effective from 01/03/2026. | L42: UK | M42: MAIN
A43: 2026 | B43: Mar | C43: Fee change | D43: STS Global Income & Growth Trust | E43: Troy Asset Management | F43: Global Equity Income | G43: The company has changed its management fee. Base fee: reduced, Tiered fee: removed. The change is effective from 01/04/2026. | L43: UK | M43: MAIN
A44: 2026 | B44: Mar | C44: Fee change | D44: Triple Point Venture VCT Venture shares | E44: Triple Point Investment Management | F44: VCT | G44: The company has changed its management fee. Base fee: no change, Performance fee: changed. The change is effective from 31/03/2026. | K44: The company plans to replace its current performance fee arrangement with a performance fee that only pays the manager if the assets are sold and shareholders receive a minimum level of returns. If those returns are achieved, the manager will receive 15–20% of the proceeds above certain hurdle levels based on NAV. | L44: UK | M44: MAIN
A45: 2026 | B45: Mar | C45: Management Change | D45: Bellevue Healthcare Trust | E45: Bellevue Asset Management | F45: Biotechnology & Healthcare | G45: to Columbia Threadneedle | K45: History remains | L45: UK | M45: MAIN
A46: 2026 | B46: Mar | C46: Management Change | D46: Murray Income | E46: Aberdeen | F46: UK Equity Income | G46: to Artemis Fund Management | K46: History remains | L46: UK | M46: MAIN
A47: 2026 | B47: Mar | C47: Merge | D47: Aberdeen Equity Income Trust | E47: Aberdeen | F47: UK Equity Income | G47: The company merged with Shires Income with Aberdeen Equity Income Trust being the continuing company. Shareholders were entitled to elect to rollover their shares or a cash exit. The implementation of the proposals was conditional upon approval from the company's shareholders at the general meeting held on 09/03/2026, and from Shires shareholders on 09/03/2026 and 13/03/2026. | H47: 115 | I47: 115 | J47: 0 | L47: UK | M47: MAIN
A48: 2026 | B48: Mar | C48: Merge/Depart | D48: Shires Income | E48: Aberdeen | F48: UK Equity Income | G48: The company merged with Aberdeen Equity Income Trust with Aberdeen Equity Income Trust being the continuing company. Shareholders were entitled to elect to rollover their shares or a cash exit. The implementation of the proposals was conditional upon approval from the company's shareholders at the general meeting held on 09/03/2026, and from Shires shareholders on 09/03/2026 and 13/03/2026. | H48: -129.27966 | I48: -115 | J48: 0 | L48: UK | M48: MAIN
A49: 2026 | B49: Mar | C49: Name Change | D49: Bellevue Healthcare Trust | E49: Columbia Threadneedle | F49: Biotechnology & Healthcare | G49: to CT Healthcare Trust | L49: UK | M49: MAIN
A50: 2026 | B50: Mar | C50: New Management | D50: Bellevue Healthcare Trust | E50: Columbia Threadneedle | F50: Biotechnology & Healthcare | G50: from Bellevue Asset Management | K50: History remains | L50: UK | M50: MAIN
A51: 2026 | B51: Mar | C51: New Management | D51: Murray Income | E51: Artemis Fund Managers | F51: UK Equity Income | G51: from Aberdeen | K51: History remains | L51: UK | M51: MAIN
A52: 2026 | B52: Mar | C52: New Name | D52: CT Healthcare Trust | E52: Columbia Threadneedle | F52: Biotechnology & Healthcare | G52: from Bellevue Healthcare Trust | L52: UK | M52: MAIN
A53: 2026 | B53: Mar | C53: Policy Change | D53: CT Healthcare Trust | E53: Columbia Threadneedle | F53: Biotechnology & Healthcare | G53: At the general meeting held on 04/03/2026 shareholders approved proposals to amend the company's investment policy and objective. The company's new objective is to invest in an actively managed portfolio of equities and derivatives with exposure to the global healthcare market. The company seeks to invest in a diversified portfolio of equity or equity-linked securities, including short positions in stocks or markets that Columbia Threadneedle, as investment manager, considers to be over-valued, impaired or where desirable for the purposes of hedging and risk control. The company defines the "global healthcare market" as businesses operating in, having revenues predominantly arising from or otherwise having significant exposure to healthcare and healthcare-related sectors including, in particular, biotechnology, healthcare information technology, healthcare providers, healthcare services, life sciences, managed care providers, medical diagnostics, medical equipment, and pharmaceuticals. | K53: History remains | L53: UK | M53: MAIN
A54: 2026 | B54: Mar | C54: Policy Change | D54: Syncona | E54: Syncona | F54: Biotechnology & Healthcare | G54: At the general meeting held on 03/03/2026 shareholders approved proposals to amend the company's investment policy and objective. The company will focus on achieving long-term capital appreciation by funding new life science investments and existing portfolio companies and consult shareholders on a new capital allocation policy. These long-term incentive arrangements aim to align rewards with portfolio asset realization, incentivize realized returns, and increase the investment manager's equity exposure without diluting shareholders. | K54: History remains | L54: GUE | M54: MAIN
A55: 2026 | B55: Mar | C55: Realisation policy | D55: Chrysalis Investments | E55: Chrysalis Investment Partners | F55: Growth Capital | G55: At the general meeting held on 24/03/2026, shareholders approved proposals to amend its investment objective and investment policy to implement an orderly realisation programme for the portfolio assets in a way that is designed to maximise returns of capital to shareholders over a three-year time horizon, while avoiding forced or value-destructive disposals. | L55: GUE | M55: MAIN
A56: 2026 | B56: Mar | C56: Tender Offer | D56: Baillie Gifford Shin Nippon | E56: Baillie Gifford | F56: Japanese Smaller Companies | G56: 36,798,009 shares tendered at a price of 156.9528p per share resulting in £57,755,505 departing on 10/03/26. | H56: -57.755505 | L56: UK | M56: MAIN
A57: 2026 | B57: Mar | C57: Tender Offer | D57: Bellevue Healthcare Trust | E57: Columbia Threadneedle | F57: Biotechnology & Healthcare | G57: 29,922,562 shares tendered at a price of 139.72p per share resulting in £41,807,385 (40.9% of the company's issued share capital) departing on 06/03/26. | H57: -41.807385 | L57: UK | M57: MAIN
A58: 2026 | B58: Mar | C58: Tender Offer | D58: BlackRock Frontiers | E58: BlackRock Investment Management (UK) | F58: Global Emerging Markets | G58: 25,628,728 shares tendered at a price of 187.83p per share resulting in £48,139,318 (40.9% of the company's issued share capital) departing on 06/03/26. | H58: -48.139318 | L58: UK | M58: MAIN
A59: 2026 | B59: Apr | C59: Capital Change | D59: Fair Oaks Income 2021 | E59: Fair Oaks Capital | F59: Debt - Structured Finance | G59: Share consolidation of 1 for 10 on 30/04/2026. The company also redenominated its shares into Euro from USD. | K59: Share consolidation. | L59: GUE | M59: SFS
A60: 2026 | B60: Apr | C60: Capital Redemption | D60: Digital 9 Infrastructure | E60: Triple Point Investment Management | F60: Infrastructure | G60: 323402398 shares redeemed at a price of 9.2753p per share resulting in £29,996,532 departing on 17/04/2026. | H60: -29.996543 | L60: JER | M60: MAIN
A61: 2026 | B61: Apr | C61: Capital Redemption | D61: JPMorgan Global Core Real Assets | E61: J.P. Morgan Asset Management | F61: Flexible Investment | G61: 24,963,977 shares redeemed at a price of 96.21p per share resulting in £24,017,267 departing on 30/04/2026. | H61: -24.017267 | L61: GUE | M61: MAIN
A62: 2026 | B62: Apr | C62: Capital Redemption | D62: Riverstone Energy | E62: Riverstone International | F62: Commodities & Natural Resources | G62: 2,512,482 shares redeemed at a price of £11.94 per share resulting in £29,999,035 departing on 29/04/2026. | H62: -29.999035 | L62: GUE | M62: MAIN
A63: 2026 | B63: Apr | C63: Fee change | D63: JPMorgan US Smaller Companies | E63: J.P. Morgan Asset Management | F63: North American Smaller Companies | G63: The company has changed its management fee. Base fee: changed, Tiered fee: introduced, Fee basis change from total assets to net assets. The change is effective from 01/01/2026. | L63: UK | M63: MAIN
A64: 2026 | B64: Apr | C64: Fee change | D64: Parvus Energy Efficiency Trust | E64: Parvus Energy Efficiency Trust | F64: Renewable Energy Infrastructure | G64: The company has changed its management fee. Base fee: changed, Performance fee: introduced, Tiered fee: removed. The change is effective from 10/04/2026. | L64: UK | M64: MAIN
A65: 2026 | B65: Apr | C65: Fee change | D65: Schroder Japan Trust | E65: Schroder Investment Management | F65: Japan | G65: The company has changed its management fee. Base fee: reduced, Tiered fee: changed, Fee basis change from net assets to net assets and market cap. The change is effective from 01/08/2026. | L65: UK | M65: MAIN
A66: 2026 | B66: Apr | C66: Listing change | D66: Cordiant Digital Infrastructure | E66: Cordiant Capital | F66: Infrastructure | G66: The company's ordinary Shares were admitted to trading on the Main Market of the LSE on 30/04/2026. | L66: GUE | M66: MAIN
A67: 2026 | B67: Apr | C67: Listing change | D67: Onward Opportunities | E67: Dowgate Wealth | F67: UK Smaller Companies | G67: The company's ordinary Shares were admitted to trading on the Main Market of the LSE on 16/04/2025. | L67: GUE | M67: MAIN
A68: 2026 | B68: Apr | C68: Management Change | D68: Aquila Energy Efficiency | E68: Aquila Capital Investment | F68: Renewable Energy Infrastructure | G68: to Parvus Energy Efficiency Trust. The company became self-managed. | K68: History remains | L68: UK | M68: MAIN
A69: 2026 | B69: Apr | C69: Management Change | D69: Crystal Amber Fund | E69: Crystal Amber Asset Management | F69: UK All Companies | G69: to Global Fund Management. | K69: History remains | L69: GUE | M69: AIM
A70: 2026 | B70: Apr | C70: Merge | D70: BlackRock Smaller Companies | E70: BlackRock Investment Management (UK) | F70: UK Smaller Companies | G70: The company merged with BlackRock Throgmorton Trust, with BlackRock Smaller Companies being the continuing company. Throgmorton offered a cash exit opportunity to shareholders for up to 38% of issued share capital, subject to a 1% discount to NAV by way of a tender offer. The company gained shareholder approval at the general meeting held on 30/03/2026, with the scheme effective 16/04/2026. | H70: 308.419 | I70: 308.419 | J70: 0 | L70: UK | M70: MAIN
A71: 2026 | B71: Apr | C71: Merge/Depart | D71: BlackRock Throgmorton Trust | E71: BlackRock Investment Management (UK) | F71: UK Smaller Companies | G71: The company merged with BlackRock Smaller Companies, with BlackRock Smaller Companies being the continuing company. Throgmorton offered a cash exit opportunity to shareholders for up to 38% of issued share capital, subject to a 1% discount to NAV by way of a tender offer. The company gained shareholder approval at the general meeting held on 30/03/2026, with the scheme effective 16/04/2026. | H71: -497.45 | I71: -308.419 | J71: 0 | L71: UK | M71: MAIN
A72: 2026 | B72: Apr | C72: Name change | D72: Aquila Energy Efficiency | E72: Parvus Energy Efficiency Trust | F72: Renewable Energy Infrastructure | G72: from Parvus Energy Efficiency Trust. The company became self-managed. | L72: UK | M72: MAIN
A73: 2026 | B73: Apr | C73: New Management | D73: Aquila Energy Efficiency | E73: Parvus Energy Efficiency Trust | F73: Renewable Energy Infrastructure | G73: from Aquila Capital Investment. The company became self-managed. | K73: History remains | L73: UK | M73: MAIN
A74: 2026 | B74: Apr | C74: New Management | D74: Crystal Amber Fund | E74: Global Fund Management | F74: UK All Companies | G74: from Crystal Amber Asset Management. | K74: History remains | L74: GUE | M74: AIM
A75: 2026 | B75: Apr | C75: New name | D75: Parvus Energy Efficiency Trust | E75: Parvus Energy Efficiency Trust | F75: Renewable Energy Infrastructure | G75: from Aquila Energy Efficiency. | L75: UK | M75: MAIN
A76: 2026 | B76: Apr | C76: Policy change | D76: BlackRock Smaller Companies | E76: BlackRock Investment Management (UK) | F76: UK Smaller Companies | G76: The company has amended its investment policy in connection with the combination of the assets with BlackRock Throgmorton Trust. Under the new investment policy, the Investment Manager will continue to seek to achieve the company's investment objective through investing predominantly in listed UK smaller companies, but will have additional latitude to invest in small cap stocks outside of the Benchmark index and will be able to invest up to 15 per cent. of the company's gross assets, at the time of acquisition, in global small cap stocks which are listed overseas and which do not have a primary or secondary UK listing. | L76: UK | M76: MAIN
A77: 2026 | B77: Apr | C77: Policy Change | D77: Crystal Amber Fund | E77: Crystal Amber Asset Management | F77: UK All Companies | G77: At the general meeting held on 22/04/2026 shareholders approved proposals to amend the company's investment policy. The company has amended its articles and investment policy aiming for capital growth, with new fee arrangements including performance fees settled primarily in shares. | L77: GUE | M77: AIM
A78: 2026 | B78: Apr | C78: Policy Change | D78: Scottish Mortgage | E78: Baillie Gifford | F78: Global | G78: At the general meeting held on 10/04/2026 shareholders approved proposals to amend the company's investment policy and objective. The new policy grants limited additional capacity to permit the Manager to make up to 250 million of additional investment in Private Companies when the Private Companies exposure exceeds (or would exceed) the existing 30% limit. | L78: UK | M78: MAIN
A79: 2026 | B79: Apr | C79: Reconstruct/Depart | D79: Hydrogen Capital Growth | E79: RWC Asset Management | F79: Renewable Energy Infrastructure | G79: The company cancelled its listing of shares from the Main Market of the LSE on 30/04/2026. Following the delisting, the company is expected to re-register as a private limited company, with the intention to facilitate a managed realisation of the company's assets over time, in order to best serve the interests of the shareholders. | H79: -39.34 | I79: 0 | J79: 0 | L79: UK | M79: MAIN
A80: 2026 | B80: Apr | C80: Reconstruct/Depart | D80: Life Science REIT | E80: Ironstone Asset Management Limited | F80: Property - UK commercial | G80: Liquidated. The company's entire issued and to be issued share capital, was acquired by British Land Company. Under the terms, Life Science REIT shareholders will receive 14.1 pence in cash and 0.07 new British Land shares for each Life Science REIT share, representing a premium of approximately 21% to Life Science REIT's closing price on 27/01/2026. The scheme was approved by its shareholders at the court and general meetings held on 19/03/2026, and the court hearing on 19/04/2026, and effective the following day. | H80: -233.1 | I80: 0 | J80: 0 | K80: UK REIT | L80: UK | M80: MAIN
A81: 2026 | B81: Apr | C81: Tender Offer | D81: CVC Income & Growth | E81: CVC Credit Partners | F81: Debt - Loans & Bonds | G81: 3,377 Euro shares and 26,941 Sterling shares tendered at prices of EUR1.0242 and 112.08p respectively, resulting in £33,264 departing. | H81: -0.033264 | L81: JER | M81: MAIN
A82: 2026 | B82: Apr | C82: Tender Offer | D82: Tetragon Financial Group | E82: Tetragon Financial Management | F82: Flexible Investment | G82: 3,773,581 shares tendered at $13.25 per share, resulting in $49,999,948 (£36,888,109) departing via a modified Dutch auction on 14/04/2026. | H82: -36.888 | K82: Dutch Auction | L82: GUE | M82: SFS/EURONEXT
A83: 2026 | B83: Apr | C83: Tender Offer | D83: TwentyFour Select Monthly Income | E83: TwentyFour Asset Management | F83: Debt - Loans & Bonds | G83: 666,341 shares tendered at a price of 80.88p per share resulting in £586,380 departing. | H83: -0.58638 | L83: GUE | M83: MAIN
A84: 2026 | B84: Apr | C84: Trading status | D84: Home REIT | E84: AEW UK Investment Management | F84: Property - UK Residential | G84: The company announced that it has relisted on the Premium Segment of the Main Exchange of the LSE on 29/04/2026 following its period of suspension, which began on 03/01/23. | K84: UK REIT | L84: UK | M84: MAIN
A85: 2026 | B85: May | C85: AIC sector Change | D85: Crystal Amber Fund | E85: Global Fund Management | F85: UK Smaller Companies | G85: to Flexible Investment | K85: History remains | L85: GUE | M85: AIM
A86: 2026 | B86: May | C86: AIC sector Name Change | D86: Biotech Growth Trust | E86: Frostrow Capital | F86: Healthcare & Biotechnology | G86: from Biotechnology & Healthcare. The AIC renamed the sector. | L86: UK | M86: MAIN
A87: 2026 | B87: May | C87: AIC sector Name Change | D87: CT Healthcare Trust | E87: Columbia Threadneedle | F87: Healthcare & Biotechnology | G87: from Biotechnology & Healthcare. The AIC renamed the sector. | L87: UK | M87: MAIN
A88: 2026 | B88: May | C88: AIC sector Name Change | D88: International Biotechnology | E88: Schroders Investment Management | F88: Healthcare & Biotechnology | G88: from Biotechnology & Healthcare. The AIC renamed the sector. | L88: UK | M88: MAIN
A89: 2026 | B89: May | C89: AIC sector Name Change | D89: Polar Capital Global Healthcare | E89: Polar Capital Holdings | F89: Healthcare & Biotechnology | G89: from Biotechnology & Healthcare. The AIC renamed the sector. | L89: UK | M89: MAIN
A90: 2026 | B90: May | C90: AIC sector Name Change | D90: RTW Biotech Opportunities | E90: RTW Investments | F90: Healthcare & Biotechnology | G90: from Biotechnology & Healthcare. The AIC renamed the sector. | L90: GUE | M90: MAIN
A91: 2026 | B91: May | C91: AIC sector Name Change | D91: Syncona | E91: Syncona | F91: Healthcare & Biotechnology | G91: from Biotechnology & Healthcare. The AIC renamed the sector. | L91: GUE | M91: MAIN
A92: 2026 | B92: May | C92: AIC sector Name Change | D92: Worldwide Healthcare Trust | E92: Frostrow Capital | F92: Healthcare & Biotechnology | G92: from Biotechnology & Healthcare. The AIC renamed the sector. | L92: UK | M92: MAIN
A93: 2026 | B93: May | C93: Capital Change | D93: F&C Investment Trust | E93: Columbia Threadneedle | F93: Global | G93: Share split of 4 for 1 on 11/05/2026. | K93: Share split | L93: UK | M93: MAIN/NZ
A94: 2026 | B94: May | C94: Capital Distribution | D94: abrdn European Logistics Income | E94: Aberdeen | F94: Property - Europe | G94: The company made a capital distribution of approximately €19,000,000 (£16,500,000) to shareholders by way of an issue and subsequent repurchase of B shares on 26/03/2026. | H94: -16.5 | L94: UK | M94: MAIN
A95: 2026 | B95: May | C95: Capital Distribution | D95: Ecofin US Renewables Infrastructure | E95: Ecofin US Renewables Infrastructure | F95: Renewable Energy Infrastructure | G95: The company made a capital distribution $10,000,00 (£7,402,397) to shareholders by way of an issue and subsequent repurchase of B shares on 15/05/2026. | H95: -7.4023972 | L95: UK | M95: MAIN
A96: 2026 | B96: May | C96: Depart/Liquidate | D96: Augmentum Fintech | E96: Augmentum Capital | F96: Financials | G96: Liquidated. No rollover vehicle. The entire issued and to be issued ordinary share capital of the company was acquired by Verdane Freya XII Investments AB. Shareholders approved the scheme at the general meeting held on 15/04/2026. The court sanction hearing was held on 11/05/2026, and an effective date 13/05/2026. | H96: -266.81 | I96: 0 | J96: 0 | L96: UK | M96: MAIN
A97: 2026 | B97: May | C97: Fee change | D97: HICL Infrastructure | E97: InfraRed Capital Partners | F97: Infrastructure | G97: The company has changed its management fee. Base fee: no change, Tiered fee: changed, Fee basis change from net assets and market cap to market cap. The change is effective from 01/07/2026. | L97: UK | M97: MAIN
A98: 2026 | B98: May | C98: Fee change | D98: Mid Wynd International | E98: Lazard Asset Management | F98: Global | G98: The company has changed its management fee. Base fee: reduced, Tiered fee: changed. The change is effective from 01/05/2026. | K98: Temporary reduction in fee for 24 months. | L98: UK | M98: MAIN
A99: 2026 | B99: May | C99: Fee change | D99: Renewables Infrastructure Group | E99: InfraRed Capital Partners | F99: Renewable Energy Infrastructure | G99: The company has changed its management fee. Base fee: no change, Performance fee: no change, Tiered fee: changed, Fee basis change from net assets and market cap to market cap. The change is effective from 01/07/2026. | L99: GUE | M99: MAIN
A100: 2026 | B100: May | C100: New AIC sector | D100: Crystal Amber Fund | E100: Global Fund Management | F100: Flexible Investment | G100: from UK Smaller Companies | L100: GUE | M100: AIM
...

Sheet Issuance
A1: Produced by theaic.co.uk, 1st August 2026. Please note that, whilst we endeavour to verify all data sources, the information contained is not guaranteed to be accurate and the AIC does not accept responsibility for any errors or omissions.
A2: "Await" entries are taken from the company news announcements and are still to be finalised - therefore they may be subject to change.
A3: Year | B3: Month | C3: Event | D3: Company name | E3: Management group | F3: AIC sector | G3: Additional | H3: Total assets (£m) | I3: Rollover assets (£m) | J3: Bank debt (£m) | K3: Other info | L3: Domicile | M3: Listing
A4: 2026 | B4: Jan | C4: Issue | D4: Aberdeen Equity Income Trust | E4: Aberdeen | F4: UK Equity Income | G4: The company raised £20,650 by way of an issue of 50,000 ordinary shares at a price of 413p per share as a part of company's share issuance authority. | H4: 0.2065 | L4: UK | M4: MAIN
A5: 2026 | B5: Jan | C5: Issue | D5: Aberdeen Equity Income Trust | E5: Aberdeen | F5: UK Equity Income | G5: The company raised £20,700 by way of an issue of 50,000 ordinary shares at a price of 414p per share as a part of company's share issuance authority. | H5: 0.207 | L5: UK | M5: MAIN
A6: 2026 | B6: Jan | C6: Issue | D6: Aberdeen Equity Income Trust | E6: Aberdeen | F6: UK Equity Income | G6: The company raised £421,000 by way of an issue of 100,000 ordinary shares at a price of 421p per share as a part of company's share issuance authority. | H6: 0.421 | L6: UK | M6: MAIN
A7: 2026 | B7: Jan | C7: Issue | D7: Aberdeen Equity Income Trust | E7: Aberdeen | F7: UK Equity Income | G7: The company raised £550,800 through a blocklisting of 132,245 ordinary shares at a price of 416.5p per share. | H7: 0.55080043 | L7: UK | M7: MAIN
A8: 2026 | B8: Jan | C8: Issue | D8: Aberdeen Equity Income Trust | E8: Aberdeen | F8: UK Equity Income | G8: The company raised £739,375 through a blocklisting of 175,000 ordinary shares at a price of 422.5p per share. | H8: 0.739375 | L8: UK | M8: MAIN
A9: 2026 | B9: Jan | C9: Issue | D9: Aberdeen Equity Income Trust | E9: Aberdeen | F9: UK Equity Income | G9: The company raised £759,600 by way of an issue of 180,000 ordinary shares at a price of 422p per share as a part of company's share issuance authority. | H9: 0.7596 | L9: UK | M9: MAIN
A10: 2026 | B10: Jan | C10: Issue | D10: Aberdeen Equity Income Trust | E10: Aberdeen | F10: UK Equity Income | G10: The company raised £1,047,500 by way of an issue of 250,000 ordinary shares at a price of 419p per share as a part of company's share issuance authority. | H10: 1.0475 | L10: UK | M10: MAIN
A11: 2026 | B11: Jan | C11: Issue | D11: Ashoka India Equity | E11: Acorn Asset Management | F11: India / Indian subcontinent | G11: The company raised £205,725 through a blocklisting of 75,000 ordinary shares at a price of 274.3p per share. | H11: 0.205725 | L11: UK | M11: MAIN
A12: 2026 | B12: Jan | C12: Issue | D12: Ashoka India Equity | E12: Acorn Asset Management | F12: India / Indian subcontinent | G12: The company raised £406,950 through a blocklisting of 150,000 ordinary shares at a price of 271.3p per share. | H12: 0.40695 | L12: UK | M12: MAIN
A13: 2026 | B13: Jan | C13: Issue | D13: Ashoka India Equity | E13: Acorn Asset Management | F13: India / Indian subcontinent | G13: The company raised £410,850 through a blocklisting of 150,000 ordinary shares at a price of 273.9p per share. | H13: 0.41085 | L13: UK | M13: MAIN
A14: 2026 | B14: Jan | C14: Issue | D14: Ashoka WhiteOak Emerging Markets | E14: Acorn Asset Management | F14: Global Emerging Markets | G14: The company raised £79,650 through a blocklisting of 50,000 ordinary shares at a price of 159.3p per share. | H14: 0.07965 | L14: UK | M14: MAIN
A15: 2026 | B15: Jan | C15: Issue | D15: Ashoka WhiteOak Emerging Markets | E15: Acorn Asset Management | F15: Global Emerging Markets | G15: The company raised £357,075 through a blocklisting of 225,000 ordinary shares at a price of 158.7p per share. | H15: 0.357075 | L15: UK | M15: MAIN
... A401: 2026 | B401: Apr | C401: Issue (from treasury) | D401: TwentyFour Select Monthly Income | E401: TwentyFour Asset Management | F401: Debt - Loans & Bonds | G401: The company raised £284,228 by way of a reissue of 333,171 shares from treasury at a price of 85p per share. | H401: 0.28422818 | L401: GUE | M401: MAIN
A402: 2026 | B402: Apr | C402: Issue (from treasury) | D402: Value and Indexed Property Income Trust | E402: OLIM Property Limited | F402: Property - UK Commercial | G402: The company raised £5,431,500 by way of a reissue of 2,550,000 shares from treasury at a price of 213p per share. | H402: 5.4315 | K402: UK REIT | L402: UK | M402: MAIN
A403: 2026 | B403: Apr | C403: Issue (from treasury) | D403: Value and Indexed Property Income Trust | E403: OLIM Property Limited | F403: Property - UK Commercial | G403: The company raised £8,536 by way of a reissue of 4,000 shares from treasury at a price of 213p per share. | H403: 0.008536 | K403: UK REIT | L403: UK | M403: MAIN
A404: 2026 | B404: May | C404: Issue | D404: Ashoka WhiteOak Emerging Markets | E404: Acorn Asset Management | F404: Global Emerging Markets | G404: The company raised £588,900 through an issue of 325,000 ordinary shares at a price of 181p per share. | H404: 0.5889 | L404: UK | M404: MAIN
A405: 2026 | B405: May | C405: Issue | D405: Ashoka WhiteOak Emerging Markets | E405: Acorn Asset Management | F405: Global Emerging Markets | G405: The company raised £177,800 through a blocklisting of 100,000 ordinary shares at a price of 178p per share. | H405: 0.1778 | L405: UK | M405: MAIN
A406: 2026 | B406: May | C406: Issue | D406: Ceiba Investments | E406: Ceiba Investments | F406: Property - Rest of World | G406: The company raised £10,463,040 through an issue of 27,534,315 ordinary shares at a price of 38p per share. | H406: 10.46304 | L406: GUE | M406: SFS
A407: 2026 | B407: May | C407: Issue | D407: City of London Investment Trust | E407: Janus Henderson Investors | F407: UK Equity Income | G407: The company raised £769,500 through an issue of 135,000 ordinary shares at a price of 570p per share. | H407: 0.7695 | L407: UK | M407: MAIN
A408: 2026 | B408: May | C408: Issue | D408: City of London Investment Trust | E408: Janus Henderson Investors | F408: UK Equity Income | G408: The company raised £565,000 through an issue of 100,000 ordinary shares at a price of 565p per share. | H408: 0.565 | L408: UK | M408: MAIN
A409: 2026 | B409: May | C409: Issue | D409: CQS New City High Yield Fund | E409: New City Investment Managers | F409: Debt - Loans & Bonds | G409: The company raised £1,257,500 through an issue of 2,500,000 ordinary shares at a price of 50p per share. | H409: 1.2575 | L409: JER | M409: MAIN
A410: 2026 | B410: May | C410: Issue | D410: CQS New City High Yield Fund | E410: New City Investment Managers | F410: Debt - Loans & Bonds | G410: The company raised £883,750 through a blocklisting of 1,750,000 ordinary shares at a price of 51p per share. | H410: 0.88375 | L410: JER | M410: MAIN
A411: 2026 | B411: May | C411: Issue | D411: CQS New City High Yield Fund | E411: New City Investment Managers | F411: Debt - Loans & Bonds | G411: The company raised £1,518,000 through a blocklisting of 3,000,000 ordinary shares at a price of 51p per share. | H411: 1.518 | L411: JER | M411: MAIN
A412: 2026 | B412: May | C412: Issue | D412: CQS New City High Yield Fund | E412: New City Investment Managers | F412: Debt - Loans & Bonds | G412: The company raised £254,000 through an issue of 500,000 ordinary shares at a price of 51p per share. | H412: 0.254 | L412: JER | M412: MAIN
A413: 2026 | B413: May | C413: Issue | D413: CT Global Managed Portfolio Income | E413: Columbia Threadneedle Investments | F413: Flexible Investment | G413: The company raised £194,250 through a blocklisting of 150,000 ordinary shares at a price of 129.5p per share. | H413: 0.19425 | L413: UK | M413: MAIN
A414: 2026 | B414: May | C414: Issue | D414: CT Global Managed Portfolio Income | E414: Columbia Threadneedle Investments | F414: Flexible Investment | G414: The company raised £65,375 through a blocklisting of 150,000 ordinary shares at a price of 130.75p per share. | H414: 0.065375 | L414: UK | M414: MAIN
A415: 2026 | B415: May | C415: Issue | D415: EJF Investments | E415: EJF Investment Manager | F415: Debt - Structured Finance | G415: The company raised £108,427 through an issue of 100,000 2029 ZDP ordinary shares at a price of 108p per share. | H415: 0.1084273 | L415: JER | M415: SFS
... A461: 2026 | B461: May | C461: Issue | D461: TwentyFour Select Monthly Income | E461: TwentyFour Asset Management | F461: Debt - Loans & Bonds | G461: The company raised £1,276,950 through an issue of 1,500,000 ordinary shares at a price of 85p per share. | H461: 1.27695 | L461: GUE | M461: MAIN
A462: 2026 | B462: May | C462: Issue (C share) | D462: Seraphim Space C shares | E462: Seraphim Space | F462: Growth Capital | G462: The company raised £137,000,000 by way of a placing, retail offer and offer for subscription of 136,508,663 new C shares at a price of 100p per share. The new C shares commenced trading on 12/11/26. | H462: 136.50866 | J462: 0 | K462: C shares | L462: UK | M462: MAIN
A463: 2026 | B463: May | C463: Issue (from treasury) | D463: BlackRock American Income | E463: BlackRock Investment Management (UK) | F463: North America | G463: The company raised £460,800 by way of a reissue of 180,000 shares from treasury at a price of 256p per share. | H463: 0.4608 | L463: UK | M463: MAIN
A464: 2026 | B464: May | C464: Issue (from treasury) | D464: BlackRock American Income | E464: BlackRock Investment Management (UK) | F464: North America | G464: The company raised £421,575 by way of a reissue of 165,000 shares from treasury at a price of 256p per share. | H464: 0.421575 | L464: UK | M464: MAIN
A465: 2026 | B465: May | C465: Issue (from treasury) | D465: BlackRock American Income | E465: BlackRock Investment Management (UK) | F465: North America | G465: The company raised £127,950 by way of a reissue of 50,000 shares from treasury at a price of 256p per share. | H465: 0.12795 | L465: UK | M465: MAIN
A466: 2026 | B466: May | C466: Issue (from treasury) | D466: BlackRock American Income | E466: BlackRock Investment Management (UK) | F466: North America | G466: The company raised £357,980 by way of a reissue of 140,000 shares from treasury at a price of 256p per share. | H466: 0.35798 | L466: UK | M466: MAIN
A467: 2026 | B467: May | C467: Issue (from treasury) | D467: BlackRock American Income | E467: BlackRock Investment Management (UK) | F467: North America | G467: The company raised £116,213 by way of a reissue of 45,000 shares from treasury at a price of 258p per share. | H467: 0.1162125 | L467: UK | M467: MAIN
A468: 2026 | B468: May | C468: Issue (from treasury) | D468: BlackRock American Income | E468: BlackRock Investment Management (UK) | F468: North America | G468: The company raised £205,040 by way of a reissue of 80,000 shares from treasury at a price of 256p per share. | H468: 0.20504 | L468: UK | M468: MAIN
A469: 2026 | B469: May | C469: Issue (from treasury) | D469: BlackRock American Income | E469: BlackRock Investment Management (UK) | F469: North America | G469: The company raised £494,813 by way of a reissue of 195,000 shares from treasury at a price of 254p per share. | H469: 0.4948125 | L469: UK | M469: MAIN
A470: 2026 | B470: May | C470: Issue (from treasury) | D470: BlackRock American Income | E470: BlackRock Investment Management (UK) | F470: North America | G470: The company raised £392,550 by way of a reissue of 150,000 shares from treasury at a price of 262p per share. | H470: 0.39255 | L470: UK | M470: MAIN
A471: 2026 | B471: May | C471: Issue (from treasury) | D471: BlackRock Frontiers | E471: BlackRock Investment Management (UK) | F471: Global Emerging Markets | G471: The company raised £574,500 by way of a reissue of 300,000 shares from treasury at a price of 192p per share. | H471: 0.5745 | L471: UK | M471: MAIN
A472: 2026 | B472: May | C472: Issue (from treasury) | D472: BlackRock Frontiers | E472: BlackRock Investment Management (UK) | F472: Global Emerging Markets | G472: The company raised £240,000 by way of a reissue of 125,000 shares from treasury at a price of 192p per share. | H472: 0.24 | L472: UK | M472: MAIN
A473: 2026 | B473: May | C473: Issue (from treasury) | D473: BlackRock Frontiers | E473: BlackRock Investment Management (UK) | F473: Global Emerging Markets | G473: The company raised £288,750 by way of a reissue of 150,000 shares from treasury at a price of 193p per share. | H473: 0.28875 | L473: UK | M473: MAIN
A474: 2026 | B474: May | C474: Issue (from treasury) | D474: CVC Income & Growth | E474: CVC Credit Partners | F474: Debt - Loans & Bonds | G474: The company raised £356,050 by way of a reissue of 250,000 ordinary shares from treasury at a price of 142.42p per share. | H474: 0.35605 | L474: JER | M474: MAIN
... A630: 2026 | B630: Jun | C630: Issue (from treasury) | D630: Temple Bar Investment Trust | E630: RWC Asset Management | F630: UK Equity Income | G630: The company raised £903,825 by way of a reissue of 225,000 shares from treasury at a price of 402p per share. | H630: 0.903825 | L630: UK | M630: MAIN
A631: 2026 | B631: Jun | C631: Issue (from treasury) | D631: Value and Indexed Property Income Trust | E631: OLIM Property Limited | F631: Property - UK Commercial | G631: The company raised £50,055 by way of a reissue of 23,500 shares from treasury at a price of 213p per share. | H631: 0.050055 | K631: UK REIT | L631: UK | M631: MAIN
A632: 2026 | B632: Jul | C632: Issue | D632: Aberdeen Equity Income Trust | E632: Aberdeen | F632: UK Equity Income | G632: The company raised £115,250 through an issue of 25,000 ordinary shares at a price of 461p per share. | H632: 0.11525 | L632: UK | M632: MAIN
A633: 2026 | B633: Jul | C633: Issue | D633: Aberdeen Equity Income Trust | E633: Aberdeen | F633: UK Equity Income | G633: The company raised £278,100 through an issue of 60,000 ordinary shares at a price of 464p per share. | H633: 0.2781 | L633: UK | M633: MAIN
A634: 2026 | B634: Jul | C634: Issue | D634: Aberdeen Equity Income Trust | E634: Aberdeen | F634: UK Equity Income | G634: The company raised £278,100 through an issue of 60,000 ordinary shares at a price of 464p per share. | H634: 0.2781 | L634: UK | M634: MAIN
A635: 2026 | B635: Jul | C635: Issue | D635: Aberdeen Equity Income Trust | E635: Aberdeen | F635: UK Equity Income | G635: The company raised £391,850 through an issue of 85,000 ordinary shares at a price of 461p per share. | H635: 0.39185 | L635: UK | M635: MAIN
A636: 2026 | B636: Jul | C636: Issue | D636: Aberdeen Equity Income Trust | E636: Aberdeen | F636: UK Equity Income | G636: The company raised £348,000 through an issue of 75,000 ordinary shares at a price of 464p per share. | H636: 0.348 | L636: UK | M636: MAIN
A637: 2026 | B637: Jul | C637: Issue | D637: Aberdeen Equity Income Trust | E637: Aberdeen | F637: UK Equity Income | G637: The company raised £533,600 through an issue of 115,000 ordinary shares at a price of 464p per share. | H637: 0.5336 | L637: UK | M637: MAIN
A638: 2026 | B638: Jul | C638: Issue | D638: Ashoka WhiteOak Emerging Markets | E638: Acorn Asset Management | F638: Global Emerging Markets | G638: The company raised £1,173,708 through an issue of 646,422 ordinary shares at a price of 181.57p per share. | H638: 1.1737084 | L638: UK | M638: MAIN
A639: 2026 | B639: Jul | C639: Issue | D639: Ashoka WhiteOak Emerging Markets | E639: Acorn Asset Management | F639: Global Emerging Markets | G639: The company raised £87,850 through a blocklisting of 50,000 ordinary shares at a price of 176p per share. | H639: 0.08785 | L639: UK | M639: MAIN
A640: 2026 | B640: Jul | C640: Issue | D640: Ashoka WhiteOak Emerging Markets | E640: Acorn Asset Management | F640: Global Emerging Markets | G640: The company raised £1,173,708 through an issue of 646,422 ordinary shares at a price of 182p per share. | H640: 1.1737084 | L640: UK | M640: MAIN
A641: 2026 | B641: Jul | C641: Issue | D641: City of London Investment Trust | E641: Janus Henderson Investors | F641: UK Equity Income | G641: The company raised £2,005,500 through an issue of 350,000 ordinary shares at a price of 573p per share. | H641: 2.0055 | L641: UK | M641: MAIN
A642: 2026 | B642: Jul | C642: Issue | D642: City of London Investment Trust | E642: Janus Henderson Investors | F642: UK Equity Income | G642: The company raised £592,000 through an issue of 100,000 ordinary shares at a price of 592p per share. | H642: 0.592 | L642: UK | M642: MAIN
A643: 2026 | B643: Jul | C643: Issue | D643: CQS New City High Yield Fund | E643: New City Investment Managers | F643: Debt - Loans & Bonds | G643: The company raised £3,395,250 through a blocklisting of 6,750,000 ordinary shares at a price of 50p per share. | H643: 3.39525 | L643: JER | M643: MAIN
... A729: 2026 | B729: Jul | C729: Issue | D729: TwentyFour Select Monthly Income | E729: TwentyFour Asset Management | F729: Debt - Loans & Bonds | G729: The company raised £1,285,800 through an issue of 1,500,000 ordinary shares at a price of 86p per share. | H729: 1.2858 | L729: GUE | M729: MAIN
A730: 2026 | B730: Jul | C730: Issue (existing assets) | D730: Living REIT | E730: Atrato Partners Limited | F730: Property - UK Residential | G730: The company has agreed with Residential Secure Income on for the sale of the entire issued share capital of RHP Holdings Limited for an aggregate consideration of approximately £107.3 million. This 66.1 million newly issued LIVE shares at £62.3 million at their issue price, and £45 million in cash. The Initial Consideration Shares will rank pari passu in all respects with the ordinary shares already in issue. | H730: -107.3 | I730: -107.3 | K730: UK REIT | L730: UK | M730: MAIN
A731: 2026 | B731: Jul | C731: Issue (from treasury) | D731: BlackRock American Income | E731: BlackRock Investment Management (UK) | F731: North America | G731: The company raised £274,000 by way of a reissue of 100,000 shares from treasury at a price of 274p per share. | H731: 0.274 | L731: UK | M731: MAIN
A732: 2026 | B732: Jul | C732: Issue (from treasury) | D732: BlackRock American Income | E732: BlackRock Investment Management (UK) | F732: North America | G732: The company raised £276,000 by way of a reissue of 100,000 shares from treasury at a price of 276p per share. | H732: 0.276 | L732: UK | M732: MAIN
A733: 2026 | B733: Jul | C733: Issue (from treasury) | D733: BlackRock American Income | E733: BlackRock Investment Management (UK) | F733: North America | G733: The company raised £275,260 by way of a reissue of 100,000 shares from treasury at a price of 275p per share. | H733: 0.27526 | L733: UK | M733: MAIN
A734: 2026 | B734: Jul | C734: Issue (from treasury) | D734: BlackRock American Income | E734: BlackRock Investment Management (UK) | F734: North America | G734: The company raised £273,750 by way of a reissue of 100,000 shares from treasury at a price of 274p per share. | H734: 0.27375 | L734: UK | M734: MAIN
A735: 2026 | B735: Jul | C735: Issue (from treasury) | D735: BlackRock American Income | E735: BlackRock Investment Management (UK) | F735: North America | G735: The company raised £274,000 by way of a reissue of 100,000 shares from treasury at a price of 274p per share. | H735: 0.274 | L735: UK | M735: MAIN
A736: 2026 | B736: Jul | C736: Issue (from treasury) | D736: BlackRock American Income | E736: BlackRock Investment Management (UK) | F736: North America | G736: The company raised £274,800 by way of a reissue of 100,000 shares from treasury at a price of 275p per share. | H736: 0.2748 | L736: UK | M736: MAIN
A737: 2026 | B737: Jul | C737: Issue (from treasury) | D737: BlackRock American Income | E737: BlackRock Investment Management (UK) | F737: North America | G737: The company raised £276,000 by way of a reissue of 100,000 shares from treasury at a price of 276p per share. | H737: 0.276 | L737: UK | M737: MAIN
A738: 2026 | B738: Jul | C738: Issue (from treasury) | D738: BlackRock American Income | E738: BlackRock Investment Management (UK) | F738: North America | G738: The company raised £277,300 by way of a reissue of 100,000 shares from treasury at a price of 277p per share. | H738: 0.2773 | L738: UK | M738: MAIN
A739: 2026 | B739: Jul | C739: Issue (from treasury) | D739: BlackRock American Income | E739: BlackRock Investment Management (UK) | F739: North America | G739: The company raised £554,000 by way of a reissue of 200,000 shares from treasury at a price of 277p per share. | H739: 0.554 | L739: UK | M739: MAIN
A740: 2026 | B740: Jul | C740: Issue (from treasury) | D740: BlackRock American Income | E740: BlackRock Investment Management (UK) | F740: North America | G740: The company raised £1,318,125 by way of a reissue of 475,000 shares from treasury at a price of 278p per share. | H740: 1.318125 | L740: UK | M740: MAIN
A741: 2026 | B741: Jul | C741: Issue (from treasury) | D741: BlackRock American Income | E741: BlackRock Investment Management (UK) | F741: North America | G741: The company raised £421,050 by way of a reissue of 150,000 shares from treasury at a price of 281p per share. | H741: 0.42105 | L741: UK | M741: MAIN
A742: 2026 | B742: Jul | C742: Issue (from treasury) | D742: BlackRock American Income | E742: BlackRock Investment Management (UK) | F742: North America | G742: The company raised £421,050 by way of a reissue of 150,000 shares from treasury at a price of 281p per share. | H742: 0.42105 | L742: UK | M742: MAIN
... A776: 2026 | B776: Jul | C776: Issue (from treasury) | D776: Temple Bar Investment Trust | E776: RWC Asset Management | F776: UK Equity Income | G776: The company raised £2,115,000 by way of a reissue of 500,000 shares from treasury at a price of 423p per share. | H776: 2.115 | L776: UK | M776: MAIN

Sheet Buybacks
A1: Produced by theaic.co.uk, 1st August 2026. Please note that, whilst we endeavour to verify all data sources, the information contained is not guaranteed to be accurate and the AIC does not accept responsibility for any errors or omissions.
A2: "Await" entries are taken from the company news announcements and are still to be finalised - therefore they may be subject to change.
A3: Year | B3: Month | C3: Event | D3: Company name | E3: Management group | F3: AIC sector | G3: Additional | H3: Total assets (£m) | I3: Other info | J3: Domicile | K3: Listing
A4: 2026 | B4: Jan | C4: Buyback | D4: Aberdeen Asia Focus | E4: Aberdeen | F4: Asia Pacific Smaller Companies | G4: The company returned £282,000 to shareholders by way of a buyback of 75,000 ordinary shares at a price of 376.p per share. | H4: -0.282 | J4: UK | K4: MAIN
A5: 2026 | B5: Jan | C5: Buyback | D5: Aberdeen Asia Focus | E5: Aberdeen | F5: Asia Pacific Smaller Companies | G5: The company returned £318,750 to shareholders by way of a buyback of 85,000 ordinary shares at a price of 375.p per share. | H5: -0.31875 | J5: UK | K5: MAIN
A6: 2026 | B6: Jan | C6: Buyback | D6: Aberdeen Asia Focus | E6: Aberdeen | F6: Asia Pacific Smaller Companies | G6: The company returned £566,424 to shareholders by way of a buyback of 150,000 ordinary shares at a price of 377.62p per share. | H6: -0.566424 | J6: UK | K6: MAIN
A7: 2026 | B7: Jan | C7: Buyback | D7: Aberdeen Asia Focus | E7: Aberdeen | F7: Asia Pacific Smaller Companies | G7: The company returned £286,500 to shareholders by way of a buyback of 75,000 ordinary shares at a price of 382.p per share. | H7: -0.2865 | J7: UK | K7: MAIN
A8: 2026 | B8: Jan | C8: Buyback | D8: Aberdeen Asia Focus | E8: Aberdeen | F8: Asia Pacific Smaller Companies | G8: The company returned £189,750 to shareholders by way of a buyback of 50,000 ordinary shares at a price of 379.5p per share. | H8: -0.18975 | J8: UK | K8: MAIN
A9: 2026 | B9: Jan | C9: Buyback | D9: Aberdeen New India Investment Trust | E9: Aberdeen | F9: India / Indian subcontinent | G9: The company returned £116,849 to shareholders by way of a buyback of 15,000 ordinary shares at a price of 778.99p per share. | H9: -0.1168488 | J9: UK | K9: MAIN
A10: 2026 | B10: Jan | C10: Buyback | D10: Aberdeen New India Investment Trust | E10: Aberdeen | F10: India / Indian subcontinent | G10: The company returned £273,772 to shareholders by way of a buyback of 35,000 ordinary shares at a price of 782.21p per share. | H10: -0.27377245 | J10: UK | K10: MAIN
A11: 2026 | B11: Jan | C11: Buyback | D11: Aberdeen New India Investment Trust | E11: Aberdeen | F11: India / Indian subcontinent | G11: The company returned £232,709 to shareholders by way of a buyback of 30,000 ordinary shares at a price of 775.7p per share. | H11: -0.2327085 | J11: UK | K11: MAIN
A12: 2026 | B12: Jan | C12: Buyback | D12: Aberdeen New India Investment Trust | E12: Aberdeen | F12: India / Indian subcontinent | G12: The company returned £192,137 to shareholders by way of a buyback of 25,000 ordinary shares at a price of 768.55p per share. | H12: -0.1921365 | J12: UK | K12: MAIN
A13: 2026 | B13: Jan | C13: Buyback | D13: Aberdeen New India Investment Trust | E13: Aberdeen | F13: India / Indian subcontinent | G13: The company returned £190,881 to shareholders by way of a buyback of 25,000 ordinary shares at a price of 763.52p per share. | H13: -0.1908805 | J13: UK | K13: MAIN
A14: 2026 | B14: Jan | C14: Buyback | D14: Aberdeen New India Investment Trust | E14: Aberdeen | F14: India / Indian subcontinent | G14: The company returned £228,699 to shareholders by way of a buyback of 30,000 ordinary shares at a price of 762.33p per share. | H14: -0.2286987 | J14: UK | K14: MAIN
A15: 2026 | B15: Jan | C15: Buyback | D15: Aberdeen New India Investment Trust | E15: Aberdeen | F15: India / Indian subcontinent | G15: The company returned £151,995 to shareholders by way of a buyback of 20,000 ordinary shares at a price of 759.98p per share. | H15: -0.1519954 | J15: UK | K15: MAIN
... A7923: 2026 | B7923: Jul | C7923: Buyback | D7923: Worldwide Healthcare Trust | E7923: Frostrow Capital | F7923: Healthcare & Biotechnology | G7923: The company returned £465,453 to shareholders by way of a buyback of 120,024 ordinary shares at a price of 387.8p per share. | H7923: -0.46545307 | J7923: UK | K7923: MAIN

Sheet VCT
A1: Produced by theaic.co.uk, 1st August 2026. Please note that, whilst we endeavour to verify all data sources, the information contained is not guaranteed to be accurate and the AIC does not accept responsibility for any errors or omissions.
A2: Transactions effective under offer are listed as a single row (Issue) as well as a cumulative total under 'Open offer for subscription' from tax year 2026/27 onwards.
A3: Await entries are taken from the company news announcements and are still to be finalised, therefore they may be subject to change.
A4: Year | B4: Month | C4: Event | D4: Company name | E4: Management group | F4: AIC sector | G4: Additional | H4: Target sought | I4: Over-allotment value | J4: Over-allotment utilised | K4: Open date | L4: Tax year 1 | M4: Tax year 1 funds raised | N4: Tax year 2 | O4: Tax year 2 funds raised | P4: Close date | Q4: Total assets (million) | R4: Rollover assets | S4: Bank debt | T4: Other info
A5: 2026 | B5: Jan | C5: Buyback | D5: Calculus VCT | E5: Calculus Capital/Investec Structured Products | F5: VCT | G5: The company returned £375,000 to shareholders by way of a buyback of 700,804 ordinary shares at a price of 37.5p per share. | Q5: -0.37500022
A6: 2026 | B6: Jan | C6: Buyback | D6: Foresight Technology VCT William Technology shares | E6: Foresight Group | F6: VCT | G6: The company returned £269,831 to shareholders by way of a buyback of 308,731 ordinary shares at a price of 26.98p per share. | Q6: -0.26983089
A7: 2026 | B7: Jan | C7: Buyback | D7: Foresight Ventures VCT | E7: Foresight Group | F7: VCT | G7: The company returned £1,287,577 to shareholders by way of a buyback of 1,485,437 ordinary shares at a price of 128.76p per share. | Q7: -1.2875768
A8: 2026 | B8: Jan | C8: Buyback | D8: Gresham House Income & Growth 2 VCT | E8: Gresham House | F8: VCT | G8: The company returned £2,318,632 to shareholders by way of a buyback of 4,667,133 ordinary shares at a price of 231.86p per share. | Q8: -2.3186317
A9: 2026 | B9: Jan | C9: Buyback | D9: Gresham House Income & Growth VCT | E9: Gresham House | F9: VCT | G9: The company returned £2,113,575 to shareholders by way of a buyback of 3,460,906 ordinary shares at a price of 211.36p per share. | Q9: -2.1135753
A10: 2026 | B10: Jan | C10: Buyback | D10: Hargreave Hale AIM VCT | E10: Hargreave Hale | F10: VCT AIM Quoted | G10: The company returned £412,099 to shareholders by way of a buyback of 1,321,255 ordinary shares at a price of 41.21p per share. | Q10: -0.41209943
A11: 2026 | B11: Jan | C11: Buyback | D11: Hargreave Hale AIM VCT | E11: Hargreave Hale | F11: VCT AIM Quoted | G11: The company returned £63,674 to shareholders by way of a buyback of 201,627 ordinary shares at a price of 6.37p per share. | Q11: -0.063673807
A12: 2026 | B12: Jan | C12: Buyback | D12: Hargreave Hale AIM VCT | E12: Hargreave Hale | F12: VCT AIM Quoted | G12: The company returned £199,271 to shareholders by way of a buyback of 628,417 ordinary shares at a price of 19.93p per share. | Q12: -0.19927103
A13: 2026 | B13: Jan | C13: Buyback | D13: Maven Income and Growth VCT | E13: Maven Capital Partners | F13: VCT | G13: The company returned £416,102 to shareholders by way of a buyback of 1,209,600 ordinary shares at a price of 41.61p per share. | Q13: -0.4161024
A14: 2026 | B14: Jan | C14: Buyback | D14: Maven Renovar VCT | E14: Maven Capital Partners | F14: VCT AIM Quoted | G14: The company returned £21,767 to shareholders by way of a buyback of 37,530 ordinary shares at a price of 2.18p per share. | Q14: -0.0217674
A15: 2026 | B15: Jan | C15: Buyback | D15: Maven Renovar VCT | E15: Maven Capital Partners | F15: VCT AIM Quoted | G15: The company returned £170,361 to shareholders by way of a buyback of 288,748 ordinary shares at a price of 17.04p per share. | Q15: -0.17036132
A16: 2026 | B16: Jan | C16: Buyback | D16: Maven Renovar VCT | E16: Maven Capital Partners | F16: VCT AIM Quoted | G16: The company returned £184,138 to shareholders by way of a buyback of 312,098 ordinary shares at a price of 18.41p per share. | Q16: -0.18413782
... A22: 2026 | B22: Jan | C22: Buyback | D22: Puma VCT 13 | E22: Puma Investments | F22: VCT | G22: The company returned £1,759,149 to shareholders by way of a buyback of 1,535,061 ordinary shares at a price of 175.91p per share. | Q22: -1.7591492
A23: 2026 | B23: Jan | C23: Closed offer for subscription | D23: British Smaller Companies VCT | E23: YFM Private Equity | F23: VCT | G23: The company raised £85,000,000 in aggregate by way of a joint open offer for subscription of shares with British Smaller Companies VCT 2. The offer opened on the 25/09/2025 and closed on 18/12/2025. | K23: 45925 | L23: 2025/26 | M23: 42.5 | P23: 46009 | Q23: 42.5
A24: 2026 | B24: Jan | C24: Closed offer for subscription | D24: British Smaller Companies VCT 2 | E24: YFM Private Equity | F24: VCT | G24: The company raised £85,000,000 in aggregate by way of a joint open offer for subscription of shares with British Smaller Companies VCT. The offer opened on the 25/09/2025 and closed on 18/12/2025. | K24: 45925 | L24: 2025/26 | M24: 42.5 | P24: 46009 | Q24: 42.5
A25: 2026 | B25: Jan | C25: Closed offer for subscription | D25: Foresight Enterprise VCT | E25: Foresight Group | F25: VCT | G25: The company raised £40,000,000 by way of an open offer for subscription. The offer opened on 06/01/2025 and closed on 29/01/2026 | K25: 45663 | L25: 2024/25 | M25: 9.693434 | N25: 2025/26 | O25: 30.306566 | P25: 46051 | Q25: 40
A26: 2026 | B26: Jan | C26: Issue (DRIS) | D26: Maven Income and Growth VCT | E26: Maven Capital Partners | F26: VCT | G26: The company raised £158,517 by way of an issue of 435,725 shares at a price of 36.38p per share as shareholders elected to reinvest their dividend under the company's dividend reinvestment scheme. | L26: 2025/26 | Q26: 0.15851676
A27: 2026 | B27: Jan | C27: Issue (DRIS) | D27: Maven Income and Growth VCT 3 | E27: Maven Capital Partners | F27: VCT | G27: The company raised £133,365 by way of an issue of 284,300 shares at a price of 46.91p per share as shareholders elected to reinvest their dividend under the company's dividend reinvestment scheme. | L27: 2025/26 | Q27: 0.13336513
A28: 2026 | B28: Jan | C28: Issue (DRIS) | D28: Maven Income and Growth VCT 4 | E28: Maven Capital Partners | F28: VCT | G28: The company raised £142,723 by way of an issue of 263,863 shares at a price of 54.09p per share as shareholders elected to reinvest their dividend under the company's dividend reinvestment scheme. | L28: 2025/26 | Q28: 0.1427235
A29: 2026 | B29: Jan | C29: Issue (DRIS) | D29: Maven Income and Growth VCT 5 | E29: Maven Capital Partners | F29: VCT | G29: The company raised £106,145 by way of an issue of 348,359 shares at a price of 30.47p per share as shareholders elected to reinvest their dividend under the company's dividend reinvestment scheme. | L29: 2025/26 | Q29: 0.10614499
A30: 2026 | B30: Jan | C30: Issue (DRIS) | D30: Northern 2 VCT | E30: Mercia Asset Management | F30: VCT | G30: The company raised £552,918 by way of an issue of 987,354 shares at a price of 56.p per share as shareholders elected to reinvest their dividend under the company's dividend reinvestment scheme. | L30: 2025/26 | Q30: 0.55291824
A31: 2026 | B31: Jan | C31: Issue (DRIS) | D31: Northern 3 VCT | E31: Mercia Asset Management | F31: VCT | G31: The company raised £351,801 by way of an issue of 403,442 shares at a price of 87.2p per share as shareholders elected to reinvest their dividend under the company's dividend reinvestment scheme. | L31: 2025/26 | Q31: 0.35180142
A32: 2026 | B32: Jan | C32: Issue (DRIS) | D32: Octopus AIM VCT | E32: Octopus Investments | F32: VCT AIM Quoted | G32: The company raised £1,060,517 by way of an issue of 2,237,378 shares at a price of 47.4p per share as shareholders elected to reinvest their dividend under the company's dividend reinvestment scheme. | L32: 2025/26 | Q32: 1.0605172
A33: 2026 | B33: Jan | C33: Issue (DRIS) | D33: Pembroke VCT B shares | E33: Pembroke Investment Managers | F33: VCT | G33: The company raised £1,108,697 by way of an issue of 1,160,939 shares at a price of 95.5p per share as shareholders elected to reinvest their dividend under the company's dividend reinvestment scheme. | L33: 2025/26 | Q33: 1.1086967
A34: 2026 | B34: Jan | C34: Issue (DRIS) | D34: ProVen Growth and Income VCT | E34: Beringea | F34: VCT | G34: The company raised £556,037 by way of an issue of 1,164,475 shares at a price of 47.75p per share as shareholders elected to reinvest their dividend under the company's dividend reinvestment scheme. | L34: 2025/26 | Q34: 0.55603681
A35: 2026 | B35: Jan | C35: Issue (DRIS) | D35: ProVen VCT | E35: Beringea | F35: VCT | G35: The company raised £694,485 by way of an issue of 1,131,083 shares at a price of 61.4p per share as shareholders elected to reinvest their dividend under the company's dividend reinvestment scheme. | L35: 2025/26 | Q35: 0.69448496
A36: 2026 | B36: Feb | C36: Buyback | D36: Baronsmead Second Venture Trust | E36: Gresham House | F36: VCT | G36: The company returned £4,767,981 to shareholders by way of a buyback of 9,002,985 ordinary shares at a price of 476.8p per share. | Q36: -4.7679809
A37: 2026 | B37: Feb | C37: Buyback | D37: Baronsmead Venture Trust | E37: Gresham House | F37: VCT | G37: The company returned £4,597,999 to shareholders by way of a buyback of 9,070,821 ordinary shares at a price of 459.8p per share. | Q37: -4.5979992
A38: 2026 | B38: Feb | C38: Buyback | D38: Hargreave Hale AIM VCT | E38: Hargreave Hale | F38: VCT AIM Quoted | G38: The company returned £227,843 to shareholders by way of a buyback of 721,023 ordinary shares at a price of 22.78p per share. | Q38: -0.22784327
A39: 2026 | B39: Feb | C39: Buyback | D39: Hargreave Hale AIM VCT | E39: Hargreave Hale | F39: VCT AIM Quoted | G39: The company returned £114,697 to shareholders by way of a buyback of 367,736 ordinary shares at a price of 11.47p per share. | Q39: -0.11469686
A40: 2026 | B40: Feb | C40: Buyback | D40: Maven Income and Growth VCT 3 | E40: Maven Capital Partners | F40: VCT | G40: The company returned £446,202 to shareholders by way of a buyback of 1,004,959 ordinary shares at a price of 44.62p per share. | Q40: -0.4462018
A41: 2026 | B41: Feb | C41: Buyback | D41: Maven Income and Growth VCT 5 | E41: Maven Capital Partners | F41: VCT | G41: The company returned £780,216 to shareholders by way of a buyback of 2,699,710 ordinary shares at a price of 78.02p per share. | Q41: -0.78021619
A42: 2026 | B42: Feb | C42: Buyback | D42: Maven Income and Growth VCT 5 | E42: Maven Capital Partners | F42: VCT | G42: The company returned £19,031 to shareholders by way of a buyback of 65,850 ordinary shares at a price of 1.9p per share. | Q42: -0.01903065
A43: 2026 | B43: Feb | C43: Buyback | D43: Maven Renovar VCT | E43: Maven Capital Partners | F43: VCT AIM Quoted | G43: The company returned £31,144 to shareholders by way of a buyback of 52,786 ordinary shares at a price of 3.11p per share. | Q43: -0.03114374
A44: 2026 | B44: Feb | C44: Buyback | D44: Maven Renovar VCT | E44: Maven Capital Partners | F44: VCT AIM Quoted | G44: The company returned £19,277 to shareholders by way of a buyback of 33,237 ordinary shares at a price of 1.93p per share. | Q44: -0.01927746
A45: 2026 | B45: Feb | C45: Buyback | D45: Maven Renovar VCT | E45: Maven Capital Partners | F45: VCT AIM Quoted | G45: The company returned £86,100 to shareholders by way of a buyback of 151,052 ordinary shares at a price of 8.61p per share. | Q45: -0.08609964
A46: 2026 | B46: Feb | C46: Buyback | D46: Maven Renovar VCT | E46: Maven Capital Partners | F46: VCT AIM Quoted | G46: The company returned £75,440 to shareholders by way of a buyback of 132,351 ordinary shares at a price of 7.54p per share. | Q46: -0.07544007
A47: 2026 | B47: Feb | C47: Buyback | D47: Octopus AIM VCT | E47: Octopus Investments | F47: VCT AIM Quoted | G47: The company returned £406,818 to shareholders by way of a buyback of 911,943 ordinary shares at a price of 40.68p per share. | Q47: -0.40681777
... A51: 2026 | B51: Feb | C51: Buyback | D51: Unicorn AIM VCT | E51: Unicorn Asset Management | F51: VCT AIM Quoted | G51: The company returned £1,886,873 to shareholders by way of a buyback of 2,515,831 ordinary shares at a price of 188.69p per share. | Q51: -1.8868733
A52: 2026 | B52: Feb | C52: Closed offer for subscription | D52: Albion Enterprise VCT | E52: Albion Capital | F52: VCT | G52: The company raised £30,000,000 by way of an open offer for subscription. The offer opened 03/11/2025, and closed on 11/02/2026. | K52: 45964 | L52: 2025/26 | M52: 30 | P52: 46064 | Q52: 30
A53: 2026 | B53: Feb | C53: Closed offer for subscription | D53: Foresight VCT | E53: Foresight Group | F53: VCT | G53: The company raised £40,000,000 by way of an open offer for subscription. The offer opened on 21/01/2026 and closed on 04/02/2026. | K53: 46043 | L53: 2025/26 | M53: 40 | P53: 46057 | Q53: 40
A54: 2026 | B54: Feb | C54: Closed offer for subscription | D54: Fuel Ventures VCT | E54: Sturgeon Ventures | F54: VCT | G54: The company raised £2,346,183 by way of an offer for subscription of shares. The offer opened on 17/02/25 and closed on 02/02/2026. The offer has been extended to closed on 02/02/2026. | K54: 45705 | L54: 2025/26 | M54: 2.346183 | P54: 46055 | Q54: 2.346183
A55: 2026 | B55: Feb | C55: Closed offer for subscription | D55: Northern Venture Trust | E55: Mercia Asset Management | F55: VCT | G55: The company raised £30,000,000 by way of an open offer for subscription. The offer opened on 24/09/2025, reopened on 08/12/2025, and closed on 23/02/2026. | K55: 45924 | L55: 2025/26 | M55: 30 | P55: 46076 | Q55: 30
A56: 2026 | B56: Feb | C56: Closed offer for subscription | D56: Oberon AIM VCT | E56: Oberon Investments | F56: VCT | G56: The company raised £658,117 by way of an offer for subscription of shares. The offer opened on 17/02/25 and closed on 04/04/2025. The offer opened on 12/02/2025 and closed on 11/02/2026 for the 2025/2026 tax year. | K56: 45705 | L56: 2024/25 | M56: 0 | N56: 2025/26 | O56: 0.66 | P56: 46064 | Q56: 0.658117
A57: 2026 | B57: Feb | C57: Issue (DRIS) | D57: Albion Enterprise VCT | E57: Albion Capital | F57: VCT | G57: The company raised £1,049,649 by way of an issue of 962,981 shares at a price of 109.p per share as shareholders elected to reinvest their dividend under the company's dividend reinvestment scheme. | L57: 2025/26 | Q57: 1.0496493
A58: 2026 | B58: Feb | C58: Issue (DRIS) | D58: Hargreave Hale AIM VCT | E58: Hargreave Hale | F58: VCT AIM Quoted | G58: The company raised £1,236,988 by way of an issue of 3,705,775 shares at a price of 33.38p per share as shareholders elected to reinvest their dividend under the company's dividend reinvestment scheme. | L58: 2025/26 | Q58: 1.2369877
A59: 2026 | B59: Feb | C59: Issue (DRIS) | D59: Unicorn AIM VCT | E59: Unicorn Asset Management | F59: VCT AIM Quoted | G59: The company raised £1,137,763 by way of an issue of 1,356,094 shares at a price of 83.9p per share as shareholders elected to reinvest their dividend under the company's dividend reinvestment scheme. | L59: 2025/26 | Q59: 1.1377629
A60: 2026 | B60: Feb | C60: Membership Change | D60: Praetura Growth VCT | E60: Praetura Ventures | F60: VCT | G60: Company became a new member.
A61: 2026 | B61: Mar | C61: Buyback | D61: Albion Enterprise VCT | E61: Albion Capital | F61: VCT | G61: The company returned £2,981,692 to shareholders by way of a buyback of 2,792,108 ordinary shares at a price of 298.17p per share. | Q61: -2.9816921
A62: 2026 | B62: Mar | C62: Buyback | D62: Baronsmead Second Venture Trust | E62: Gresham House | F62: VCT | G62: The company returned £575,090 to shareholders by way of a buyback of 1,310,000 ordinary shares at a price of 57.51p per share. | Q62: -0.57509
A63: 2026 | B63: Mar | C63: Buyback | D63: Baronsmead Venture Trust | E63: Gresham House | F63: VCT | G63: The company returned £195,299 to shareholders by way of a buyback of 455,879 ordinary shares at a price of 19.53p per share. | Q63: -0.19529856
A64: 2026 | B64: Mar | C64: Buyback | D64: British Smaller Companies VCT | E64: YFM Private Equity | F64: VCT | G64: The company returned £1,553,959 to shareholders by way of a buyback of 2,064,513 ordinary shares at a price of 155.4p per share. | Q64: -1.5539589
A65: 2026 | B65: Mar | C65: Buyback | D65: British Smaller Companies VCT 2 | E65: YFM Private Equity | F65: VCT | G65: The company returned £1,296,457 to shareholders by way of a buyback of 2,484,587 ordinary shares at a price of 129.65p per share. | Q65: -1.2964575
A66: 2026 | B66: Mar | C66: Buyback | D66: Foresight Technology VCT William Technology shares | E66: Foresight Group | F66: VCT | G66: The company returned £356,141 to shareholders by way of a buyback of 403,514 ordinary shares at a price of 35.61p per share. | Q66: -0.35614146
A67: 2026 | B67: Mar | C67: Buyback | D67: Hargreave Hale AIM VCT | E67: Hargreave Hale | F67: VCT AIM Quoted | G67: The company returned £84,347 to shareholders by way of a buyback of 272,088 ordinary shares at a price of 8.43p per share. | Q67: -0.08434728
A68: 2026 | B68: Mar | C68: Buyback | D68: Hargreave Hale AIM VCT | E68: Hargreave Hale | F68: VCT AIM Quoted | G68: The company returned £129,300 to shareholders by way of a buyback of 424,911 ordinary shares at a price of 12.93p per share. | Q68: -0.12930042
A69: 2026 | B69: Mar | C69: Buyback | D69: Hargreave Hale AIM VCT | E69: Hargreave Hale | F69: VCT AIM Quoted | G69: The company returned £47,892 to shareholders by way of a buyback of 161,251 ordinary shares at a price of 4.79p per share. | Q69: -0.047891547
A70: 2026 | B70: Mar | C70: Buyback | D70: Hargreave Hale AIM VCT | E70: Hargreave Hale | F70: VCT AIM Quoted | G70: The company returned £43,136 to shareholders by way of a buyback of 148,029 ordinary shares at a price of 4.31p per share. | Q70: -0.043135651
A71: 2026 | B71: Mar | C71: Buyback | D71: Maven Renovar VCT | E71: Maven Capital Partners | F71: VCT AIM Quoted | G71: The company returned £37,563 to shareholders by way of a buyback of 66,483 ordinary shares at a price of 3.76p per share. | Q71: -0.037562895
A72: 2026 | B72: Mar | C72: Buyback | D72: Maven Renovar VCT | E72: Maven Capital Partners | F72: VCT AIM Quoted | G72: The company returned £66,232 to shareholders by way of a buyback of 118,271 ordinary shares at a price of 6.62p per share. | Q72: -0.06623176
... A81: 2026 | B81: Mar | C81: Buyback | D81: Unicorn AIM VCT | E81: Unicorn Asset Management | F81: VCT AIM Quoted | G81: The company returned £260,645 to shareholders by way of a buyback of 359,510 ordinary shares at a price of 26.06p per share. | Q81: -0.26064475
A82: 2026 | B82: Mar | C82: Closed offer for subscription | D82: Albion Crown VCT | E82: Albion Capital | F82: VCT | G82: The company raised £30,000,000 by way of an open offer for subscription. The offer opened 03/11/2025, and closed on 16/03/2026. | K82: 45964 | L82: 2025/26 | M82: 30 | P82: 46097 | Q82: 30
A83: 2026 | B83: Mar | C83: Closed offer for subscription | D83: Albion Technology & General VCT | E83: Albion Capital | F83: VCT | G83: The company raised £30,000,000 by way of an open offer for subscription. The offer opened 03/11/2025, and closed on 10/03/2026. | K83: 45964 | L83: 2025/26 | M83: 30 | P83: 46091 | Q83: 30
A84: 2026 | B84: Mar | C84: Closed offer for subscription | D84: Maven Income and Growth VCT 5 | E84: Maven Capital Partners | F84: VCT | G84: The company raised £12,50,000 by way of a joint offer for subscription of shares, in conjunction with Maven Income and Growth VCT 3, Maven Income and Growth VCT 4 and Maven Income and Growth VCT. The offer opened on 02/10/2025 and closed on 30/03/2026. | K84: 45932 | L84: 2025/26 | M84: 12.170341 | N84: 2026/27 | O84: 0.32965918 | P84: 46111 | Q84: 12.5
A85: 2026 | B85: Mar | C85: Closed offer for subscription | D85: Northern 2 VCT | E85: Mercia Asset Management | F85: VCT | G85: The company raised £20,000,000 by way of an open offer for subscription. The offer opened on 24/09/2025 and closed on 02/12/2025 and reopened on 08/12/2025 to further applications, and closed on 09/03/2026. | K85: 45924 | L85: 2025/26 | M85: 20 | P85: 46090 | Q85: 20
A86: 2026 | B86: Mar | C86: Closed offer for subscription | D86: Northern 3 VCT | E86: Mercia Asset Management | F86: VCT | G86: The company raised £30,000,000 by way of an open offer for subscription. The offer opened on 24/09/2025 and closed on 10/03/2026 | K86: 45924 | L86: 2025/26 | M86: 30 | P86: 46091 | Q86: 30
A87: 2026 | B87: Mar | C87: Issue (DRIS) | D87: Foresight Ventures VCT | E87: Foresight Group | F87: VCT | G87: The company raised £266,104 by way of an issue of 301,023 shares at a price of 88.4p per share as shareholders elected to reinvest their dividend under the company's dividend reinvestment scheme. | L87: 2025/26 | Q87: 0.26610433
A88: 2026 | B88: Mar | C88: Issue (DRIS) | D88: Puma VCT 13 | E88: Puma Investments | F88: VCT | G88: The company raised £637,819 by way of an issue of 542,225 shares at a price of 117.63p per share as shareholders elected to reinvest their dividend under the company's dividend reinvestment scheme. | L88: 2025/26 | Q88: 0.63781927
A89: 2026 | B89: Mar | C89: Issue (DRIS) | D89: Triple Point Venture VCT Venture shares | E89: Triple Point Investment Management | F89: VCT | G89: The company raised £385,102 by way of an issue of 424,729 shares at a price of 90.67p per share as shareholders elected to reinvest their dividend under the company's dividend reinvestment scheme. | L89: 2025/26 | Q89: 0.38510178
A90: 2026 | B90: Mar | C90: Issue (DRIS) | D90: Unicorn AIM VCT | E90: Unicorn Asset Management | F90: VCT AIM Quoted | G90: The company raised £8,651,725 by way of an issue of 10,667,972 shares at a price of 81.1p per share as shareholders elected to reinvest their dividend under the company's dividend reinvestment scheme. | L90: 2025/26 | Q90: 8.6517253
A91: 2026 | B91: Apr | C91: Buyback | D91: Albion Crown VCT | E91: Albion Capital | F91: VCT | G91: The company returned £1,327,855 to shareholders by way of a buyback of 4,764,461 ordinary shares at a price of 132.79p per share. | Q91: -1.3278553
A92: 2026 | B92: Apr | C92: Buyback | D92: Calculus VCT | E92: Calculus Capital/Investec Structured Products | F92: VCT | G92: The company returned £378,617 to shareholders by way of a buyback of 722,000 ordinary shares at a price of 37.86p per share. | Q92: -0.3786168
A93: 2026 | B93: Apr | C93: Buyback | D93: Foresight VCT | E93: Foresight Group | F93: VCT | G93: The company returned £2,039,334 to shareholders by way of a buyback of 3,079,170 ordinary shares at a price of 203.93p per share. | Q93: -2.0393343
A94: 2026 | B94: Apr | C94: Buyback | D94: Hargreave Hale AIM VCT | E94: Hargreave Hale | F94: VCT AIM Quoted | G94: The company returned £69,952 to shareholders by way of a buyback of 228,376 ordinary shares at a price of 7.p per share. | Q94: -0.069951569
A95: 2026 | B95: Apr | C95: Buyback | D95: Hargreave Hale AIM VCT | E95: Hargreave Hale | F95: VCT AIM Quoted | G95: The company returned £103,900 to shareholders by way of a buyback of 338,216 ordinary shares at a price of 10.39p per share. | Q95: -0.10389996
A96: 2026 | B96: Apr | C96: Buyback | D96: Maven Renovar VCT | E96: Maven Capital Partners | F96: VCT AIM Quoted | G96: The company returned £38,737 to shareholders by way of a buyback of 72,001 ordinary shares at a price of 3.87p per share. | Q96: -0.038736538
A97: 2026 | B97: Apr | C97: Buyback | D97: Maven Renovar VCT | E97: Maven Capital Partners | F97: VCT AIM Quoted | G97: The company returned £27,611 to shareholders by way of a buyback of 53,613 ordinary shares at a price of 2.76p per share. | Q97: -0.027610695
A98: 2026 | B98: Apr | C98: Buyback | D98: Octopus AIM VCT | E98: Octopus Investments | F98: VCT AIM Quoted | G98: The company returned £494,775 to shareholders by way of a buyback of 1,243,434 ordinary shares at a price of 49.48p per share. | Q98: -0.49477482
A99: 2026 | B99: Apr | C99: Buyback | D99: Octopus AIM VCT 2 | E99: Octopus Investments | F99: VCT AIM Quoted | G99: The company returned £215,583 to shareholders by way of a buyback of 678,509 ordinary shares at a price of 21.56p per share. | Q99: -0.21558266
A100: 2026 | B100: Apr | C100: Buyback | D100: Octopus Apollo VCT | E100: Octopus Investments | F100: VCT | G100: The company returned £9,217,129 to shareholders by way of a buyback of 19,620,096 ordinary shares at a price of 921.71p per share. | Q100: -9.2171287
A101: 2026 | B101: Apr | C101: Buyback | D101: Pembroke VCT B shares | E101: Pembroke Investment Managers | F101: VCT | G101: The company returned £6,609,510 to shareholders by way of a buyback of 7,233,786 ordinary shares at a price of 660.95p per share. | Q101: -6.6095103
A102: 2026 | B102: Apr | C102: Closed offer for subscription | D102: Octopus AIM VCT | E102: Octopus Investments | F102: VCT AIM Quoted | G102: The company raised £30,000,000 by way of an offer for subscription of shares. The offer opened on 12/01/2026 and closed on 05/04/2026. | K102: 46034 | L102: 2025/26 | M102: 30 | P102: 46117 | Q102: 30
A103: 2026 | B103: Apr | C103: Closed offer for subscription | D103: Octopus AIM VCT 2 | E103: Octopus Investments | F103: VCT AIM Quoted | G103: The company raised £30,000,000 by way of an offer for subscription of shares. The offer opened on 12/01/2026 and closed on 05/04/2026. | K103: 46034 | L103: 2025/26 | M103: 30 | P103: 46117 | Q103: 30
A104: 2026 | B104: Apr | C104: Closed offer for subscription | D104: Triple Point Venture VCT Venture shares | E104: Triple Point Investment Management | F104: VCT | G104: The company raised £7,385,030 by way of an open offer for subscription of shares. The offer opened on 09/10/2025 and closed on 11/04/2026. | H104: 10 | I104: 35 | J104: Y | K104: 45939 | L104: 2025/26 | M104: 7.0920736 | N104: 2026/27 | O104: 0.29295635 | P104: 46234 | Q104: 7.38503
A105: 2026 | B105: Apr | C105: Issue | D105: Guinness VCT | E105: Guinness Global Investors | F105: VCT | G105: The company raised £10,001 by way of an allotment of 10,121 shares at an average price of 98.81p as part of their open offer for subscription for the 2026/27 tax year. | N105: 2026/27 | Q105: 0.01000056
A106: 2026 | B106: Apr | C106: Issue | D106: Hargreave Hale AIM VCT | E106: Hargreave Hale | F106: VCT AIM Quoted | G106: The company raised £257,202 by way of an allotment of 789,933 shares at an average price of 32.56p as part of their open offer for subscription for the 2026/27 tax year. | N106: 2026/27 | Q106: 0.25720218
A107: 2026 | B107: Apr | C107: Issue | D107: Maven Income and Growth VCT | E107: Maven Capital Partners | F107: VCT | G107: The company raised £324,192 by way of an allotment of 879,761 shares at an average price of 36.85p as part of their open offer for subscription for the 2026/27 tax year. | N107: 2026/27 | Q107: 0.32419193
A108: 2026 | B108: Apr | C108: Issue | D108: Maven Income and Growth VCT | E108: Maven Capital Partners | F108: VCT | G108: The company raised £92,205 by way of an allotment of 248,463 shares at an average price of 37.11p as part of their open offer for subscription for the 2026/27 tax year. | N108: 2026/27 | Q108: 0.092204619
A109: 2026 | B109: Apr | C109: Issue | D109: Maven Income and Growth VCT 3 | E109: Maven Capital Partners | F109: VCT | G109: The company raised £190,183 by way of an allotment of 401,061 shares at an average price of 47.42p as part of their open offer for subscription for the 2026/27 tax year. | N109: 2026/27 | Q109: 0.19018313
A110: 2026 | B110: Apr | C110: Issue | D110: Maven Income and Growth VCT 3 | E110: Maven Capital Partners | F110: VCT | G110: The company raised £144,000 by way of an allotment of 300,000 shares at an average price of 48.p as part of their open offer for subscription for the 2026/27 tax year. | N110: 2026/27 | Q110: 0.144
A111: 2026 | B111: Apr | C111: Issue | D111: Maven Income and Growth VCT 3 | E111: Maven Capital Partners | F111: VCT | G111: The company raised £68,713 by way of an allotment of 145,672 shares at an average price of 47.17p as part of their open offer for subscription for the 2026/27 tax year. | N111: 2026/27 | Q111: 0.068713482
A112: 2026 | B112: Apr | C112: Issue | D112: Maven Income and Growth VCT 4 | E112: Maven Capital Partners | F112: VCT | G112: The company raised £170,944 by way of an allotment of 314,930 shares at an average price of 54.28p as part of their open offer for subscription for the 2026/27 tax year. | N112: 2026/27 | Q112: 0.170944
A113: 2026 | B113: Apr | C113: Issue | D113: Maven Income and Growth VCT 4 | E113: Maven Capital Partners | F113: VCT | G113: The company raised £56,204 by way of an allotment of 103,927 shares at an average price of 54.08p as part of their open offer for subscription for the 2026/27 tax year. | N113: 2026/27 | Q113: 0.056203722
A114: 2026 | B114: Apr | C114: Issue | D114: Maven Income and Growth VCT 5 | E114: Maven Capital Partners | F114: VCT | G114: The company raised £329,712 by way of an allotment of 1,064,275 shares at an average price of 30.98p as part of their open offer for subscription for the 2026/27 tax year. | N114: 2026/27 | Q114: 0.32971239
A115: 2026 | B115: Apr | C115: Issue | D115: Molten Ventures VCT | E115: Molten Ventures | F115: VCT | G115: The company raised £187,037 by way of an allotment of 455,854 shares at an average price of 41.03p as part of their open offer for subscription for the 2026/27 tax year. | N115: 2026/27 | Q115: 0.1870369
A116: 2026 | B116: Apr | C116: Issue | D116: Pembroke VCT B shares | E116: Pembroke Investment Managers | F116: VCT | G116: The company raised £497,864 by way of an allotment of 496,870 shares at an average price of 100.2p as part of their open offer for subscription for the 2026/27 tax year. | N116: 2026/27 | Q116: 0.49786374
...

Sheet Definitions
A1: Please note that there are five tabs included in this document: Conventional, Issuance, Buybacks, VCT and Definitions
A3: Event | B3: Use
A4: Buyback | B4: Used when a company repurchases its own shares through on-market purchases or other buyback mechanisms.
A5: Capital Change | B5: Used for share splits and consolidations as well as bonus issues of subscription shares.
A6: Capital Distribution | B6: Used for the distribution of capital by way of an issue and subsequent repurchase of B shares.
A7: Capital Redemption | B7: Used to record when capital is returned to shareholders by way of a voluntary or compulsory redemptions of shares (may be part of a regular redemption policy).
A8: Capital Reorganisation | B8: Primarily used for the departure of pools or additional share classes not covered elsewhere.
A9: Capital Reorganisation/Depart | B9: A final redemption of ZDP shares.
A10: Capital Reorganisation/Issue | B10: Used for issues of new ZDP shares.
A11: Closed offer for subscription | B11: Used to record the closure of a subscription offer period, after which no further applications for shares may be accepted. (VCT only)
A12: Convert | B12: Used for a conversion of C shares.
A13: Depart/Liquidate | B13: Used for a company who is liquidating in its entirety and returning all cash to shareholders.
A14: Domicile Change | B14: For when a company changes domicile.
... A48: Trading status | B48: Denotes a change in trading status, either a suspension or a suspension being lifted.
